Workbook

Sheet NONO
A2: Nono
B3: Number of units
C4: MW | D4: WE | E4: MW | F4: WE | G4: MW | H4: WE | I4: MW | J4: WE | K4: MW | L4: WE | M4: MW | N4: WE | O4: MW | P4: WE | Q4: MW | R4: WE | S4: MW | T4: WE | U4: MW | V4: WE | W4: MW | X4: WE | Y4: MW | Z4: WE
C5: Jan | E5: Feb | G5: Mar | I5: Apr | K5: May | M5: June | O5: July | Q5: August | S5: September | U5: October | W5: November | Y5: December
A6: Average Occupancy | C6: =C22 -> 0.58548387 | E6: =E22 -> 0.65714286 | G6: =G22 -> 0.74354839 | I6: =I22 -> 0.82 | K6: =K22 -> 0.8283871 | M6: =M22 -> 0.801 | O6: =O22 -> 0.85032258 | Q6: =Q22 -> 0.86451613 | S6: =S22 -> 0.835 | U6: =U22 -> 0.77709677 | W6: =W22 -> 0.68333333 | Y6: =Y22 -> 0.68
A7: Average Occupancy per Midweek and weekend (or special dates and holidays) | C7: 0.55 | D7: 0.65 | E7: 0.62 | F7: 0.75 | G7: 0.7 | H7: 0.85 | I7: 0.78 | J7: 0.88 | K7: 0.8 | L7: 0.88 | M7: 0.78 | N7: 0.85 | O7: 0.83 | P7: 0.9 | Q7: 0.85 | R7: 0.9 | S7: 0.82 | T7: 0.87 | U7: 0.75 | V7: 0.82 | W7: 0.65 | X7: 0.75 | Y7: 0.6 | Z7: 0.8
A8: Number of days per midweek/weekend Price | C8: 20 | D8: 11 | E8: 20 | F8: 8 | G8: 22 | H8: 9 | I8: 18 | J8: 12 | K8: 20 | L8: 11 | M8: 21 | N8: 9 | O8: 22 | P8: 9 | Q8: 22 | R8: 9 | S8: 21 | T8: 9 | U8: 19 | V8: 12 | W8: 20 | X8: 10 | Y8: 18 | Z8: 12
A9: Studio | B9: 22 | C9: 80 | D9: 100 | E9: 85 | F9: 110 | G9: 110 | H9: 135 | I9: 125 | J9: 150 | K9: 125 | L9: 150 | M9: 120 | N9: 140 | O9: 125 | P9: 145 | Q9: 150 | R9: 160 | S9: 130 | T9: 150 | U9: 120 | V9: 145 | W9: 105 | X9: 125 | Y9: 85 | Z9: 140
A10: Studio French Balcony | B10: 13 | C10: =C9*1.05 -> 84 | D10: =D9*1.15 -> 115 | E10: =E9*1.05 -> 89.25 | F10: =F9*1.15 -> 126.5 | G10: =G9*1.05 -> 115.5 | H10: =H9*1.15 -> 155.25 | I10: =I9*1.05 -> 131.25 | J10: =J9*1.15 -> 172.5 | K10: =K9*1.05 -> 131.25 | L10: =L9*1.15 -> 172.5 | M10: =M9*1.05 -> 126 | N10: =N9*1.15 -> 161 | O10: =O9*1.05 -> 131.25 | P10: =P9*1.15 -> 166.75 | Q10: =Q9*1.05 -> 157.5 | R10: =R9*1.15 -> 184 | S10: =S9*1.05 -> 136.5 | T10: =T9*1.15 -> 172.5 | U10: =U9*1.05 -> 126 | V10: =V9*1.15 -> 166.75 | W10: =W9*1.05 -> 110.25 | X10: =X9*1.15 -> 143.75 | Y10: =Y9*1.05 -> 89.25 | Z10: =Z9*1.15 -> 161
A11: Superior Studio | B11: 2 | C11: =C9*1.15 -> 92 | D11: =D9*1.15 -> 115 | E11: =E9*1.15 -> 97.75 | F11: =F9*1.15 -> 126.5 | G11: =G9*1.15 -> 126.5 | H11: =H9*1.15 -> 155.25 | I11: =I9*1.15 -> 143.75 | J11: =J9*1.15 -> 172.5 | ... Z11: =Z9*1.15 -> 161
A12: Studio with Terrace | B12: 4 | C12: =C9*1.15 -> 92 | D12: =D9*1.15 -> 115 | E12: =E9*1.15 -> 97.75 | F12: =F9*1.15 -> 126.5 | G12: =G9*1.2 -> 132 | H12: =H9*1.2 -> 162 | I12: =I9*1.25 -> 156.25 | J12: =J9*1.25 -> 187.5 | K12: =K9*1.25 -> 156.25 | L12: =L9*1.25 -> 187.5 | M12: =M9*1.25 -> 150 | N12: =N9*1.25 -> 175 | O12: =O9*1.25 -> 156.25 | P12: =P9*1.25 -> 181.25 | ... T12: =T9*1.25 -> 187.5 | U12: =U9*1.2 -> 144 | V12: =V9*1.2 -> 174 | W12: =W9*1.15 -> 120.75 | X12: =X9*1.15 -> 143.75 | Y12: =Y9*1.15 -> 97.75 | Z12: =Z9*1.15 -> 161
A13: Triple Studio | B13: 4 | C13: =C9*1.12 -> 89.6 | D13: =D9*1.12 -> 112 | E13: =E9*1.12 -> 95.2 | F13: =F9*1.12 -> 123.2 | G13: =G9*1.12 -> 123.2 | H13: =H9*1.12 -> 151.2 | I13: =I9*1.12 -> 140 | J13: =J9*1.12 -> 168 | ... Z13: =Z9*1.12 -> 156.8
A14: One Bedroom Apartment | B14: 5 | C14: =C9*1.3 -> 104 | D14: =D9*1.3 -> 130 | E14: =E9*1.3 -> 110.5 | F14: =F9*1.3 -> 143 | G14: =G9*1.3 -> 143 | H14: =H9*1.3 -> 175.5 | I14: =I9*1.3 -> 162.5 | J14: =J9*1.3 -> 195 | ... Z14: =Z9*1.3 -> 182
A15: One Bedroom Terrace | B15: 4 | C15: =C9*1.4 -> 112 | D15: =D9*1.4 -> 140 | E15: =E9*1.4 -> 119 | F15: =F9*1.4 -> 154 | G15: =G9*1.4 -> 154 | H15: =H9*1.4 -> 189 | I15: =I9*1.4 -> 175 | J15: =J9*1.4 -> 210 | ... Z15: =Z9*1.4 -> 196
A16: Two Bedroom Terrace | B16: 2 | C16: =C9*1.65 -> 132 | D16: =D9*1.65 -> 165 | E16: =E9*1.65 -> 140.25 | F16: =F9*1.65 -> 181.5 | G16: =G9*1.65 -> 181.5 | H16: =H9*1.65 -> 222.75 | I16: =I9*1.75 -> 218.75 | J16: =J9*1.75 -> 262.5 | K16: =K9*1.75 -> 218.75 | L16: =L9*1.75 -> 262.5 | M16: =M9*1.75 -> 210 | N16: =N9*1.75 -> 245 | O16: =O9*1.75 -> 218.75 | P16: =P9*1.75 -> 253.75 | ... R16: =R9*1.75 -> 280 | S16: =S9*1.65 -> 214.5 | T16: =T9*1.65 -> 247.5 | U16: =U9*1.65 -> 198 | V16: =V9*1.65 -> 239.25 | W16: =W9*1.65 -> 173.25 | X16: =X9*1.65 -> 206.25 | Y16: =Y9*1.65 -> 140.25 | Z16: =Z9*1.65 -> 231
B17: 56 | C17: =($B9*C9*C8*C7)+($B10*C10*C8*C7)+($B11*C11*C8*C7)+($B12*C12*C8*C7)+($B13*C13*C8*C7)+($B14*C14*C8*C7)+($B15*C15*C8*C7)+($B16+C16+C8*C7) -> 52179.4 | D17: =($B9*D9*D8*D7)+($B10*D10*D8*D7)+($B11*D11*D8*D7)+($B12*D12*D8*D7)+($B13*D13*D8*D7)+($B14*D14*D8*D7)+($B15*D15*D8*D7)+($B16+D16+D8*D7) -> 43381.6 | E17: =($B9*E9*E8*E7)+($B10*E10*E8*E7)+($B11*E11*E8*E7)+($B12*E12*E8*E7)+($B13*E13*E8*E7)+($B14*E14*E8*E7)+($B15*E15*E8*E7)+($B16+E16+E8*E7) -> 62477.67 | F17: =($B9*F9*F8*F7)+($B10*F10*F8*F7)+($B11*F11*F8*F7)+($B12*F12*F8*F7)+($B13*F13*F8*F7)+($B14*F14*F8*F7)+($B15*F15*F8*F7)+($B16+F16+F8*F7) -> 40073.3 | G17: =($B9*G9*G8*G7)+($B10*G10*G8*G7)+($B11*G11*G8*G7)+($B12*G12*G8*G7)+($B13*G13*G8*G7)+($B14*G14*G8*G7)+($B15*G15*G8*G7)+($B16+G16+G8*G7) -> 100703.92 | H17: =($B9*H9*H8*H7)+($B10*H10*H8*H7)+($B11*H11*H8*H7)+($B12*H12*H8*H7)+($B13*H13*H8*H7)+($B14*H14*H8*H7)+($B15*H15*H8*H7)+($B16+H16+H8*H7) -> 62848.033 | I17: =($B9*I9*I8*I7)+($B10*I10*I8*I7)+($B11*I11*I8*I7)+($B12*I12*I8*I7)+($B13*I13*I8*I7)+($B14*I14*I8*I7)+($B15*I15*I8*I7)+($B16+I16+I8*I7) -> 104709.94 | J17: =($B9*J9*J8*J7)+($B10*J10*J8*J7)+($B11*J11*J8*J7)+($B12*J12*J8*J7)+($B13*J13*J8*J7)+($B14*J14*J8*J7)+($B15*J15*J8*J7)+($B16+J16+J8*J7) -> 96629.78 | ... Z17: =($B9*Z9*Z8*Z7)+($B10*Z10*Z8*Z7)+($B11*Z11*Z8*Z7)+($B12*Z12*Z8*Z7)+($B13*Z13*Z8*Z7)+($B14*Z14*Z8*Z7)+($B15*Z15*Z8*Z7)+($B16+Z16+Z8*Z7) -> 81460.52
C19: =C17+D17 -> 95561 | E19: =E17+F17 -> 102550.97 | G19: =G17+H17 -> 163551.95 | I19: =I17+J17 -> 201339.72 | K19: =K17+L17 -> 207896.09 | M19: =M17+N17 -> 182644.13 | O19: =O17+P17 -> 207824.92 | Q19: =Q17+R17 -> 246390.63 | S19: =S17+T17 -> 205199.74 | U19: =U17+V17 -> 188426.52 | W19: =W17+X17 -> 137769.58 | Y19: =Y17+Z17 -> 135894.91
B20: Occupancy Yearly | C20: =(C7*C8+D7*D8) -> 18.15 | E20: =(E7*E8+F7*F8) -> 18.4 | G20: =(G7*G8+H7*H8) -> 23.05 | I20: =(I7*I8+J7*J8) -> 24.6 | K20: =(K7*K8+L7*L8) -> 25.68 | M20: =(M7*M8+N7*N8) -> 24.03 | O20: =(O7*O8+P7*P8) -> 26.36 | Q20: =(Q7*Q8+R7*R8) -> 26.8 | S20: =(S7*S8+T7*T8) -> 25.05 | U20: =(U7*U8+V7*V8) -> 24.09 | W20: =(W7*W8+X7*X8) -> 20.5 | Y20: =(Y7*Y8+Z7*Z8) -> 20.4
C21: =C8+D8 -> 31 | E21: =E8+F8 -> 28 | G21: =G8+H8 -> 31 | I21: =I8+J8 -> 30 | K21: =K8+L8 -> 31 | M21: =M8+N8 -> 30 | O21: =O8+P8 -> 31 | Q21: =Q8+R8 -> 31 | S21: =S8+T8 -> 30 | U21: =U8+V8 -> 31 | W21: =W8+X8 -> 30 | Y21: =Y8+Z8 -> 30
C22: =C20/C21 -> 0.58548387 | E22: =E20/E21 -> 0.65714286 | G22: =G20/G21 -> 0.74354839 | I22: =I20/I21 -> 0.82 | K22: =K20/K21 -> 0.8283871 | M22: =M20/M21 -> 0.801 | O22: =O20/O21 -> 0.85032258 | Q22: =Q20/Q21 -> 0.86451613 | S22: =S20/S21 -> 0.835 | U22: =U20/U21 -> 0.77709677 | W22: =W20/W21 -> 0.68333333 | Y22: =Y20/Y21 -> 0.68
B23: =C22*C21+E22*E21+G22*G21+I22*I21+K22*K21+M22*M21+O22*O21+Q22*Q21+S22*S21+U22*U21+W22*W21+Y22*Y21 -> 277.11 | C23: =B23/365 -> 0.75920548
A24: MONTHLY ADR | C24: =C19/(C21*$B$17*C6) -> 94.019087 | E24: =E19/(E21*$B$17*E6) -> 99.525398 | G24: =G19/(G21*$B$17*G6) -> 126.70588 | I24: =I19/(I21*$B$17*I6) -> 146.15253 | K24: =K19/(K21*$B$17*K6) -> 144.56504 | M24: =M19/(M21*$B$17*M6) -> 135.72627 | O24: =O19/(O21*$B$17*O6) -> 140.78753 | Q24: =Q19/(Q21*$B$17*Q6) -> 164.17286 | S24: =S19/(S21*$B$17*S6) -> 146.27869 | U24: =U19/(U21*$B$17*U6) -> 139.67453 | W24: =W19/(W21*$B$17*W6) -> 120.00834 | Y24: =Y19/(Y21*$B$17*Y6) -> 118.95563
A28: INCOME YEARLY | B28: =SUM(C19:Z19) -> 2075050.2 | D28: Euros | F28: =+B28/1.1 -> 1886409.2
A29: OCC YEARLY | C29: =C23 -> 0.75920548
A30: ADR YEARLY | C30: =AVERAGE(C24:Z24) -> 131.38098
A32: Figures incl VAT | C32: =+C30/1.1 -> 119.43726
C34: 140 | D34: =+(C32/$C$34)-1 -> -0.14687674
C36: 133 | D36: =+(C32/$C$36)-1 -> -0.10197552

Sheet Lease option 1
C4: Inv x Space | H4: Units | I4: Inv. x unit | K4: Total inv .
C6: 35000 | F6: Common areas | H6: 1 | I6: =+C6 -> 35000 | K6: =+C6*H6 -> 35000
C7: 5000 | F7: Studio | H7: 22 | I7: =+C7 -> 5000 | K7: =+C7*H7 -> 110000
C8: 5500 | F8: Studio French Balcony | H8: 13 | I8: =+C8 -> 5500 | K8: =+C8*H8 -> 71500
C9: 6000 | F9: Superior Studio | H9: 2 | I9: =+C9 -> 6000 | K9: =+C9*H9 -> 12000
C10: 7000 | F10: Studio with Terrace | H10: 4 | I10: =+C10 -> 7000 | K10: =+C10*H10 -> 28000
C11: 7000 | F11: Triple Studio | H11: 4 | I11: =+C11 -> 7000 | K11: =+C11*H11 -> 28000
C12: 7000 | F12: One Bedroom Apartment | H12: 5 | I12: =+C12 -> 7000 | K12: =+C12*H12 -> 35000
C13: 7000 | F13: One Bedroom Terrace | H13: 4 | I13: =+C13 -> 7000 | K13: =+C13*H13 -> 28000
C14: 8000 | F14: Two Bedroom Terrace | H14: 2 | I14: =+C14 -> 8000 | K14: =+C14*H14 -> 16000
F16: Total investment | K16: =+SUM(K6:K14) -> 363500
F19: Template | H19: Peña | K19: 140.9 | L19: 154.1 | M19: 169.5 | N19: =+M19*(1+$H$27) -> 174.585 | O19: =+N19*(1+$H$27) -> 179.82255 | P19: =+O19*(1+$H$27) -> 185.21723 | Q19: =+P19*(1+$H$27) -> 190.77374 | R19: =+Q19*(1+$H$27) -> 196.49696 | S19: =+R19*(1+$H$27) -> 202.39186 | T19: =+S19*(1+$H$27) -> 208.46362
H21: Fix min. Lease x apartment | K21: 1300 | L21: 1400 | M21: 1500 | N21: =+M21*(1+SUM($H$27)) -> 1545 | O21: =+N21*(1+SUM($H$27)) -> 1591.35 | P21: =+O21*(1+SUM($H$27)) -> 1639.0905 | Q21: =+P21*(1+SUM($H$27)) -> 1688.2632 | R21: =+Q21*(1+SUM($H$27)) -> 1738.9111 | S21: =+R21*(1+SUM($H$27)) -> 1791.0784 | T21: =+S21*(1+SUM($H$27)) -> 1844.8108
H22: /rev | K22: =+K57/K47 -> 0.38528283 | L22: =+L57/L47 -> 0.37639314 | M22: =+M57/M47 -> 0.37419012 | N22: =+N57/N47 -> 0.36801915 | O22: =+O57/O47 -> 0.36100926 | P22: =+P57/P47 -> 0.35413289 | Q22: =+Q57/Q47 -> 0.34648466 | R22: =+R57/R47 -> 0.3407706 | ... T22: =+T57/T47 -> 0.3279125
H24: Variable lease | K24: 0.37 | L24: 0.38 | M24: 0.4 | N24: 0.41 | O24: 0.41 | P24: 0.365 | Q24: 0.365 | R24: 0.365 | S24: 0.365 | T24: 0.365
F27: IPC | H27: 0.03
F28: GROWTH | H28: 0.02
K32: 2026 | L32: 2027 | M32: 2028 | N32: 2029 | O32: 2030 | P32: 2031 | Q32: 2032 | R32: 2033 | S32: 2034 | T32: 2035
F34: % Average occupancy | K34: 0.76 | L34: 0.8 | M34: 0.82 | N34: 0.82 | O34: 0.82 | P34: 0.82 | Q34: 0.82 | R34: 0.82 | S34: 0.82 | T34: 0.82 | W34: =+AVERAGE(K34:T34) -> 0.812
F35: Number of opened days | K35: 365 | L35: 365 | M35: 366 | N35: 365 | O35: 365 | P35: 365 | Q35: 366 | R35: 365 | S35: 365 | T35: 365
F36: Units | K36: 56 | L36: 56 | M36: 56 | N36: 56 | O36: 56 | P36: 56 | Q36: 56 | R36: 56 | S36: 56 | T36: 56
B37: Asaf Assumption | C37: 119.43726 | F37: ADR | K37: =+($H$38*K38+$H$39*K39+$H$40*K40+$H$41*K41+$H$42*K42+$H$43*K43+$H$44*K44+$H$45*K45)/SUM($H$38:$H$45) -> 138.28827 | L37: =+($H$38*L38+$H$39*L39+$H$40*L40+$H$41*L41+$H$42*L42+$H$43*L43+$H$44*L44+$H$45*L45)/SUM($H$38:$H$45) -> 145.20268 | M37: =+($H$38*M38+$H$39*M39+$H$40*M40+$H$41*M41+$H$42*M42+$H$43*M43+$H$44*M44+$H$45*M45)/SUM($H$38:$H$45) -> 152.46281 | N37: =+($H$38*N38+$H$39*N39+$H$40*N40+$H$41*N41+$H$42*N42+$H$43*N43+$H$44*N44+$H$45*N45)/SUM($H$38:$H$45) -> 160.08595 | O37: =+($H$38*O38+$H$39*O39+$H$40*O40+$H$41*O41+$H$42*O42+$H$43*O43+$H$44*O44+$H$45*O45)/SUM($H$38:$H$45) -> 168.09025 | P37: =+($H$38*P38+$H$39*P39+$H$40*P40+$H$41*P41+$H$42*P42+$H$43*P43+$H$44*P44+$H$45*P45)/SUM($H$38:$H$45) -> 176.49476 | Q37: =+($H$38*Q38+$H$39*Q39+$H$40*Q40+$H$41*Q41+$H$42*Q42+$H$43*Q43+$H$44*Q44+$H$45*Q45)/SUM($H$38:$H$45) -> 185.3195 | R37: =+($H$38*R38+$H$39*R39+$H$40*R40+$H$41*R41+$H$42*R42+$H$43*R43+$H$44*R44+$H$45*R45)/SUM($H$38:$H$45) -> 194.58548 | ... T37: =+($H$38*T38+$H$39*T39+$H$40*T40+$H$41*T41+$H$42*T42+$H$43*T43+$H$44*T44+$H$45*T45)/SUM($H$38:$H$45) -> 214.53049 | W37: =+AVERAGE(K37:T37) -> 173.93749
F38: Studio | H38: 22 | K38: 115 | L38: =+K38*(1+SUM($H$27:$H$28)) -> 120.75 | M38: =+L38*(1+SUM($H$27:$H$28)) -> 126.7875 | N38: =+M38*(1+SUM($H$27:$H$28)) -> 133.12688 | O38: =+N38*(1+SUM($H$27:$H$28)) -> 139.78322 | P38: =+O38*(1+SUM($H$27:$H$28)) -> 146.77238 | Q38: =+P38*(1+SUM($H$27:$H$28)) -> 154.111 | R38: =+Q38*(1+SUM($H$27:$H$28)) -> 161.81655 | S38: =+R38*(1+SUM($H$27:$H$28)) -> 169.90738 | T38: =+S38*(1+SUM($H$27:$H$28)) -> 178.40274
F39: Studio French Balcony | H39: 13 | K39: 135 | L39: =+K39*(1+SUM($H$27:$H$28)) -> 141.75 | M39: =+L39*(1+SUM($H$27:$H$28)) -> 148.8375 | N39: =+M39*(1+SUM($H$27:$H$28)) -> 156.27938 | O39: =+N39*(1+SUM($H$27:$H$28)) -> 164.09334 | P39: =+O39*(1+SUM($H$27:$H$28)) -> 172.29801 | Q39: =+P39*(1+SUM($H$27:$H$28)) -> 180.91291 | R39: =+Q39*(1+SUM($H$27:$H$28)) -> 189.95856 | S39: =+R39*(1+SUM($H$27:$H$28)) -> 199.45648 | T39: =+S39*(1+SUM($H$27:$H$28)) -> 209.42931
F40: Superior Studio | H40: 2 | K40: 135 | L40: =+K40*(1+SUM($H$27:$H$28)) -> 141.75 | M40: =+L40*(1+SUM($H$27:$H$28)) -> 148.8375 | N40: =+M40*(1+SUM($H$27:$H$28)) -> 156.27938 | O40: =+N40*(1+SUM($H$27:$H$28)) -> 164.09334 | P40: =+O40*(1+SUM($H$27:$H$28)) -> 172.29801 | Q40: =+P40*(1+SUM($H$27:$H$28)) -> 180.91291 | R40: =+Q40*(1+SUM($H$27:$H$28)) -> 189.95856 | S40: =+R40*(1+SUM($H$27:$H$28)) -> 199.45648 | T40: =+S40*(1+SUM($H$27:$H$28)) -> 209.42931
F41: Studio with Terrace | H41: 4 | K41: 146.03571 | L41: =+K41*(1+SUM($H$27:$H$28)) -> 153.3375 | M41: =+L41*(1+SUM($H$27:$H$28)) -> 161.00438 | N41: =+M41*(1+SUM($H$27:$H$28)) -> 169.05459 | O41: =+N41*(1+SUM($H$27:$H$28)) -> 177.50732 | P41: =+O41*(1+SUM($H$27:$H$28)) -> 186.38269 | Q41: =+P41*(1+SUM($H$27:$H$28)) -> 195.70182 | R41: =+Q41*(1+SUM($H$27:$H$28)) -> 205.48692 | S41: =+R41*(1+SUM($H$27:$H$28)) -> 215.76126 | T41: =+S41*(1+SUM($H$27:$H$28)) -> 226.54932
F42: Triple Studio | H42: 4 | K42: 140 | L42: =+K42*(1+SUM($H$27:$H$28)) -> 147 | M42: =+L42*(1+SUM($H$27:$H$28)) -> 154.35 | N42: =+M42*(1+SUM($H$27:$H$28)) -> 162.0675 | O42: =+N42*(1+SUM($H$27:$H$28)) -> 170.17087 | P42: =+O42*(1+SUM($H$27:$H$28)) -> 178.67942 | Q42: =+P42*(1+SUM($H$27:$H$28)) -> 187.61339 | R42: =+Q42*(1+SUM($H$27:$H$28)) -> 196.99406 | S42: =+R42*(1+SUM($H$27:$H$28)) -> 206.84376 | T42: =+S42*(1+SUM($H$27:$H$28)) -> 217.18595
F43: One Bedroom Apartment | H43: 5 | K43: 165 | L43: =+K43*(1+SUM($H$27:$H$28)) -> 173.25 | M43: =+L43*(1+SUM($H$27:$H$28)) -> 181.9125 | N43: =+M43*(1+SUM($H$27:$H$28)) -> 191.00813 | O43: =+N43*(1+SUM($H$27:$H$28)) -> 200.55853 | P43: =+O43*(1+SUM($H$27:$H$28)) -> 210.58646 | Q43: =+P43*(1+SUM($H$27:$H$28)) -> 221.11578 | R43: =+Q43*(1+SUM($H$27:$H$28)) -> 232.17157 | S43: =+R43*(1+SUM($H$27:$H$28)) -> 243.78015 | T43: =+S43*(1+SUM($H$27:$H$28)) -> 255.96916
F44: One Bedroom Terrace | H44: 4 | K44: 190 | L44: =+K44*(1+SUM($H$27:$H$28)) -> 199.5 | M44: =+L44*(1+SUM($H$27:$H$28)) -> 209.475 | N44: =+M44*(1+SUM($H$27:$H$28)) -> 219.94875 | O44: =+N44*(1+SUM($H$27:$H$28)) -> 230.94619 | P44: =+O44*(1+SUM($H$27:$H$28)) -> 242.4935 | Q44: =+P44*(1+SUM($H$27:$H$28)) -> 254.61817 | R44: =+Q44*(1+SUM($H$27:$H$28)) -> 267.34908 | S44: =+R44*(1+SUM($H$27:$H$28)) -> 280.71653 | T44: =+S44*(1+SUM($H$27:$H$28)) -> 294.75236
F45: Two Bedroom Terrace | H45: 2 | K45: 230 | L45: =+K45*(1+SUM($H$27:$H$28)) -> 241.5 | M45: =+L45*(1+SUM($H$27:$H$28)) -> 253.575 | N45: =+M45*(1+SUM($H$27:$H$28)) -> 266.25375 | O45: =+N45*(1+SUM($H$27:$H$28)) -> 279.56644 | P45: =+O45*(1+SUM($H$27:$H$28)) -> 293.54476 | Q45: =+P45*(1+SUM($H$27:$H$28)) -> 308.222 | R45: =+Q45*(1+SUM($H$27:$H$28)) -> 323.6331 | S45: =+R45*(1+SUM($H$27:$H$28)) -> 339.81475 | T45: =+S45*(1+SUM($H$27:$H$28)) -> 356.80549
F47: Revenue | K47: =+SUM(K48:K51) -> 2267425.2 | L47: =+SUM(L48:L51) -> 2499514.2 | M47: =+SUM(M48:M51) -> 2693817.8 | N47: =+SUM(N48:N51) -> 2821157.5 | O47: =+SUM(O48:O51) -> 2962215.4 | P47: =+SUM(P48:P51) -> 3110326.2 | Q47: =+SUM(Q48:Q51) -> 3274352.4 | R47: =+SUM(R48:R51) -> 3429134.6 | ... T47: =+SUM(T48:T51) -> 3780620.9 | W47: =+SUM(K47:T47) -> 30439156
F48: Bed revenue | K48: =+K34*K35*K36*K37 -> 2148225.2 | L48: =+L34*L35*L36*L37 -> 2374354.2 | M48: =+M34*M35*M36*M37 -> 2562399.8 | N48: =+N34*N35*N36*N37 -> 2683168.6 | O48: =+O34*O35*O36*O37 -> 2817327.1 | P48: =+P34*P35*P36*P37 -> 2958193.4 | Q48: =+Q34*Q35*Q36*Q37 -> 3114613 | R48: =+R34*R35*R36*R37 -> 3261408.3 | ... T48: =+T34*T35*T36*T37 -> 3595702.6
F49: F&B Bartola | H49: 9333.3333 | K49: =+H49*12 -> 112000 | L49: =+K49*(1+SUM($H$27:$H$28)) -> 117600 | M49: =+L49*(1+SUM($H$27:$H$28)) -> 123480 | N49: =+M49*(1+SUM($H$27:$H$28)) -> 129654 | O49: =+N49*(1+SUM($H$27:$H$28)) -> 136136.7 | P49: =+O49*(1+SUM($H$27:$H$28)) -> 142943.54 | Q49: =+P49*(1+SUM($H$27:$H$28)) -> 150090.71 | R49: =+Q49*(1+SUM($H$27:$H$28)) -> 157595.25 | S49: =+R49*(1+SUM($H$27:$H$28)) -> 165475.01 | T49: =+S49*(1+SUM($H$27:$H$28)) -> 173748.76
F50: Experiences | H50: 300 | K50: =+H50*12 -> 3600 | L50: =+K50*(1+SUM($H$27:$H$28)) -> 3780 | M50: =+L50*(1+SUM($H$27:$H$28)) -> 3969 | N50: =+M50*(1+SUM($H$27:$H$28)) -> 4167.45 | O50: =+N50*(1+SUM($H$27:$H$28)) -> 4375.8225 | P50: =+O50*(1+SUM($H$27:$H$28)) -> 4594.6136 | Q50: =+P50*(1+SUM($H$27:$H$28)) -> 4824.3443 | R50: =+Q50*(1+SUM($H$27:$H$28)) -> 5065.5615 | S50: =+R50*(1+SUM($H$27:$H$28)) -> 5318.8396 | T50: =+S50*(1+SUM($H$27:$H$28)) -> 5584.7816
F51: Parking | H51: 300 | K51: =+H51*12 -> 3600 | L51: =+K51*(1+SUM($H$27:$H$28)) -> 3780 | M51: =+L51*(1+SUM($H$27:$H$28)) -> 3969 | N51: =+M51*(1+SUM($H$27:$H$28)) -> 4167.45 | O51: =+N51*(1+SUM($H$27:$H$28)) -> 4375.8225 | P51: =+O51*(1+SUM($H$27:$H$28)) -> 4594.6136 | Q51: =+P51*(1+SUM($H$27:$H$28)) -> 4824.3443 | R51: =+Q51*(1+SUM($H$27:$H$28)) -> 5065.5615 | S51: =+R51*(1+SUM($H$27:$H$28)) -> 5318.8396 | T51: =+S51*(1+SUM($H$27:$H$28)) -> 5584.7816
F53: Grace-Months | H53: =+K16/(K57/12) -> 4.9931319 | K53: =-(K21*56)*H53 -> -363500
F55: Lease to Charming Stay | K55: =+IF(K53<0,MIN(K56:K58),MAX(K56:K58)) -> 510100 | L55: =+IF(L53<0,MIN(L56:L58),MAX(L56:L58)) -> 949815.4 | M55: =+IF(M53<0,MIN(M56:M58),MAX(M56:M58)) -> 1077527.1 | N55: =+IF(N53<0,MIN(N56:N58),MAX(N56:N58)) -> 1156674.6 | O55: =+IF(O53<0,MIN(O56:O58),MAX(O56:O58)) -> 1214508.3 | P55: =+IF(P53<0,MIN(P56:P58),MAX(P56:P58)) -> 1135269.1 | Q55: =+IF(Q53<0,MIN(Q56:Q58),MAX(Q56:Q58)) -> 1195138.6 | R55: =+IF(R53<0,MIN(R56:R58),MAX(R56:R58)) -> 1251634.1 | ... T55: =+IF(T53<0,MIN(T56:T58),MAX(T56:T58)) -> 1379926.6 | W55: =+SUM(K55:T55) -> 11184810
F56: Fix minimum lease | K56: =+K57+K53 -> 510100 | L56: =+L57+L53 -> 940800 | M56: =+M57+M53 -> 1008000 | N56: =+N57+N53 -> 1038240 | O56: =+O57+O53 -> 1069387.2 | P56: =+P57+P53 -> 1101468.8 | Q56: =+Q57+Q53 -> 1134512.9 | R56: =+R57+R53 -> 1168548.3 | ... T56: =+T57+T53 -> 1239712.9
F57: Fix minimum lease | K57: =+K21*K36*12 -> 873600 | L57: =+L21*L36*12 -> 940800 | M57: =+M21*M36*12 -> 1008000 | N57: =+N21*N36*12 -> 1038240 | O57: =+O21*O36*12 -> 1069387.2 | P57: =+P21*P36*12 -> 1101468.8 | Q57: =+Q21*Q36*12 -> 1134512.9 | R57: =+R21*R36*12 -> 1168548.3 | ... T57: =+T21*T36*12 -> 1239712.9
F58: Variable lease | K58: =+K24*K47 -> 838947.33 | L58: =+L24*L47 -> 949815.4 | M58: =+M24*M47 -> 1077527.1 | N58: =+N24*N47 -> 1156674.6 | O58: =+O24*O47 -> 1214508.3 | P58: =+P24*P47 -> 1135269.1 | Q58: =+Q24*Q47 -> 1195138.6 | R58: =+R24*R47 -> 1251634.1 | ... T58: =+T24*T47 -> 1379926.6
F62: Total nights sold | H62: =+K36*K35*K34 -> 15534.4
E64: Employees | F64: Expenses | H64: Monthly | K64: =+K65+K66+K70+K74+K79+K90+K94+K95+K97+K98+K101 -> 1162180.8 | L64: =+L65+L66+L70+L74+L79+L90+L94+L95+L97+L98+L101 -> 1197046.2 | M64: =+M65+M66+M70+M74+M79+M90+M94+M95+M97+M98+M101 -> 1232957.6 | N64: =+N65+N66+N70+N74+N79+N90+N94+N95+N97+N98+N101 -> 1269946.3 | O64: =+O65+O66+O70+O74+O79+O90+O94+O95+O97+O98+O101 -> 1308044.7 | P64: =+P65+P66+P70+P74+P79+P90+P94+P95+P97+P98+P101 -> 1347286.1 | Q64: =+Q65+Q66+Q70+Q74+Q79+Q90+Q94+Q95+Q97+Q98+Q101 -> 1387704.6 | R64: =+R65+R66+R70+R74+R79+R90+R94+R95+R97+R98+R101 -> 1429335.8 | ... T64: =+T65+T66+T70+T74+T79+T90+T94+T95+T97+T98+T101 -> 1516382.3 | W64: =+SUM(K64:T64) -> 13323100 | X64: =+K64/K47 -> 0.51255528
E65: 1 | F65: Asset Manager | H65: 2750 | I65: N | K65: =+$H65*$E65*12 -> 33000 | L65: =+K65*(1+$H$27) -> 33990 | M65: =+L65*(1+$H$27) -> 35009.7 | N65: =+M65*(1+$H$27) -> 36059.991 | O65: =+N65*(1+$H$27) -> 37141.791 | P65: =+O65*(1+$H$27) -> 38256.044 | Q65: =+P65*(1+$H$27) -> 39403.726 | R65: =+Q65*(1+$H$27) -> 40585.838 | S65: =+R65*(1+$H$27) -> 41803.413 | T65: =+S65*(1+$H$27) -> 43057.515
A66: N | B66: NOMINAL | F66: Cleaning | K66: =+SUM(K67:K69) -> 286841.28 | L66: =+K66*(1+$H$27) -> 295446.52 | M66: =+L66*(1+$H$27) -> 304309.91 | N66: =+M66*(1+$H$27) -> 313439.21 | O66: =+N66*(1+$H$27) -> 322842.39 | P66: =+O66*(1+$H$27) -> 332527.66 | Q66: =+P66*(1+$H$27) -> 342503.49 | R66: =+Q66*(1+$H$27) -> 352778.59 | S66: =+R66*(1+$H$27) -> 363361.95 | T66: =+S66*(1+$H$27) -> 374262.81
A67: W | B67: WEIGHTS/REV | E67: 1 | F67: Housekeeper Payroll | H67: 2350 | I67: N | K67: =+$H67*$E67*12 -> 28200 | L67: =+K67*(1+$H$27) -> 29046 | M67: =+L67*(1+$H$27) -> 29917.38 | N67: =+M67*(1+$H$27) -> 30814.901 | O67: =+N67*(1+$H$27) -> 31739.348 | P67: =+O67*(1+$H$27) -> 32691.529 | Q67: =+P67*(1+$H$27) -> 33672.275 | R67: =+Q67*(1+$H$27) -> 34682.443 | S67: =+R67*(1+$H$27) -> 35722.916 | T67: =+S67*(1+$H$27) -> 36794.604
A68: R | B68: RATIOS | E68: 10 | F68: Cleaning cost payroll | H68: 2000 | I68: N | K68: =+$H68*$E68*12 -> 240000 | L68: =+K68*(1+$H$27) -> 247200 | M68: =+L68*(1+$H$27) -> 254616 | N68: =+M68*(1+$H$27) -> 262254.48 | O68: =+N68*(1+$H$27) -> 270122.11 | P68: =+O68*(1+$H$27) -> 278225.78 | Q68: =+P68*(1+$H$27) -> 286572.55 | R68: =+Q68*(1+$H$27) -> 295169.73 | S68: =+R68*(1+$H$27) -> 304024.82 | T68: =+S68*(1+$H$27) -> 313145.56
F69: Other cleaning + products | H69: 1.2 | I69: R | K69: =+$H69*$H$62 -> 18641.28 | L69: =+K69*(1+$H$27) -> 19200.518 | M69: =+L69*(1+$H$27) -> 19776.534 | N69: =+M69*(1+$H$27) -> 20369.83 | O69: =+N69*(1+$H$27) -> 20980.925 | P69: =+O69*(1+$H$27) -> 21610.353 | Q69: =+P69*(1+$H$27) -> 22258.663 | R69: =+Q69*(1+$H$27) -> 22926.423 | S69: =+R69*(1+$H$27) -> 23614.216 | T69: =+S69*(1+$H$27) -> 24322.642
F70: Maintenance | K70: =+SUM(K71:K73) -> 37837.04 | L70: =+K70*(1+$H$27) -> 38972.151 | M70: =+L70*(1+$H$27) -> 40141.316 | N70: =+M70*(1+$H$27) -> 41345.555 | O70: =+N70*(1+$H$27) -> 42585.922 | P70: =+O70*(1+$H$27) -> 43863.5 | Q70: =+P70*(1+$H$27) -> 45179.405 | R70: =+Q70*(1+$H$27) -> 46534.787 | S70: =+R70*(1+$H$27) -> 47930.83 | T70: =+S70*(1+$H$27) -> 49368.755
F71: Elevator maintenance | H71: 500 | I71: N | K71: =+H71*12 -> 6000 | L71: =+K71*(1+$H$27) -> 6180 | M71: =+L71*(1+$H$27) -> 6365.4 | N71: =+M71*(1+$H$27) -> 6556.362 | O71: =+N71*(1+$H$27) -> 6753.0529 | P71: =+O71*(1+$H$27) -> 6955.6444 | Q71: =+P71*(1+$H$27) -> 7164.3138 | R71: =+Q71*(1+$H$27) -> 7379.2432 | S71: =+R71*(1+$H$27) -> 7600.6205 | T71: =+S71*(1+$H$27) -> 7828.6391
E72: 1 | F72: Maintenance cost payroll | H72: 2200 | I72: N | K72: =+$H72*$E72*12 -> 26400 | L72: =+K72*(1+$H$27) -> 27192 | M72: =+L72*(1+$H$27) -> 28007.76 | N72: =+M72*(1+$H$27) -> 28847.993 | O72: =+N72*(1+$H$27) -> 29713.433 | P72: =+O72*(1+$H$27) -> 30604.836 | Q72: =+P72*(1+$H$27) -> 31522.981 | R72: =+Q72*(1+$H$27) -> 32468.67 | S72: =+R72*(1+$H$27) -> 33442.73 | T72: =+S72*(1+$H$27) -> 34446.012
F73: Maintenance expenses | H73: 0.35 | I73: R | K73: =+$H73*$H$62 -> 5437.04 | L73: =+K73*(1+$H$27) -> 5600.1512 | M73: =+L73*(1+$H$27) -> 5768.1557 | N73: =+M73*(1+$H$27) -> 5941.2004 | O73: =+N73*(1+$H$27) -> 6119.4364 | P73: =+O73*(1+$H$27) -> 6303.0195 | Q73: =+P73*(1+$H$27) -> 6492.1101 | R73: =+Q73*(1+$H$27) -> 6686.8734 | S73: =+R73*(1+$H$27) -> 6887.4796 | T73: =+S73*(1+$H$27) -> 7094.104
F74: Marketing | K74: =+SUM(K75:K78) -> 70789.631 | L74: =+K74*(1+$H$27) -> 72913.32 | M74: =+L74*(1+$H$27) -> 75100.719 | N74: =+M74*(1+$H$27) -> 77353.741 | O74: =+N74*(1+$H$27) -> 79674.353 | P74: =+O74*(1+$H$27) -> 82064.584 | Q74: =+P74*(1+$H$27) -> 84526.521 | R74: =+Q74*(1+$H$27) -> 87062.317 | S74: =+R74*(1+$H$27) -> 89674.186 | T74: =+S74*(1+$H$27) -> 92364.412
F75: Marketing Expenses | H75: 0.025 | I75: W | K75: =+$H75*K$47 -> 56685.631 | L75: =+K75*(1+$H$27) -> 58386.2 | M75: =+L75*(1+$H$27) -> 60137.786 | N75: =+M75*(1+$H$27) -> 61941.919 | O75: =+N75*(1+$H$27) -> 63800.177 | P75: =+O75*(1+$H$27) -> 65714.182 | Q75: =+P75*(1+$H$27) -> 67685.608 | R75: =+Q75*(1+$H$27) -> 69716.176 | S75: =+R75*(1+$H$27) -> 71807.661 | T75: =+S75*(1+$H$27) -> 73961.891
E76: 0.5 | F76: Experience payroll | H76: 2200 | I76: N | K76: =+$H76*$E76*12 -> 13200 | L76: =+K76*(1+$H$27) -> 13596 | M76: =+L76*(1+$H$27) -> 14003.88 | N76: =+M76*(1+$H$27) -> 14423.996 | O76: =+N76*(1+$H$27) -> 14856.716 | P76: =+O76*(1+$H$27) -> 15302.418 | Q76: =+P76*(1+$H$27) -> 15761.49 | R76: =+Q76*(1+$H$27) -> 16234.335 | S76: =+R76*(1+$H$27) -> 16721.365 | T76: =+S76*(1+$H$27) -> 17223.006
F77: Experience expenses | H77: 0.14 | I77: W/Exp. Rev | K77: =+$H77*K$50 -> 504 | L77: =+K77*(1+$H$27) -> 519.12 | M77: =+L77*(1+$H$27) -> 534.6936 | N77: =+M77*(1+$H$27) -> 550.73441 | O77: =+N77*(1+$H$27) -> 567.25644 | P77: =+O77*(1+$H$27) -> 584.27413 | Q77: =+P77*(1+$H$27) -> 601.80236 | R77: =+Q77*(1+$H$27) -> 619.85643 | S77: =+R77*(1+$H$27) -> 638.45212 | T77: =+S77*(1+$H$27) -> 657.60568
F78: Experience insurance | H78: 33.333333 | I78: N | K78: =+H78*12 -> 400 | L78: =+K78*(1+$H$27) -> 412 | M78: =+L78*(1+$H$27) -> 424.36 | N78: =+M78*(1+$H$27) -> 437.0908 | O78: =+N78*(1+$H$27) -> 450.20352 | P78: =+O78*(1+$H$27) -> 463.70963 | Q78: =+P78*(1+$H$27) -> 477.62092 | R78: =+Q78*(1+$H$27) -> 491.94955 | S78: =+R78*(1+$H$27) -> 506.70803 | T78: =+S78*(1+$H$27) -> 521.90927
F79: Others | K79: =+SUM(K80:K89) -> 89838.555 | L79: =+K79*(1+$H$27) -> 92533.712 | M79: =+L79*(1+$H$27) -> 95309.723 | N79: =+M79*(1+$H$27) -> 98169.015 | O79: =+N79*(1+$H$27) -> 101114.09 | P79: =+O79*(1+$H$27) -> 104147.51 | Q79: =+P79*(1+$H$27) -> 107271.93 | R79: =+Q79*(1+$H$27) -> 110490.09 | S79: =+R79*(1+$H$27) -> 113804.79 | T79: =+S79*(1+$H$27) -> 117218.94
F80: Amenities | H80: 0.5 | I80: R | K80: =+$H80*$H$62 -> 7767.2 | L80: =+K80*(1+$H$27) -> 8000.216 | M80: =+L80*(1+$H$27) -> 8240.2225 | N80: =+M80*(1+$H$27) -> 8487.4292 | O80: =+N80*(1+$H$27) -> 8742.052 | P80: =+O80*(1+$H$27) -> 9004.3136 | Q80: =+P80*(1+$H$27) -> 9274.443 | R80: =+Q80*(1+$H$27) -> 9552.6763 | S80: =+R80*(1+$H$27) -> 9839.2566 | T80: =+S80*(1+$H$27) -> 10134.434
F81: Fire System | H81: 65 | I81: N | K81: =+H81*12 -> 780 | L81: =+K81*(1+$H$27) -> 803.4 | M81: =+L81*(1+$H$27) -> 827.502 | N81: =+M81*(1+$H$27) -> 852.32706 | O81: =+N81*(1+$H$27) -> 877.89687 | P81: =+O81*(1+$H$27) -> 904.23378 | Q81: =+P81*(1+$H$27) -> 931.36079 | R81: =+Q81*(1+$H$27) -> 959.30162 | S81: =+R81*(1+$H$27) -> 988.08066 | T81: =+S81*(1+$H$27) -> 1017.7231
F82: Insurances | H82: 1250 | I82: N | K82: =+H82*12 -> 15000 | L82: =+K82*(1+$H$27) -> 15450 | M82: =+L82*(1+$H$27) -> 15913.5 | N82: =+M82*(1+$H$27) -> 16390.905 | O82: =+N82*(1+$H$27) -> 16882.632 | P82: =+O82*(1+$H$27) -> 17389.111 | Q82: =+P82*(1+$H$27) -> 17910.784 | R82: =+Q82*(1+$H$27) -> 18448.108 | S82: =+R82*(1+$H$27) -> 19001.551 | T82: =+S82*(1+$H$27) -> 19571.598
F83: Taxes | H83: 0 | I83: N | K83: =+H83*12 -> 0 | L83: =+K83*(1+$H$27) -> 0 | M83: =+L83*(1+$H$27) -> 0 | N83: =+M83*(1+$H$27) -> 0 | O83: =+N83*(1+$H$27) -> 0 | P83: =+O83*(1+$H$27) -> 0 | Q83: =+P83*(1+$H$27) -> 0 | R83: =+Q83*(1+$H$27) -> 0 | S83: =+R83*(1+$H$27) -> 0 | T83: =+S83*(1+$H$27) -> 0
F84: Duve | H84: 333.33333 | I84: N | K84: =+H84*12 -> 4000 | L84: =+K84*(1+$H$27) -> 4120 | M84: =+L84*(1+$H$27) -> 4243.6 | N84: =+M84*(1+$H$27) -> 4370.908 | O84: =+N84*(1+$H$27) -> 4502.0352 | P84: =+O84*(1+$H$27) -> 4637.0963 | Q84: =+P84*(1+$H$27) -> 4776.2092 | R84: =+Q84*(1+$H$27) -> 4919.4955 | S84: =+R84*(1+$H$27) -> 5067.0803 | T84: =+S84*(1+$H$27) -> 5219.0927
F85: Mews software | H85: =56*14 -> 784 | I85: N | K85: =+H85*12 -> 9408 | L85: =+K85*(1+$H$27) -> 9690.24 | M85: =+L85*(1+$H$27) -> 9980.9472 | N85: =+M85*(1+$H$27) -> 10280.376 | O85: =+N85*(1+$H$27) -> 10588.787 | P85: =+O85*(1+$H$27) -> 10906.45 | Q85: =+P85*(1+$H$27) -> 11233.644 | R85: =+Q85*(1+$H$27) -> 11570.653 | S85: =+R85*(1+$H$27) -> 11917.773 | T85: =+S85*(1+$H$27) -> 12275.306
F86: Stripe fees | H86: 0.02 | I86: W | K86: =+$H86*K$47 -> 45348.505 | L86: =+K86*(1+$H$27) -> 46708.96 | M86: =+L86*(1+$H$27) -> 48110.228 | N86: =+M86*(1+$H$27) -> 49553.535 | O86: =+N86*(1+$H$27) -> 51040.141 | P86: =+O86*(1+$H$27) -> 52571.346 | Q86: =+P86*(1+$H$27) -> 54148.486 | R86: =+Q86*(1+$H$27) -> 55772.941 | S86: =+R86*(1+$H$27) -> 57446.129 | T86: =+S86*(1+$H$27) -> 59169.513
F87: Bank fees | H87: 0.002 | I87: W | K87: =+$H87*K$47 -> 4534.8505 | L87: =+K87*(1+$H$27) -> 4670.896 | M87: =+L87*(1+$H$27) -> 4811.0228 | N87: =+M87*(1+$H$27) -> 4955.3535 | O87: =+N87*(1+$H$27) -> 5104.0141 | P87: =+O87*(1+$H$27) -> 5257.1346 | Q87: =+P87*(1+$H$27) -> 5414.8486 | R87: =+Q87*(1+$H$27) -> 5577.2941 | S87: =+R87*(1+$H$27) -> 5744.6129 | T87: =+S87*(1+$H$27) -> 5916.9513
F88: Labour consulting | H88: 166.66667 | I88: N | K88: =+H88*12 -> 2000 | L88: =+K88*(1+$H$27) -> 2060 | M88: =+L88*(1+$H$27) -> 2121.8 | N88: =+M88*(1+$H$27) -> 2185.454 | O88: =+N88*(1+$H$27) -> 2251.0176 | P88: =+O88*(1+$H$27) -> 2318.5481 | Q88: =+P88*(1+$H$27) -> 2388.1046 | R88: =+Q88*(1+$H$27) -> 2459.7477 | S88: =+R88*(1+$H$27) -> 2533.5402 | T88: =+S88*(1+$H$27) -> 2609.5464
F89: Occupational risk prevention | H89: 83.333333 | I89: N | K89: =+H89*12 -> 1000 | L89: =+K89*(1+$H$27) -> 1030 | M89: =+L89*(1+$H$27) -> 1060.9 | N89: =+M89*(1+$H$27) -> 1092.727 | O89: =+N89*(1+$H$27) -> 1125.5088 | P89: =+O89*(1+$H$27) -> 1159.2741 | Q89: =+P89*(1+$H$27) -> 1194.0523 | R89: =+Q89*(1+$H$27) -> 1229.8739 | S89: =+R89*(1+$H$27) -> 1266.7701 | T89: =+S89*(1+$H$27) -> 1304.7732
F90: Supplies | K90: =+SUM(K91:K93) -> 67997.92 | L90: =+K90*(1+$H$27) -> 70037.858 | M90: =+L90*(1+$H$27) -> 72138.993 | N90: =+M90*(1+$H$27) -> 74303.163 | O90: =+N90*(1+$H$27) -> 76532.258 | P90: =+O90*(1+$H$27) -> 78828.226 | Q90: =+P90*(1+$H$27) -> 81193.073 | R90: =+Q90*(1+$H$27) -> 83628.865 | S90: =+R90*(1+$H$27) -> 86137.731 | T90: =+S90*(1+$H$27) -> 88721.863
F91: Lights supply | H91: 3.5 | I91: R | K91: =+$H91*$H$62 -> 54370.4 | L91: =+K91*(1+$H$27) -> 56001.512 | M91: =+L91*(1+$H$27) -> 57681.557 | N91: =+M91*(1+$H$27) -> 59412.004 | O91: =+N91*(1+$H$27) -> 61194.364 | P91: =+O91*(1+$H$27) -> 63030.195 | Q91: =+P91*(1+$H$27) -> 64921.101 | R91: =+Q91*(1+$H$27) -> 66868.734 | S91: =+R91*(1+$H$27) -> 68874.796 | T91: =+S91*(1+$H$27) -> 70941.04
F92: Water supply | H92: 0.8 | I92: R | K92: =+$H92*$H$62 -> 12427.52 | L92: =+K92*(1+$H$27) -> 12800.346 | M92: =+L92*(1+$H$27) -> 13184.356 | N92: =+M92*(1+$H$27) -> 13579.887 | O92: =+N92*(1+$H$27) -> 13987.283 | P92: =+O92*(1+$H$27) -> 14406.902 | Q92: =+P92*(1+$H$27) -> 14839.109 | R92: =+Q92*(1+$H$27) -> 15284.282 | S92: =+R92*(1+$H$27) -> 15742.811 | T92: =+S92*(1+$H$27) -> 16215.095
F93: Wifi and phone supply | H93: 100 | I93: N | K93: =+H93*12 -> 1200 | L93: =+K93*(1+$H$27) -> 1236 | M93: =+L93*(1+$H$27) -> 1273.08 | N93: =+M93*(1+$H$27) -> 1311.2724 | O93: =+N93*(1+$H$27) -> 1350.6106 | P93: =+O93*(1+$H$27) -> 1391.1289 | Q93: =+P93*(1+$H$27) -> 1432.8628 | R93: =+Q93*(1+$H$27) -> 1475.8486 | S93: =+R93*(1+$H$27) -> 1520.1241 | T93: =+S93*(1+$H$27) -> 1565.7278
E94: 5 | F94: Reception | H94: 2300 | I94: N | K94: =+$H94*$E94*12 -> 138000 | L94: =+K94*(1+$H$27) -> 142140 | M94: =+L94*(1+$H$27) -> 146404.2 | N94: =+M94*(1+$H$27) -> 150796.33 | O94: =+N94*(1+$H$27) -> 155320.22 | P94: =+O94*(1+$H$27) -> 159979.82 | Q94: =+P94*(1+$H$27) -> 164779.22 | R94: =+Q94*(1+$H$27) -> 169722.59 | S94: =+R94*(1+$H$27) -> 174814.27 | T94: =+S94*(1+$H$27) -> 180058.7
F95: Bar | K95: =+SUM(K96:K96) -> 76363.636 | L95: =+K95*(1+$H$27) -> 78654.545 | M95: =+L95*(1+$H$27) -> 81014.182 | N95: =+M95*(1+$H$27) -> 83444.607 | O95: =+N95*(1+$H$27) -> 85947.945 | P95: =+O95*(1+$H$27) -> 88526.384 | Q95: =+P95*(1+$H$27) -> 91182.175 | R95: =+Q95*(1+$H$27) -> 93917.641 | S95: =+R95*(1+$H$27) -> 96735.17 | T95: =+S95*(1+$H$27) -> 99637.225
F96: Bartola | H96: 0.68181818 | I96: W/Bart. Rev. | K96: =+$H96*K$49 -> 76363.636 | L96: =+K96*(1+$H$27) -> 78654.545 | M96: =+L96*(1+$H$27) -> 81014.182 | N96: =+M96*(1+$H$27) -> 83444.607 | O96: =+N96*(1+$H$27) -> 85947.945 | P96: =+O96*(1+$H$27) -> 88526.384 | Q96: =+P96*(1+$H$27) -> 91182.175 | R96: =+Q96*(1+$H$27) -> 93917.641 | S96: =+R96*(1+$H$27) -> 96735.17 | T96: =+S96*(1+$H$27) -> 99637.225
F97: Laundry | H97: 4.5 | I97: R | K97: =+$H97*$H$62 -> 69904.8 | L97: =+K97*(1+$H$27) -> 72001.944 | M97: =+L97*(1+$H$27) -> 74162.002 | N97: =+M97*(1+$H$27) -> 76386.862 | O97: =+N97*(1+$H$27) -> 78678.468 | P97: =+O97*(1+$H$27) -> 81038.822 | Q97: =+P97*(1+$H$27) -> 83469.987 | R97: =+Q97*(1+$H$27) -> 85974.087 | S97: =+R97*(1+$H$27) -> 88553.309 | T97: =+S97*(1+$H$27) -> 91209.908
B98: Walk-in | C98: 0.03 | F98: OTA's | K98: =+SUM(K99:K100) -> 261636.39 | L98: =+K98*(1+$H$27) -> 269485.49 | M98: =+L98*(1+$H$27) -> 277570.05 | N98: =+M98*(1+$H$27) -> 285897.15 | O98: =+N98*(1+$H$27) -> 294474.07 | P98: =+O98*(1+$H$27) -> 303308.29 | Q98: =+P98*(1+$H$27) -> 312407.54 | R98: =+Q98*(1+$H$27) -> 321779.76 | S98: =+R98*(1+$H$27) -> 331433.16 | T98: =+S98*(1+$H$27) -> 341376.15
B99: Website | C99: 0.21 | F99: Website | H99: 0.015 | I99: W/SB REV. | K99: =+(K$48+K$49*$C$100)*C99*H99 -> 7035.0375 | L99: =+K99*(1+$H$27) -> 7246.0886 | M99: =+L99*(1+$H$27) -> 7463.4713 | N99: =+M99*(1+$H$27) -> 7687.3754 | O99: =+N99*(1+$H$27) -> 7917.9967 | P99: =+O99*(1+$H$27) -> 8155.5366 | Q99: =+P99*(1+$H$27) -> 8400.2026 | R99: =+Q99*(1+$H$27) -> 8652.2087 | S99: =+R99*(1+$H$27) -> 8911.775 | T99: =+S99*(1+$H$27) -> 9179.1282
B100: Booking, Expedia, Airbnb | C100: =100%-SUM(C98:C99) -> 0.76 | F100: Booking, Expedia, Airbnb | H100: 0.15 | I100: W/B. REV. | K100: =+(K$48+K$49*$C$100)*C100*H100 -> 254601.36 | L100: =+K100*(1+$H$27) -> 262239.4 | M100: =+L100*(1+$H$27) -> 270106.58 | N100: =+M100*(1+$H$27) -> 278209.78 | O100: =+N100*(1+$H$27) -> 286556.07 | P100: =+O100*(1+$H$27) -> 295152.75 | Q100: =+P100*(1+$H$27) -> 304007.33 | R100: =+Q100*(1+$H$27) -> 313127.55 | S100: =+R100*(1+$H$27) -> 322521.38 | T100: =+S100*(1+$H$27) -> 332197.02
F101: Revenue Manager | K101: =+SUM(K102:K103) -> 29971.528 | L101: =+K101*(1+$H$27) -> 30870.674 | M101: =+L101*(1+$H$27) -> 31796.794 | N101: =+M101*(1+$H$27) -> 32750.698 | O101: =+N101*(1+$H$27) -> 33733.219 | P101: =+O101*(1+$H$27) -> 34745.215 | Q101: =+P101*(1+$H$27) -> 35787.572 | R101: =+Q101*(1+$H$27) -> 36861.199 | S101: =+R101*(1+$H$27) -> 37967.035 | T101: =+S101*(1+$H$27) -> 39106.046
F102: Channel Manager Software | H102: 41.25 | I102: N | K102: =+H102*12 -> 495 | L102: =+K102*(1+$H$27) -> 509.85 | M102: =+L102*(1+$H$27) -> 525.1455 | N102: =+M102*(1+$H$27) -> 540.89987 | O102: =+N102*(1+$H$27) -> 557.12686 | P102: =+O102*(1+$H$27) -> 573.84067 | Q102: =+P102*(1+$H$27) -> 591.05589 | R102: =+Q102*(1+$H$27) -> 608.78756 | S102: =+R102*(1+$H$27) -> 627.05119 | T102: =+S102*(1+$H$27) -> 645.86273
F103: Fees Excellation (Asaf) | H103: 0.013 | I103: W | K103: =+$H103*K$47 -> 29476.528 | L103: =+K103*(1+$H$27) -> 30360.824 | M103: =+L103*(1+$H$27) -> 31271.649 | N103: =+M103*(1+$H$27) -> 32209.798 | O103: =+N103*(1+$H$27) -> 33176.092 | P103: =+O103*(1+$H$27) -> 34171.375 | Q103: =+P103*(1+$H$27) -> 35196.516 | R103: =+Q103*(1+$H$27) -> 36252.411 | S103: =+R103*(1+$H$27) -> 37339.984 | T103: =+S103*(1+$H$27) -> 38460.183
F105: NOI | K105: =+K47-K55-K64 -> 595144.44 | L105: =+L47-L55-L64 -> 352652.6 | M105: =+M47-M55-M64 -> 383333.09 | N105: =+N47-N55-N64 -> 394536.63 | O105: =+O47-O55-O64 -> 439662.39 | P105: =+P47-P55-P64 -> 627771.08 | Q105: =+Q47-Q55-Q64 -> 691509.12 | R105: =+R47-R55-R64 -> 748164.71 | ... T105: =+T47-T55-T64 -> 884311.97 | W105: =+SUM(K105:T105) -> 5931245.7
F107: NOI after inv. | K107: =+K105-K16 -> 231644.44 | L107: =+L105 -> 352652.6 | M107: =+M105 -> 383333.09 | N107: =+N105 -> 394536.63 | O107: =+O105 -> 439662.39 | P107: =+P105 -> 627771.08 | Q107: =+Q105 -> 691509.12 | R107: =+R105 -> 748164.71 | S107: =+S105 -> 814159.67 | T107: =+T105 -> 884311.97 | W107: =+SUM(K107:T107) -> 5567745.7
B109: FF&E Replacement | C109: 0.01 | F109: FF&E Replacement | K109: 0 | L109: =+L47*$C$109 -> 24995.142 | M109: =+M47*$C$109 -> 26938.178 | N109: =+N47*$C$109 -> 28211.575 | O109: =+O47*$C$109 -> 29622.154 | P109: =+P47*$C$109 -> 31103.262 | Q109: =+Q47*$C$109 -> 32743.524 | R109: =+R47*$C$109 -> 34291.346 | S109: =+S47*$C$109 -> 36005.914 | T109: =+T47*$C$109 -> 37806.209
F111: Final FCF | K111: =+K107-K109 -> 231644.44 | L111: =+L107-L109 -> 327657.45 | M111: =+M107-M109 -> 356394.91 | N111: =+N107-N109 -> 366325.05 | O111: =+O107-O109 -> 410040.23 | P111: =+P107-P109 -> 596667.82 | Q111: =+Q107-Q109 -> 658765.6 | R111: =+R107-R109 -> 713873.37 | ... T111: =+T107-T109 -> 846505.76
F114: Impact for Bartola NOI | K114: =+K49/(14.9/1.1) -> 8268.4564 | L114: =+L49/(14.9/1.1) -> 8681.8792 | M114: =+M49/(14.9/1.1) -> 9115.9732 | N114: =+N49/(14.9/1.1) -> 9571.7718 | O114: =+O49/(14.9/1.1) -> 10050.36 | P114: =+P49/(14.9/1.1) -> 10552.878 | Q114: =+Q49/(14.9/1.1) -> 11080.522 | R114: =+R49/(14.9/1.1) -> 11634.548 | ... T114: =+T49/(14.9/1.1) -> 12827.09
F115: Great impact to Experiences P&L
C120: Inv x Space | H120: Units | I120: Inv. x unit | K120: Total inv .
C122: 80000 | F122: Bar-F&B investment | H122: 1 | I122: =+C122 -> 80000 | K122: =+C122*H122 -> 80000
F124: Total investment | K124: =+SUM(K122:K122) -> 80000
F129: Roftop Bar P&L | K129: 2026 | L129: 2027 | M129: 2028 | N129: 2029 | O129: 2030 | P129: 2031 | Q129: 2032 | R129: 2033 | S129: 2034 | T129: 2035
F131: Revenue | K131: =+K132 -> 600000 | L131: =+L132 -> 630000 | M131: =+M132 -> 661500 | N131: =+N132 -> 694575 | O131: =+O132 -> 729303.75 | P131: =+P132 -> 765768.94 | Q131: =+Q132 -> 804057.38 | R131: =+R132 -> 844260.25 | ... T131: =+T132 -> 930796.93 | W131: 32323594
F132: Rooftop bar | H132: 50000 | K132: =+H132*12 -> 600000 | L132: =+K132*(1+SUM($H$27:$H$28)) -> 630000 | M132: =+L132*(1+SUM($H$27:$H$28)) -> 661500 | N132: =+M132*(1+SUM($H$27:$H$28)) -> 694575 | O132: =+N132*(1+SUM($H$27:$H$28)) -> 729303.75 | P132: =+O132*(1+SUM($H$27:$H$28)) -> 765768.94 | Q132: =+P132*(1+SUM($H$27:$H$28)) -> 804057.38 | R132: =+Q132*(1+SUM($H$27:$H$28)) -> 844260.25 | S132: =+R132*(1+SUM($H$27:$H$28)) -> 886473.27 | T132: =+S132*(1+SUM($H$27:$H$28)) -> 930796.93
F134: Grace-Months | H134: =+K124/(K137/12) -> 11.940299 | K134: =-(H138)*H134 -> -80000
F136: Lease to Charming Stay | K136: =+K137+K134 -> 400 | L136: =+L137+L134 -> 82812 | M136: =+M137+M134 -> 85296.36 | N136: =+N137+N134 -> 87855.251 | O136: =+O137+O134 -> 90490.908 | P136: =+P137+P134 -> 93205.636 | Q136: =+Q137+Q134 -> 96001.805 | R136: =+R137+R134 -> 98881.859 | ... U136: =+U137+U134 -> 0
F137: Lease to Charming Stay | K137: =+K138 -> 80400 | L137: =+IF(L132<0,MIN(L138:L140),MAX(L138:L140)) -> 82812 | M137: =+IF(M132<0,MIN(M138:M140),MAX(M138:M140)) -> 85296.36 | N137: =+IF(N132<0,MIN(N138:N140),MAX(N138:N140)) -> 87855.251 | O137: =+IF(O132<0,MIN(O138:O140),MAX(O138:O140)) -> 90490.908 | P137: =+IF(P132<0,MIN(P138:P140),MAX(P138:P140)) -> 93205.636 | Q137: =+IF(Q132<0,MIN(Q138:Q140),MAX(Q138:Q140)) -> 96001.805 | R137: =+IF(R132<0,MIN(R138:R140),MAX(R138:R140)) -> 98881.859 | S137: =+IF(S132<0,MIN(S138:S140),MAX(S138:S140)) -> 101848.31 | T137: =+IF(T132<0,MIN(T138:T140),MAX(T138:T140)) -> 104903.76
F138: Rooftop bar rent | H138: 6700 | K138: =+$H138*12 -> 80400 | L138: =+K138*(1+$H$27) -> 82812 | M138: =+L138*(1+$H$27) -> 85296.36 | N138: =+M138*(1+$H$27) -> 87855.251 | O138: =+N138*(1+$H$27) -> 90490.908 | P138: =+O138*(1+$H$27) -> 93205.636 | Q138: =+P138*(1+$H$27) -> 96001.805 | R138: =+Q138*(1+$H$27) -> 98881.859 | S138: =+R138*(1+$H$27) -> 101848.31 | T138: =+S138*(1+$H$27) -> 104903.76
F145: Expenses | K145: =+SUM(K146:K148) -> 298800 | L145: =+K145*(1+$H$27) -> 307764 | M145: =+L145*(1+$H$27) -> 316996.92 | N145: =+M145*(1+$H$27) -> 326506.83 | O145: =+N145*(1+$H$27) -> 336302.03 | P145: =+O145*(1+$H$27) -> 346391.09 | Q145: =+P145*(1+$H$27) -> 356782.83 | R145: =+Q145*(1+$H$27) -> 367486.31 | S145: =+R145*(1+$H$27) -> 378510.9 | T145: =+S145*(1+$H$27) -> 389866.23
F146: Rooftop bar rent | H146: 3000 | I146: N | K146: =+$H146*12 -> 36000 | L146: =+K146*(1+$H$27) -> 37080 | M146: =+L146*(1+$H$27) -> 38192.4 | N146: =+M146*(1+$H$27) -> 39338.172 | O146: =+N146*(1+$H$27) -> 40518.317 | P146: =+O146*(1+$H$27) -> 41733.867 | Q146: =+P146*(1+$H$27) -> 42985.883 | R146: =+Q146*(1+$H$27) -> 44275.459 | S146: =+R146*(1+$H$27) -> 45603.723 | T146: =+S146*(1+$H$27) -> 46971.835
E147: 2 | F147: Bartender payroll | H147: 2200 | I147: N | K147: =+$H147*$E147*12 -> 52800 | L147: =+K147*(1+$H$27) -> 54384 | M147: =+L147*(1+$H$27) -> 56015.52 | N147: =+M147*(1+$H$27) -> 57695.986 | O147: =+N147*(1+$H$27) -> 59426.865 | P147: =+O147*(1+$H$27) -> 61209.671 | Q147: =+P147*(1+$H$27) -> 63045.961 | R147: =+Q147*(1+$H$27) -> 64937.34 | S147: =+R147*(1+$H$27) -> 66885.46 | T147: =+S147*(1+$H$27) -> 68892.024
...

Sheet Lease option 2
C4: Inv x Space | H4: Units | I4: Inv. x unit | K4: Total inv .
C6: 35000 | F6: Common areas | H6: 1 | I6: =+C6 -> 35000 | K6: =+C6*H6 -> 35000
C7: 5000 | F7: Studio | H7: 22 | I7: =+C7 -> 5000 | K7: =+C7*H7 -> 110000
C8: 5500 | F8: Studio French Balcony | H8: 13 | I8: =+C8 -> 5500 | K8: =+C8*H8 -> 71500
C9: 6000 | F9: Superior Studio | H9: 2 | I9: =+C9 -> 6000 | K9: =+C9*H9 -> 12000
C10: 7000 | F10: Studio with Terrace | H10: 4 | I10: =+C10 -> 7000 | K10: =+C10*H10 -> 28000
C11: 7000 | F11: Triple Studio | H11: 4 | I11: =+C11 -> 7000 | K11: =+C11*H11 -> 28000
C12: 7000 | F12: One Bedroom Apartment | H12: 5 | I12: =+C12 -> 7000 | K12: =+C12*H12 -> 35000
C13: 7000 | F13: One Bedroom Terrace | H13: 4 | I13: =+C13 -> 7000 | K13: =+C13*H13 -> 28000
C14: 8000 | F14: Two Bedroom Terrace | H14: 2 | I14: =+C14 -> 8000 | K14: =+C14*H14 -> 16000
F16: Total investment | K16: =+SUM(K6:K14) -> 363500
F19: Template | H19: Peña | K19: 140.9 | L19: 154.1 | M19: 169.5 | N19: =+M19*(1+$H$27) -> 174.585 | O19: =+N19*(1+$H$27) -> 179.82255 | P19: =+O19*(1+$H$27) -> 185.21723 | Q19: =+P19*(1+$H$27) -> 190.77374 | R19: =+Q19*(1+$H$27) -> 196.49696 | S19: =+R19*(1+$H$27) -> 202.39186 | T19: =+S19*(1+$H$27) -> 208.46362
H21: Fix min. Lease x apartment | K21: 1300 | L21: 1400 | M21: 1500 | N21: =+M21*(1+SUM($H$27)) -> 1545 | O21: =+N21*(1+SUM($H$27)) -> 1591.35 | P21: =+O21*(1+SUM($H$27)) -> 1639.0905 | Q21: =+P21*(1+SUM($H$27)) -> 1688.2632 | R21: =+Q21*(1+SUM($H$27)) -> 1738.9111 | S21: =+R21*(1+SUM($H$27)) -> 1791.0784 | T21: =+S21*(1+SUM($H$27)) -> 1844.8108
H22: /rev | K22: =+K57/K47 -> 0.38528283 | L22: =+L57/L47 -> 0.37639314 | M22: =+M57/M47 -> 0.37419012 | N22: =+N57/N47 -> 0.36801915 | O22: =+O57/O47 -> 0.36100926 | P22: =+P57/P47 -> 0.35413289 | Q22: =+Q57/Q47 -> 0.34648466 | R22: =+R57/R47 -> 0.3407706 | ... T22: =+T57/T47 -> 0.3279125
H24: Variable lease | K24: 0.37 | L24: 0.38 | M24: 0.4 | N24: 0.41 | O24: 0.41 | P24: 0.41 | Q24: 0.41 | R24: 0.41 | S24: 0.41 | T24: 0.41
H25: Variable lease (F&B Bartola) | K25: 0.05 | L25: 0.08 | M25: 0.08 | N25: 0.08 | O25: 0.08 | P25: 0.08 | Q25: 0.08 | R25: 0.08 | S25: 0.08 | T25: 0.08
F27: IPC | H27: 0.03
F28: GROWTH | H28: 0.02
K32: 2026 | L32: 2027 | M32: 2028 | N32: 2029 | O32: 2030 | P32: 2031 | Q32: 2032 | R32: 2033 | S32: 2034 | T32: 2035
F34: % Average occupancy | K34: 0.76 | L34: 0.8 | M34: 0.82 | N34: 0.82 | O34: 0.82 | P34: 0.82 | Q34: 0.82 | R34: 0.82 | S34: 0.82 | T34: 0.82 | W34: =+AVERAGE(K34:T34) -> 0.812
F35: Number of opened days | K35: 365 | L35: 365 | M35: 366 | N35: 365 | O35: 365 | P35: 365 | Q35: 366 | R35: 365 | S35: 365 | T35: 365
F36: Units | K36: 56 | L36: 56 | M36: 56 | N36: 56 | O36: 56 | P36: 56 | Q36: 56 | R36: 56 | S36: 56 | T36: 56
B37: Asaf Assumption | C37: 119.43726 | F37: ADR | K37: =+($H$38*K38+$H$39*K39+$H$40*K40+$H$41*K41+$H$42*K42+$H$43*K43+$H$44*K44+$H$45*K45)/SUM($H$38:$H$45) -> 138.28827 | L37: =+($H$38*L38+$H$39*L39+$H$40*L40+$H$41*L41+$H$42*L42+$H$43*L43+$H$44*L44+$H$45*L45)/SUM($H$38:$H$45) -> 145.20268 | M37: =+($H$38*M38+$H$39*M39+$H$40*M40+$H$41*M41+$H$42*M42+$H$43*M43+$H$44*M44+$H$45*M45)/SUM($H$38:$H$45) -> 152.46281 | N37: =+($H$38*N38+$H$39*N39+$H$40*N40+$H$41*N41+$H$42*N42+$H$43*N43+$H$44*N44+$H$45*N45)/SUM($H$38:$H$45) -> 160.08595 | O37: =+($H$38*O38+$H$39*O39+$H$40*O40+$H$41*O41+$H$42*O42+$H$43*O43+$H$44*O44+$H$45*O45)/SUM($H$38:$H$45) -> 168.09025 | P37: =+($H$38*P38+$H$39*P39+$H$40*P40+$H$41*P41+$H$42*P42+$H$43*P43+$H$44*P44+$H$45*P45)/SUM($H$38:$H$45) -> 176.49476 | Q37: =+($H$38*Q38+$H$39*Q39+$H$40*Q40+$H$41*Q41+$H$42*Q42+$H$43*Q43+$H$44*Q44+$H$45*Q45)/SUM($H$38:$H$45) -> 185.3195 | R37: =+($H$38*R38+$H$39*R39+$H$40*R40+$H$41*R41+$H$42*R42+$H$43*R43+$H$44*R44+$H$45*R45)/SUM($H$38:$H$45) -> 194.58548 | ... T37: =+($H$38*T38+$H$39*T39+$H$40*T40+$H$41*T41+$H$42*T42+$H$43*T43+$H$44*T44+$H$45*T45)/SUM($H$38:$H$45) -> 214.53049 | W37: =+AVERAGE(K37:T37) -> 173.93749
F38: Studio | H38: 22 | K38: 115 | L38: =+K38*(1+SUM($H$27:$H$28)) -> 120.75 | M38: =+L38*(1+SUM($H$27:$H$28)) -> 126.7875 | N38: =+M38*(1+SUM($H$27:$H$28)) -> 133.12688 | O38: =+N38*(1+SUM($H$27:$H$28)) -> 139.78322 | P38: =+O38*(1+SUM($H$27:$H$28)) -> 146.77238 | Q38: =+P38*(1+SUM($H$27:$H$28)) -> 154.111 | R38: =+Q38*(1+SUM($H$27:$H$28)) -> 161.81655 | S38: =+R38*(1+SUM($H$27:$H$28)) -> 169.90738 | T38: =+S38*(1+SUM($H$27:$H$28)) -> 178.40274
F39: Studio French Balcony | H39: 13 | K39: 135 | L39: =+K39*(1+SUM($H$27:$H$28)) -> 141.75 | M39: =+L39*(1+SUM($H$27:$H$28)) -> 148.8375 | N39: =+M39*(1+SUM($H$27:$H$28)) -> 156.27938 | O39: =+N39*(1+SUM($H$27:$H$28)) -> 164.09334 | P39: =+O39*(1+SUM($H$27:$H$28)) -> 172.29801 | Q39: =+P39*(1+SUM($H$27:$H$28)) -> 180.91291 | R39: =+Q39*(1+SUM($H$27:$H$28)) -> 189.95856 | S39: =+R39*(1+SUM($H$27:$H$28)) -> 199.45648 | T39: =+S39*(1+SUM($H$27:$H$28)) -> 209.42931
F40: Superior Studio | H40: 2 | K40: 135 | L40: =+K40*(1+SUM($H$27:$H$28)) -> 141.75 | M40: =+L40*(1+SUM($H$27:$H$28)) -> 148.8375 | N40: =+M40*(1+SUM($H$27:$H$28)) -> 156.27938 | O40: =+N40*(1+SUM($H$27:$H$28)) -> 164.09334 | P40: =+O40*(1+SUM($H$27:$H$28)) -> 172.29801 | Q40: =+P40*(1+SUM($H$27:$H$28)) -> 180.91291 | R40: =+Q40*(1+SUM($H$27:$H$28)) -> 189.95856 | S40: =+R40*(1+SUM($H$27:$H$28)) -> 199.45648 | T40: =+S40*(1+SUM($H$27:$H$28)) -> 209.42931
F41: Studio with Terrace | H41: 4 | K41: 146.03571 | L41: =+K41*(1+SUM($H$27:$H$28)) -> 153.3375 | M41: =+L41*(1+SUM($H$27:$H$28)) -> 161.00438 | N41: =+M41*(1+SUM($H$27:$H$28)) -> 169.05459 | O41: =+N41*(1+SUM($H$27:$H$28)) -> 177.50732 | P41: =+O41*(1+SUM($H$27:$H$28)) -> 186.38269 | Q41: =+P41*(1+SUM($H$27:$H$28)) -> 195.70182 | R41: =+Q41*(1+SUM($H$27:$H$28)) -> 205.48692 | S41: =+R41*(1+SUM($H$27:$H$28)) -> 215.76126 | T41: =+S41*(1+SUM($H$27:$H$28)) -> 226.54932
F42: Triple Studio | H42: 4 | K42: 140 | L42: =+K42*(1+SUM($H$27:$H$28)) -> 147 | M42: =+L42*(1+SUM($H$27:$H$28)) -> 154.35 | N42: =+M42*(1+SUM($H$27:$H$28)) -> 162.0675 | O42: =+N42*(1+SUM($H$27:$H$28)) -> 170.17087 | P42: =+O42*(1+SUM($H$27:$H$28)) -> 178.67942 | Q42: =+P42*(1+SUM($H$27:$H$28)) -> 187.61339 | R42: =+Q42*(1+SUM($H$27:$H$28)) -> 196.99406 | S42: =+R42*(1+SUM($H$27:$H$28)) -> 206.84376 | T42: =+S42*(1+SUM($H$27:$H$28)) -> 217.18595
F43: One Bedroom Apartment | H43: 5 | K43: 165 | L43: =+K43*(1+SUM($H$27:$H$28)) -> 173.25 | M43: =+L43*(1+SUM($H$27:$H$28)) -> 181.9125 | N43: =+M43*(1+SUM($H$27:$H$28)) -> 191.00813 | O43: =+N43*(1+SUM($H$27:$H$28)) -> 200.55853 | P43: =+O43*(1+SUM($H$27:$H$28)) -> 210.58646 | Q43: =+P43*(1+SUM($H$27:$H$28)) -> 221.11578 | R43: =+Q43*(1+SUM($H$27:$H$28)) -> 232.17157 | S43: =+R43*(1+SUM($H$27:$H$28)) -> 243.78015 | T43: =+S43*(1+SUM($H$27:$H$28)) -> 255.96916
F44: One Bedroom Terrace | H44: 4 | K44: 190 | L44: =+K44*(1+SUM($H$27:$H$28)) -> 199.5 | M44: =+L44*(1+SUM($H$27:$H$28)) -> 209.475 | N44: =+M44*(1+SUM($H$27:$H$28)) -> 219.94875 | O44: =+N44*(1+SUM($H$27:$H$28)) -> 230.94619 | P44: =+O44*(1+SUM($H$27:$H$28)) -> 242.4935 | Q44: =+P44*(1+SUM($H$27:$H$28)) -> 254.61817 | R44: =+Q44*(1+SUM($H$27:$H$28)) -> 267.34908 | S44: =+R44*(1+SUM($H$27:$H$28)) -> 280.71653 | T44: =+S44*(1+SUM($H$27:$H$28)) -> 294.75236
F45: Two Bedroom Terrace | H45: 2 | K45: 230 | L45: =+K45*(1+SUM($H$27:$H$28)) -> 241.5 | M45: =+L45*(1+SUM($H$27:$H$28)) -> 253.575 | N45: =+M45*(1+SUM($H$27:$H$28)) -> 266.25375 | O45: =+N45*(1+SUM($H$27:$H$28)) -> 279.56644 | P45: =+O45*(1+SUM($H$27:$H$28)) -> 293.54476 | Q45: =+P45*(1+SUM($H$27:$H$28)) -> 308.222 | R45: =+Q45*(1+SUM($H$27:$H$28)) -> 323.6331 | S45: =+R45*(1+SUM($H$27:$H$28)) -> 339.81475 | T45: =+S45*(1+SUM($H$27:$H$28)) -> 356.80549
F47: Revenue | K47: =+SUM(K48:K51) -> 2267425.2 | L47: =+SUM(L48:L51) -> 2499514.2 | M47: =+SUM(M48:M51) -> 2693817.8 | N47: =+SUM(N48:N51) -> 2821157.5 | O47: =+SUM(O48:O51) -> 2962215.4 | P47: =+SUM(P48:P51) -> 3110326.2 | Q47: =+SUM(Q48:Q51) -> 3274352.4 | R47: =+SUM(R48:R51) -> 3429134.6 | ... T47: =+SUM(T48:T51) -> 3780620.9 | W47: =+SUM(K47:T47) -> 30439156
F48: Bed revenue | K48: =+K34*K35*K36*K37 -> 2148225.2 | L48: =+L34*L35*L36*L37 -> 2374354.2 | M48: =+M34*M35*M36*M37 -> 2562399.8 | N48: =+N34*N35*N36*N37 -> 2683168.6 | O48: =+O34*O35*O36*O37 -> 2817327.1 | P48: =+P34*P35*P36*P37 -> 2958193.4 | Q48: =+Q34*Q35*Q36*Q37 -> 3114613 | R48: =+R34*R35*R36*R37 -> 3261408.3 | ... T48: =+T34*T35*T36*T37 -> 3595702.6
F49: F&B Bartola | H49: 9333.3333 | K49: =+H49*12 -> 112000 | L49: =+K49*(1+SUM($H$27:$H$28)) -> 117600 | M49: =+L49*(1+SUM($H$27:$H$28)) -> 123480 | N49: =+M49*(1+SUM($H$27:$H$28)) -> 129654 | O49: =+N49*(1+SUM($H$27:$H$28)) -> 136136.7 | P49: =+O49*(1+SUM($H$27:$H$28)) -> 142943.54 | Q49: =+P49*(1+SUM($H$27:$H$28)) -> 150090.71 | R49: =+Q49*(1+SUM($H$27:$H$28)) -> 157595.25 | S49: =+R49*(1+SUM($H$27:$H$28)) -> 165475.01 | T49: =+S49*(1+SUM($H$27:$H$28)) -> 173748.76
F50: Experiences | H50: 300 | K50: =+H50*12 -> 3600 | L50: =+K50*(1+SUM($H$27:$H$28)) -> 3780 | M50: =+L50*(1+SUM($H$27:$H$28)) -> 3969 | N50: =+M50*(1+SUM($H$27:$H$28)) -> 4167.45 | O50: =+N50*(1+SUM($H$27:$H$28)) -> 4375.8225 | P50: =+O50*(1+SUM($H$27:$H$28)) -> 4594.6136 | Q50: =+P50*(1+SUM($H$27:$H$28)) -> 4824.3443 | R50: =+Q50*(1+SUM($H$27:$H$28)) -> 5065.5615 | S50: =+R50*(1+SUM($H$27:$H$28)) -> 5318.8396 | T50: =+S50*(1+SUM($H$27:$H$28)) -> 5584.7816
F51: Parking | H51: 300 | K51: =+H51*12 -> 3600 | L51: =+K51*(1+SUM($H$27:$H$28)) -> 3780 | M51: =+L51*(1+SUM($H$27:$H$28)) -> 3969 | N51: =+M51*(1+SUM($H$27:$H$28)) -> 4167.45 | O51: =+N51*(1+SUM($H$27:$H$28)) -> 4375.8225 | P51: =+O51*(1+SUM($H$27:$H$28)) -> 4594.6136 | Q51: =+P51*(1+SUM($H$27:$H$28)) -> 4824.3443 | R51: =+Q51*(1+SUM($H$27:$H$28)) -> 5065.5615 | S51: =+R51*(1+SUM($H$27:$H$28)) -> 5318.8396 | T51: =+S51*(1+SUM($H$27:$H$28)) -> 5584.7816
F53: Grace-Months | H53: =+K16/(K57/12) -> 4.9931319 | K53: =-(K21*56)*H53 -> -363500
F55: Lease to Charming Stay | K55: =+IF(K53<0,MIN(K56:K58),MAX(K56:K58)) -> 510100 | L55: =+IF(L53<0,MIN(L56:L58),MAX(L56:L58)) -> 940800 | M55: =+IF(M53<0,MIN(M56:M58),MAX(M56:M58)) -> 1034309.1 | N55: =+IF(N53<0,MIN(N56:N58),MAX(N56:N58)) -> 1109999.2 | O55: =+IF(O53<0,MIN(O56:O58),MAX(O56:O58)) -> 1165499.1 | P55: =+IF(P53<0,MIN(P56:P58),MAX(P56:P58)) -> 1223774.1 | Q55: =+IF(Q53<0,MIN(Q56:Q58),MAX(Q56:Q58)) -> 1288451.8 | R55: =+IF(R53<0,MIN(R56:R58),MAX(R56:R58)) -> 1349210.9 | ... T55: =+IF(T53<0,MIN(T56:T58),MAX(T56:T58)) -> 1487505 | W55: =+SUM(K55:T55) -> 11526321
F56: Fix minimum lease | K56: =+K57+K53 -> 510100 | L56: =+L57+L53 -> 940800 | M56: =+M57+M53 -> 1008000 | N56: =+N57+N53 -> 1038240 | O56: =+O57+O53 -> 1069387.2 | P56: =+P57+P53 -> 1101468.8 | Q56: =+Q57+Q53 -> 1134512.9 | R56: =+R57+R53 -> 1168548.3 | ... T56: =+T57+T53 -> 1239712.9
F57: Fix minimum lease | K57: =+K21*K36*12 -> 873600 | L57: =+L21*L36*12 -> 940800 | M57: =+M21*M36*12 -> 1008000 | N57: =+N21*N36*12 -> 1038240 | O57: =+O21*O36*12 -> 1069387.2 | P57: =+P21*P36*12 -> 1101468.8 | Q57: =+Q21*Q36*12 -> 1134512.9 | R57: =+R21*R36*12 -> 1168548.3 | ... T57: =+T21*T36*12 -> 1239712.9
F58: Variable lease | K58: =+(K24*(K48+K50+K51))+(K49*$K$25) -> 803107.33 | L58: =+L24*(L48+L50+L51)+(L49*$K$25) -> 911007.4 | M58: =+M24*(M48+M50+M51)+(M49*$K$25) -> 1034309.1 | N58: =+N24*(N48+N50+N51)+(N49*$K$25) -> 1109999.2 | O58: =+O24*(O48+O50+O51)+(O49*$K$25) -> 1165499.1 | P58: =+P24*(P48+P50+P51)+(P49*$K$25) -> 1223774.1 | Q58: =+Q24*(Q48+Q50+Q51)+(Q49*$K$25) -> 1288451.8 | R58: =+R24*(R48+R50+R51)+(R49*$K$25) -> 1349210.9 | S58: =+S24*(S48+S50+S51)+(S49*$K$25) -> 1416671.5 | T58: =+T24*(T48+T50+T51)+(T49*$K$25) -> 1487505
F62: Total nights sold | H62: =+K36*K35*K34 -> 15534.4
E64: Employees | F64: Expenses | H64: Monthly | K64: =+K65+K66+K70+K74+K79+K90+K94+K95+K97+K98+K101 -> 1165698.3 | L64: =+L65+L66+L70+L74+L79+L90+L94+L95+L97+L98+L101 -> 1200669.3 | M64: =+M65+M66+M70+M74+M79+M90+M94+M95+M97+M98+M101 -> 1236689.3 | N64: =+N65+N66+N70+N74+N79+N90+N94+N95+N97+N98+N101 -> 1273790 | O64: =+O65+O66+O70+O74+O79+O90+O94+O95+O97+O98+O101 -> 1312003.7 | P64: =+P65+P66+P70+P74+P79+P90+P94+P95+P97+P98+P101 -> 1351363.8 | Q64: =+Q65+Q66+Q70+Q74+Q79+Q90+Q94+Q95+Q97+Q98+Q101 -> 1391904.7 | R64: =+R65+R66+R70+R74+R79+R90+R94+R95+R97+R98+R101 -> 1433661.9 | ... T64: =+T65+T66+T70+T74+T79+T90+T94+T95+T97+T98+T101 -> 1520971.9 | W64: =+SUM(K64:T64) -> 13363425 | X64: =+K64/K47 -> 0.51410661
E65: 1 | F65: Asset Manager | H65: 2750 | I65: N | K65: =+$H65*$E65*12 -> 33000 | L65: =+K65*(1+$H$27) -> 33990 | M65: =+L65*(1+$H$27) -> 35009.7 | N65: =+M65*(1+$H$27) -> 36059.991 | O65: =+N65*(1+$H$27) -> 37141.791 | P65: =+O65*(1+$H$27) -> 38256.044 | Q65: =+P65*(1+$H$27) -> 39403.726 | R65: =+Q65*(1+$H$27) -> 40585.838 | S65: =+R65*(1+$H$27) -> 41803.413 | T65: =+S65*(1+$H$27) -> 43057.515
A66: N | B66: NOMINAL | F66: Cleaning | K66: =+SUM(K67:K69) -> 286841.28 | L66: =+K66*(1+$H$27) -> 295446.52 | M66: =+L66*(1+$H$27) -> 304309.91 | N66: =+M66*(1+$H$27) -> 313439.21 | O66: =+N66*(1+$H$27) -> 322842.39 | P66: =+O66*(1+$H$27) -> 332527.66 | Q66: =+P66*(1+$H$27) -> 342503.49 | R66: =+Q66*(1+$H$27) -> 352778.59 | S66: =+R66*(1+$H$27) -> 363361.95 | T66: =+S66*(1+$H$27) -> 374262.81
A67: W | B67: WEIGHTS/REV | E67: 1 | F67: Housekeeper Payroll | H67: 2350 | I67: N | K67: =+$H67*$E67*12 -> 28200 | L67: =+K67*(1+$H$27) -> 29046 | M67: =+L67*(1+$H$27) -> 29917.38 | N67: =+M67*(1+$H$27) -> 30814.901 | O67: =+N67*(1+$H$27) -> 31739.348 | P67: =+O67*(1+$H$27) -> 32691.529 | Q67: =+P67*(1+$H$27) -> 33672.275 | R67: =+Q67*(1+$H$27) -> 34682.443 | S67: =+R67*(1+$H$27) -> 35722.916 | T67: =+S67*(1+$H$27) -> 36794.604
A68: R | B68: RATIOS | E68: 10 | F68: Cleaning cost payroll | H68: 2000 | I68: N | K68: =+$H68*$E68*12 -> 240000 | L68: =+K68*(1+$H$27) -> 247200 | M68: =+L68*(1+$H$27) -> 254616 | N68: =+M68*(1+$H$27) -> 262254.48 | O68: =+N68*(1+$H$27) -> 270122.11 | P68: =+O68*(1+$H$27) -> 278225.78 | Q68: =+P68*(1+$H$27) -> 286572.55 | R68: =+Q68*(1+$H$27) -> 295169.73 | S68: =+R68*(1+$H$27) -> 304024.82 | T68: =+S68*(1+$H$27) -> 313145.56
F69: Other cleaning + products | H69: 1.2 | I69: R | K69: =+$H69*$H$62 -> 18641.28 | L69: =+K69*(1+$H$27) -> 19200.518 | M69: =+L69*(1+$H$27) -> 19776.534 | N69: =+M69*(1+$H$27) -> 20369.83 | O69: =+N69*(1+$H$27) -> 20980.925 | P69: =+O69*(1+$H$27) -> 21610.353 | Q69: =+P69*(1+$H$27) -> 22258.663 | R69: =+Q69*(1+$H$27) -> 22926.423 | S69: =+R69*(1+$H$27) -> 23614.216 | T69: =+S69*(1+$H$27) -> 24322.642
F70: Maintenance | K70: =+SUM(K71:K73) -> 37837.04 | L70: =+K70*(1+$H$27) -> 38972.151 | M70: =+L70*(1+$H$27) -> 40141.316 | N70: =+M70*(1+$H$27) -> 41345.555 | O70: =+N70*(1+$H$27) -> 42585.922 | P70: =+O70*(1+$H$27) -> 43863.5 | Q70: =+P70*(1+$H$27) -> 45179.405 | R70: =+Q70*(1+$H$27) -> 46534.787 | S70: =+R70*(1+$H$27) -> 47930.83 | T70: =+S70*(1+$H$27) -> 49368.755
F71: Elevator maintenance | H71: 500 | I71: N | K71: =+H71*12 -> 6000 | L71: =+K71*(1+$H$27) -> 6180 | M71: =+L71*(1+$H$27) -> 6365.4 | N71: =+M71*(1+$H$27) -> 6556.362 | O71: =+N71*(1+$H$27) -> 6753.0529 | P71: =+O71*(1+$H$27) -> 6955.6444 | Q71: =+P71*(1+$H$27) -> 7164.3138 | R71: =+Q71*(1+$H$27) -> 7379.2432 | S71: =+R71*(1+$H$27) -> 7600.6205 | T71: =+S71*(1+$H$27) -> 7828.6391
E72: 1 | F72: Maintenance cost payroll | H72: 2200 | I72: N | K72: =+$H72*$E72*12 -> 26400 | L72: =+K72*(1+$H$27) -> 27192 | M72: =+L72*(1+$H$27) -> 28007.76 | N72: =+M72*(1+$H$27) -> 28847.993 | O72: =+N72*(1+$H$27) -> 29713.433 | P72: =+O72*(1+$H$27) -> 30604.836 | Q72: =+P72*(1+$H$27) -> 31522.981 | R72: =+Q72*(1+$H$27) -> 32468.67 | S72: =+R72*(1+$H$27) -> 33442.73 | T72: =+S72*(1+$H$27) -> 34446.012
F73: Maintenance expenses | H73: 0.35 | I73: R | K73: =+$H73*$H$62 -> 5437.04 | L73: =+K73*(1+$H$27) -> 5600.1512 | M73: =+L73*(1+$H$27) -> 5768.1557 | N73: =+M73*(1+$H$27) -> 5941.2004 | O73: =+N73*(1+$H$27) -> 6119.4364 | P73: =+O73*(1+$H$27) -> 6303.0195 | Q73: =+P73*(1+$H$27) -> 6492.1101 | R73: =+Q73*(1+$H$27) -> 6686.8734 | S73: =+R73*(1+$H$27) -> 6887.4796 | T73: =+S73*(1+$H$27) -> 7094.104
F74: Marketing | K74: =+SUM(K75:K78) -> 70789.631 | L74: =+K74*(1+$H$27) -> 72913.32 | M74: =+L74*(1+$H$27) -> 75100.719 | N74: =+M74*(1+$H$27) -> 77353.741 | O74: =+N74*(1+$H$27) -> 79674.353 | P74: =+O74*(1+$H$27) -> 82064.584 | Q74: =+P74*(1+$H$27) -> 84526.521 | R74: =+Q74*(1+$H$27) -> 87062.317 | S74: =+R74*(1+$H$27) -> 89674.186 | T74: =+S74*(1+$H$27) -> 92364.412
F75: Marketing Expenses | H75: 0.025 | I75: W | K75: =+$H75*K$47 -> 56685.631 | L75: =+K75*(1+$H$27) -> 58386.2 | M75: =+L75*(1+$H$27) -> 60137.786 | N75: =+M75*(1+$H$27) -> 61941.919 | O75: =+N75*(1+$H$27) -> 63800.177 | P75: =+O75*(1+$H$27) -> 65714.182 | Q75: =+P75*(1+$H$27) -> 67685.608 | R75: =+Q75*(1+$H$27) -> 69716.176 | S75: =+R75*(1+$H$27) -> 71807.661 | T75: =+S75*(1+$H$27) -> 73961.891
E76: 0.5 | F76: Experience payroll | H76: 2200 | I76: N | K76: =+$H76*$E76*12 -> 13200 | L76: =+K76*(1+$H$27) -> 13596 | M76: =+L76*(1+$H$27) -> 14003.88 | N76: =+M76*(1+$H$27) -> 14423.996 | O76: =+N76*(1+$H$27) -> 14856.716 | P76: =+O76*(1+$H$27) -> 15302.418 | Q76: =+P76*(1+$H$27) -> 15761.49 | R76: =+Q76*(1+$H$27) -> 16234.335 | S76: =+R76*(1+$H$27) -> 16721.365 | T76: =+S76*(1+$H$27) -> 17223.006
F77: Experience expenses | H77: 0.14 | I77: W/Exp. Rev | K77: =+$H77*K$50 -> 504 | L77: =+K77*(1+$H$27) -> 519.12 | M77: =+L77*(1+$H$27) -> 534.6936 | N77: =+M77*(1+$H$27) -> 550.73441 | O77: =+N77*(1+$H$27) -> 567.25644 | P77: =+O77*(1+$H$27) -> 584.27413 | Q77: =+P77*(1+$H$27) -> 601.80236 | R77: =+Q77*(1+$H$27) -> 619.85643 | S77: =+R77*(1+$H$27) -> 638.45212 | T77: =+S77*(1+$H$27) -> 657.60568
F78: Experience insurance | H78: 33.333333 | I78: N | K78: =+H78*12 -> 400 | L78: =+K78*(1+$H$27) -> 412 | M78: =+L78*(1+$H$27) -> 424.36 | N78: =+M78*(1+$H$27) -> 437.0908 | O78: =+N78*(1+$H$27) -> 450.20352 | P78: =+O78*(1+$H$27) -> 463.70963 | Q78: =+P78*(1+$H$27) -> 477.62092 | R78: =+Q78*(1+$H$27) -> 491.94955 | S78: =+R78*(1+$H$27) -> 506.70803 | T78: =+S78*(1+$H$27) -> 521.90927
F79: Others | K79: =+SUM(K80:K89) -> 89838.555 | L79: =+K79*(1+$H$27) -> 92533.712 | M79: =+L79*(1+$H$27) -> 95309.723 | N79: =+M79*(1+$H$27) -> 98169.015 | O79: =+N79*(1+$H$27) -> 101114.09 | P79: =+O79*(1+$H$27) -> 104147.51 | Q79: =+P79*(1+$H$27) -> 107271.93 | R79: =+Q79*(1+$H$27) -> 110490.09 | S79: =+R79*(1+$H$27) -> 113804.79 | T79: =+S79*(1+$H$27) -> 117218.94
F80: Amenities | H80: 0.5 | I80: R | K80: =+$H80*$H$62 -> 7767.2 | L80: =+K80*(1+$H$27) -> 8000.216 | M80: =+L80*(1+$H$27) -> 8240.2225 | N80: =+M80*(1+$H$27) -> 8487.4292 | O80: =+N80*(1+$H$27) -> 8742.052 | P80: =+O80*(1+$H$27) -> 9004.3136 | Q80: =+P80*(1+$H$27) -> 9274.443 | R80: =+Q80*(1+$H$27) -> 9552.6763 | S80: =+R80*(1+$H$27) -> 9839.2566 | T80: =+S80*(1+$H$27) -> 10134.434
F81: Fire System | H81: 65 | I81: N | K81: =+H81*12 -> 780 | L81: =+K81*(1+$H$27) -> 803.4 | M81: =+L81*(1+$H$27) -> 827.502 | N81: =+M81*(1+$H$27) -> 852.32706 | O81: =+N81*(1+$H$27) -> 877.89687 | P81: =+O81*(1+$H$27) -> 904.23378 | Q81: =+P81*(1+$H$27) -> 931.36079 | R81: =+Q81*(1+$H$27) -> 959.30162 | S81: =+R81*(1+$H$27) -> 988.08066 | T81: =+S81*(1+$H$27) -> 1017.7231
F82: Insurances | H82: 1250 | I82: N | K82: =+H82*12 -> 15000 | L82: =+K82*(1+$H$27) -> 15450 | M82: =+L82*(1+$H$27) -> 15913.5 | N82: =+M82*(1+$H$27) -> 16390.905 | O82: =+N82*(1+$H$27) -> 16882.632 | P82: =+O82*(1+$H$27) -> 17389.111 | Q82: =+P82*(1+$H$27) -> 17910.784 | R82: =+Q82*(1+$H$27) -> 18448.108 | S82: =+R82*(1+$H$27) -> 19001.551 | T82: =+S82*(1+$H$27) -> 19571.598
F83: Taxes | H83: 0 | I83: N | K83: =+H83*12 -> 0 | L83: =+K83*(1+$H$27) -> 0 | M83: =+L83*(1+$H$27) -> 0 | N83: =+M83*(1+$H$27) -> 0 | O83: =+N83*(1+$H$27) -> 0 | P83: =+O83*(1+$H$27) -> 0 | Q83: =+P83*(1+$H$27) -> 0 | R83: =+Q83*(1+$H$27) -> 0 | S83: =+R83*(1+$H$27) -> 0 | T83: =+S83*(1+$H$27) -> 0
F84: Duve | H84: 333.33333 | I84: N | K84: =+H84*12 -> 4000 | L84: =+K84*(1+$H$27) -> 4120 | M84: =+L84*(1+$H$27) -> 4243.6 | N84: =+M84*(1+$H$27) -> 4370.908 | O84: =+N84*(1+$H$27) -> 4502.0352 | P84: =+O84*(1+$H$27) -> 4637.0963 | Q84: =+P84*(1+$H$27) -> 4776.2092 | R84: =+Q84*(1+$H$27) -> 4919.4955 | S84: =+R84*(1+$H$27) -> 5067.0803 | T84: =+S84*(1+$H$27) -> 5219.0927
F85: Mews software | H85: =56*14 -> 784 | I85: N | K85: =+H85*12 -> 9408 | L85: =+K85*(1+$H$27) -> 9690.24 | M85: =+L85*(1+$H$27) -> 9980.9472 | N85: =+M85*(1+$H$27) -> 10280.376 | O85: =+N85*(1+$H$27) -> 10588.787 | P85: =+O85*(1+$H$27) -> 10906.45 | Q85: =+P85*(1+$H$27) -> 11233.644 | R85: =+Q85*(1+$H$27) -> 11570.653 | S85: =+R85*(1+$H$27) -> 11917.773 | T85: =+S85*(1+$H$27) -> 12275.306
F86: Stripe fees | H86: 0.02 | I86: W | K86: =+$H86*K$47 -> 45348.505 | L86: =+K86*(1+$H$27) -> 46708.96 | M86: =+L86*(1+$H$27) -> 48110.228 | N86: =+M86*(1+$H$27) -> 49553.535 | O86: =+N86*(1+$H$27) -> 51040.141 | P86: =+O86*(1+$H$27) -> 52571.346 | Q86: =+P86*(1+$H$27) -> 54148.486 | R86: =+Q86*(1+$H$27) -> 55772.941 | S86: =+R86*(1+$H$27) -> 57446.129 | T86: =+S86*(1+$H$27) -> 59169.513
F87: Bank fees | H87: 0.002 | I87: W | K87: =+$H87*K$47 -> 4534.8505 | L87: =+K87*(1+$H$27) -> 4670.896 | M87: =+L87*(1+$H$27) -> 4811.0228 | N87: =+M87*(1+$H$27) -> 4955.3535 | O87: =+N87*(1+$H$27) -> 5104.0141 | P87: =+O87*(1+$H$27) -> 5257.1346 | Q87: =+P87*(1+$H$27) -> 5414.8486 | R87: =+Q87*(1+$H$27) -> 5577.2941 | S87: =+R87*(1+$H$27) -> 5744.6129 | T87: =+S87*(1+$H$27) -> 5916.9513
F88: Labour consulting | H88: 166.66667 | I88: N | K88: =+H88*12 -> 2000 | L88: =+K88*(1+$H$27) -> 2060 | M88: =+L88*(1+$H$27) -> 2121.8 | N88: =+M88*(1+$H$27) -> 2185.454 | O88: =+N88*(1+$H$27) -> 2251.0176 | P88: =+O88*(1+$H$27) -> 2318.5481 | Q88: =+P88*(1+$H$27) -> 2388.1046 | R88: =+Q88*(1+$H$27) -> 2459.7477 | S88: =+R88*(1+$H$27) -> 2533.5402 | T88: =+S88*(1+$H$27) -> 2609.5464
F89: Occupational risk prevention | H89: 83.333333 | I89: N | K89: =+H89*12 -> 1000 | L89: =+K89*(1+$H$27) -> 1030 | M89: =+L89*(1+$H$27) -> 1060.9 | N89: =+M89*(1+$H$27) -> 1092.727 | O89: =+N89*(1+$H$27) -> 1125.5088 | P89: =+O89*(1+$H$27) -> 1159.2741 | Q89: =+P89*(1+$H$27) -> 1194.0523 | R89: =+Q89*(1+$H$27) -> 1229.8739 | S89: =+R89*(1+$H$27) -> 1266.7701 | T89: =+S89*(1+$H$27) -> 1304.7732
F90: Supplies | K90: =+SUM(K91:K93) -> 67997.92 | L90: =+K90*(1+$H$27) -> 70037.858 | M90: =+L90*(1+$H$27) -> 72138.993 | N90: =+M90*(1+$H$27) -> 74303.163 | O90: =+N90*(1+$H$27) -> 76532.258 | P90: =+O90*(1+$H$27) -> 78828.226 | Q90: =+P90*(1+$H$27) -> 81193.073 | R90: =+Q90*(1+$H$27) -> 83628.865 | S90: =+R90*(1+$H$27) -> 86137.731 | T90: =+S90*(1+$H$27) -> 88721.863
F91: Lights supply | H91: 3.5 | I91: R | K91: =+$H91*$H$62 -> 54370.4 | L91: =+K91*(1+$H$27) -> 56001.512 | M91: =+L91*(1+$H$27) -> 57681.557 | N91: =+M91*(1+$H$27) -> 59412.004 | O91: =+N91*(1+$H$27) -> 61194.364 | P91: =+O91*(1+$H$27) -> 63030.195 | Q91: =+P91*(1+$H$27) -> 64921.101 | R91: =+Q91*(1+$H$27) -> 66868.734 | S91: =+R91*(1+$H$27) -> 68874.796 | T91: =+S91*(1+$H$27) -> 70941.04
F92: Water supply | H92: 0.8 | I92: R | K92: =+$H92*$H$62 -> 12427.52 | L92: =+K92*(1+$H$27) -> 12800.346 | M92: =+L92*(1+$H$27) -> 13184.356 | N92: =+M92*(1+$H$27) -> 13579.887 | O92: =+N92*(1+$H$27) -> 13987.283 | P92: =+O92*(1+$H$27) -> 14406.902 | Q92: =+P92*(1+$H$27) -> 14839.109 | R92: =+Q92*(1+$H$27) -> 15284.282 | S92: =+R92*(1+$H$27) -> 15742.811 | T92: =+S92*(1+$H$27) -> 16215.095
F93: Wifi and phone supply | H93: 100 | I93: N | K93: =+H93*12 -> 1200 | L93: =+K93*(1+$H$27) -> 1236 | M93: =+L93*(1+$H$27) -> 1273.08 | N93: =+M93*(1+$H$27) -> 1311.2724 | O93: =+N93*(1+$H$27) -> 1350.6106 | P93: =+O93*(1+$H$27) -> 1391.1289 | Q93: =+P93*(1+$H$27) -> 1432.8628 | R93: =+Q93*(1+$H$27) -> 1475.8486 | S93: =+R93*(1+$H$27) -> 1520.1241 | T93: =+S93*(1+$H$27) -> 1565.7278
E94: 5 | F94: Reception | H94: 2300 | I94: N | K94: =+$H94*$E94*12 -> 138000 | L94: =+K94*(1+$H$27) -> 142140 | M94: =+L94*(1+$H$27) -> 146404.2 | N94: =+M94*(1+$H$27) -> 150796.33 | O94: =+N94*(1+$H$27) -> 155320.22 | P94: =+O94*(1+$H$27) -> 159979.82 | Q94: =+P94*(1+$H$27) -> 164779.22 | R94: =+Q94*(1+$H$27) -> 169722.59 | S94: =+R94*(1+$H$27) -> 174814.27 | T94: =+S94*(1+$H$27) -> 180058.7
F95: Bar | K95: =+SUM(K96:K96) -> 76363.636 | L95: =+K95*(1+$H$27) -> 78654.545 | M95: =+L95*(1+$H$27) -> 81014.182 | N95: =+M95*(1+$H$27) -> 83444.607 | O95: =+N95*(1+$H$27) -> 85947.945 | P95: =+O95*(1+$H$27) -> 88526.384 | Q95: =+P95*(1+$H$27) -> 91182.175 | R95: =+Q95*(1+$H$27) -> 93917.641 | S95: =+R95*(1+$H$27) -> 96735.17 | T95: =+S95*(1+$H$27) -> 99637.225
F96: Bartola | H96: 0.68181818 | I96: W/Bart. Rev. | K96: =+$H96*K$49 -> 76363.636 | L96: =+K96*(1+$H$27) -> 78654.545 | M96: =+L96*(1+$H$27) -> 81014.182 | N96: =+M96*(1+$H$27) -> 83444.607 | O96: =+N96*(1+$H$27) -> 85947.945 | P96: =+O96*(1+$H$27) -> 88526.384 | Q96: =+P96*(1+$H$27) -> 91182.175 | R96: =+Q96*(1+$H$27) -> 93917.641 | S96: =+R96*(1+$H$27) -> 96735.17 | T96: =+S96*(1+$H$27) -> 99637.225
F97: Laundry | H97: 4.5 | I97: R | K97: =+$H97*$H$62 -> 69904.8 | L97: =+K97*(1+$H$27) -> 72001.944 | M97: =+L97*(1+$H$27) -> 74162.002 | N97: =+M97*(1+$H$27) -> 76386.862 | O97: =+N97*(1+$H$27) -> 78678.468 | P97: =+O97*(1+$H$27) -> 81038.822 | Q97: =+P97*(1+$H$27) -> 83469.987 | R97: =+Q97*(1+$H$27) -> 85974.087 | S97: =+R97*(1+$H$27) -> 88553.309 | T97: =+S97*(1+$H$27) -> 91209.908
B98: Walk-in | C98: 0.03 | F98: OTA's | K98: =+SUM(K99:K100) -> 265153.91 | L98: =+K98*(1+$H$27) -> 273108.53 | M98: =+L98*(1+$H$27) -> 281301.79 | N98: =+M98*(1+$H$27) -> 289740.84 | O98: =+N98*(1+$H$27) -> 298433.06 | P98: =+O98*(1+$H$27) -> 307386.06 | Q98: =+P98*(1+$H$27) -> 316607.64 | R98: =+Q98*(1+$H$27) -> 326105.87 | S98: =+R98*(1+$H$27) -> 335889.04 | T98: =+S98*(1+$H$27) -> 345965.71
B99: Website | C99: 0.21 | F99: Website | H99: 0.0225 | I99: W/SB REV. | K99: =+(K$48+K$49*$C$100)*C99*H99 -> 10552.556 | L99: =+K99*(1+$H$27) -> 10869.133 | M99: =+L99*(1+$H$27) -> 11195.207 | N99: =+M99*(1+$H$27) -> 11531.063 | O99: =+N99*(1+$H$27) -> 11876.995 | P99: =+O99*(1+$H$27) -> 12233.305 | Q99: =+P99*(1+$H$27) -> 12600.304 | R99: =+Q99*(1+$H$27) -> 12978.313 | S99: =+R99*(1+$H$27) -> 13367.662 | T99: =+S99*(1+$H$27) -> 13768.692
B100: Booking, Expedia, Airbnb | C100: =100%-SUM(C98:C99) -> 0.76 | F100: Booking, Expedia, Airbnb | H100: 0.15 | I100: W/B. REV. | K100: =+(K$48+K$49*$C$100)*C100*H100 -> 254601.36 | L100: =+K100*(1+$H$27) -> 262239.4 | M100: =+L100*(1+$H$27) -> 270106.58 | N100: =+M100*(1+$H$27) -> 278209.78 | O100: =+N100*(1+$H$27) -> 286556.07 | P100: =+O100*(1+$H$27) -> 295152.75 | Q100: =+P100*(1+$H$27) -> 304007.33 | R100: =+Q100*(1+$H$27) -> 313127.55 | S100: =+R100*(1+$H$27) -> 322521.38 | T100: =+S100*(1+$H$27) -> 332197.02
F101: Revenue Manager | K101: =+SUM(K102:K103) -> 29971.528 | L101: =+K101*(1+$H$27) -> 30870.674 | M101: =+L101*(1+$H$27) -> 31796.794 | N101: =+M101*(1+$H$27) -> 32750.698 | O101: =+N101*(1+$H$27) -> 33733.219 | P101: =+O101*(1+$H$27) -> 34745.215 | Q101: =+P101*(1+$H$27) -> 35787.572 | R101: =+Q101*(1+$H$27) -> 36861.199 | S101: =+R101*(1+$H$27) -> 37967.035 | T101: =+S101*(1+$H$27) -> 39106.046
F102: Channel Manager Software | H102: 41.25 | I102: N | K102: =+H102*12 -> 495 | L102: =+K102*(1+$H$27) -> 509.85 | M102: =+L102*(1+$H$27) -> 525.1455 | N102: =+M102*(1+$H$27) -> 540.89987 | O102: =+N102*(1+$H$27) -> 557.12686 | P102: =+O102*(1+$H$27) -> 573.84067 | Q102: =+P102*(1+$H$27) -> 591.05589 | R102: =+Q102*(1+$H$27) -> 608.78756 | S102: =+R102*(1+$H$27) -> 627.05119 | T102: =+S102*(1+$H$27) -> 645.86273
F103: Fees Excellation (Asaf) | H103: 0.013 | I103: W | K103: =+$H103*K$47 -> 29476.528 | L103: =+K103*(1+$H$27) -> 30360.824 | M103: =+L103*(1+$H$27) -> 31271.649 | N103: =+M103*(1+$H$27) -> 32209.798 | O103: =+N103*(1+$H$27) -> 33176.092 | P103: =+O103*(1+$H$27) -> 34171.375 | Q103: =+P103*(1+$H$27) -> 35196.516 | R103: =+Q103*(1+$H$27) -> 36252.411 | S103: =+R103*(1+$H$27) -> 37339.984 | T103: =+S103*(1+$H$27) -> 38460.183
F105: NOI | K105: =+K47-K55-K64 -> 591626.93 | L105: =+L47-L55-L64 -> 358044.95 | M105: =+M47-M55-M64 -> 422819.35 | N105: =+N47-N55-N64 -> 437368.38 | O105: =+O47-O55-O64 -> 484712.6 | P105: =+P47-P55-P64 -> 535188.31 | Q105: =+Q47-Q55-Q64 -> 593995.82 | R105: =+R47-R55-R64 -> 646261.84 | ... T105: =+T47-T55-T64 -> 772144.01 | W105: =+SUM(K105:T105) -> 5549410.4
F107: NOI after inv. | K107: =+K105-K16 -> 228126.93 | L107: =+L105 -> 358044.95 | M107: =+M105 -> 422819.35 | N107: =+N105 -> 437368.38 | O107: =+O105 -> 484712.6 | P107: =+P105 -> 535188.31 | Q107: =+Q105 -> 593995.82 | R107: =+R105 -> 646261.84 | S107: =+S105 -> 707248.17 | T107: =+T105 -> 772144.01 | W107: =+SUM(K107:T107) -> 5185910.4
B109: FF&E Replacement | C109: 0.03 | F109: FF&E Replacement | K109: 0 | L109: =+L47*$C$109 -> 74985.426 | M109: =+M47*$C$109 -> 80814.534 | N109: =+N47*$C$109 -> 84634.726 | O109: =+O47*$C$109 -> 88866.463 | P109: =+P47*$C$109 -> 93309.786 | Q109: =+Q47*$C$109 -> 98230.571 | R109: =+R47*$C$109 -> 102874.04 | S109: =+S47*$C$109 -> 108017.74 | T109: =+T47*$C$109 -> 113418.63
F111: Final FCF | K111: =+K107-K109 -> 228126.93 | L111: =+L107-L109 -> 283059.52 | M111: =+M107-M109 -> 342004.82 | N111: =+N107-N109 -> 352733.66 | O111: =+O107-O109 -> 395846.14 | P111: =+P107-P109 -> 441878.52 | Q111: =+Q107-Q109 -> 495765.25 | R111: =+R107-R109 -> 543387.8 | ... T111: =+T107-T109 -> 658725.39
F114: Impact for Bartola NOI | K114: =+K49/(14.9/1.1) -> 8268.4564 | L114: =+L49/(14.9/1.1) -> 8681.8792 | M114: =+M49/(14.9/1.1) -> 9115.9732 | N114: =+N49/(14.9/1.1) -> 9571.7718 | O114: =+O49/(14.9/1.1) -> 10050.36 | P114: =+P49/(14.9/1.1) -> 10552.878 | Q114: =+Q49/(14.9/1.1) -> 11080.522 | R114: =+R49/(14.9/1.1) -> 11634.548 | ... T114: =+T49/(14.9/1.1) -> 12827.09
F115: Great impact to Experiences P&L
C120: Inv x Space | H120: Units | I120: Inv. x unit | K120: Total inv .
C122: 80000 | F122: Bar-F&B investment | H122: 1 | I122: =+C122 -> 80000 | K122: =+C122*H122 -> 80000
F124: Total investment | K124: =+SUM(K122:K122) -> 80000
F129: Roftop Bar P&L | K129: 2026 | L129: 2027 | M129: 2028 | N129: 2029 | O129: 2030 | P129: 2031 | Q129: 2032 | R129: 2033 | S129: 2034 | T129: 2035
F131: Revenue | K131: =+K132 -> 360000 | L131: =+L132 -> 456000 | M131: =+M132 -> 478800 | N131: =+N132 -> 502740 | O131: =+O132 -> 527877 | P131: =+P132 -> 554270.85 | Q131: =+Q132 -> 581984.39 | R131: =+R132 -> 611083.61 | ... T131: =+T132 -> 673719.68 | W131: 32323594
F132: Rooftop bar | H132: 30000 | K132: =+H132*12 -> 360000 | L132: =38000*12 -> 456000 | M132: =+L132*(1+SUM($H$27:$H$28)) -> 478800 | N132: =+M132*(1+SUM($H$27:$H$28)) -> 502740 | O132: =+N132*(1+SUM($H$27:$H$28)) -> 527877 | P132: =+O132*(1+SUM($H$27:$H$28)) -> 554270.85 | Q132: =+P132*(1+SUM($H$27:$H$28)) -> 581984.39 | R132: =+Q132*(1+SUM($H$27:$H$28)) -> 611083.61 | S132: =+R132*(1+SUM($H$27:$H$28)) -> 641637.79 | T132: =+S132*(1+SUM($H$27:$H$28)) -> 673719.68
F134: Grace-Months | H134: 6 | K134: =-(H138)*H134 -> -18000
F136: Lease to Charming Stay | K136: =+MAX(K138:K139) -> 36000 | L136: =+MAX(L138:L139) -> 37080 | M136: =+MAX(M138:M139) -> 38304 | N136: =+MAX(N138:N139) -> 40219.2 | O136: =+MAX(O138:O139) -> 42230.16 | P136: =+MAX(P138:P139) -> 44341.668 | Q136: =+MAX(Q138:Q139) -> 46558.751 | R136: =+MAX(R138:R139) -> 48886.689 | ... T136: =+MAX(T138:T139) -> 53897.575 | U136: =+U137+U134 -> 0
F137: Lease to Charming Stay | K137: =+K138 -> 36000 | L137: =+IF(L132<0,MIN(L138:L140),MAX(L138:L140)) -> 37080 | M137: =+IF(M132<0,MIN(M138:M140),MAX(M138:M140)) -> 38304 | N137: =+IF(N132<0,MIN(N138:N140),MAX(N138:N140)) -> 40219.2 | O137: =+IF(O132<0,MIN(O138:O140),MAX(O138:O140)) -> 42230.16 | P137: =+IF(P132<0,MIN(P138:P140),MAX(P138:P140)) -> 44341.668 | Q137: =+IF(Q132<0,MIN(Q138:Q140),MAX(Q138:Q140)) -> 46558.751 | R137: =+IF(R132<0,MIN(R138:R140),MAX(R138:R140)) -> 48886.689 | S137: =+IF(S132<0,MIN(S138:S140),MAX(S138:S140)) -> 51331.023 | T137: =+IF(T132<0,MIN(T138:T140),MAX(T138:T140)) -> 53897.575
F138: Rooftop bar rent | H138: 3000 | K138: =+$H138*12 -> 36000 | L138: =+K138*(1+$H$27) -> 37080 | M138: =+L138*(1+$H$27) -> 38192.4 | N138: =+M138*(1+$H$27) -> 39338.172 | O138: =+N138*(1+$H$27) -> 40518.317 | P138: =+O138*(1+$H$27) -> 41733.867 | Q138: =+P138*(1+$H$27) -> 42985.883 | R138: =+Q138*(1+$H$27) -> 44275.459 | S138: =+R138*(1+$H$27) -> 45603.723 | T138: =+S138*(1+$H$27) -> 46971.835
F139: Variable lease | H139: 0.08 | K139: =+K131*$H$139 -> 28800 | L139: =+L131*$H$139 -> 36480 | M139: =+M131*$H$139 -> 38304 | N139: =+N131*$H$139 -> 40219.2 | O139: =+O131*$H$139 -> 42230.16 | P139: =+P131*$H$139 -> 44341.668 | Q139: =+Q131*$H$139 -> 46558.751 | R139: =+R131*$H$139 -> 48886.689 | ... T139: =+T131*$H$139 -> 53897.575
F145: Expenses | K145: =+SUM(K146:K148) -> 399600 | L145: =+K145*(1+$H$27) -> 411588 | M145: =+L145*(1+$H$27) -> 423935.64 | N145: =+M145*(1+$H$27) -> 436653.71 | O145: =+N145*(1+$H$27) -> 449753.32 | P145: =+O145*(1+$H$27) -> 463245.92 | Q145: =+P145*(1+$H$27) -> 477143.3 | R145: =+Q145*(1+$H$27) -> 491457.6 | S145: =+R145*(1+$H$27) -> 506201.32 | T145: =+S145*(1+$H$27) -> 521387.36
...

Sheet FORM
B2: Hospitality form
B4: Building type | C4: TA | E4: FORMULADO | F4: He añadido un if que afecta al lease y a las expenses
B5: Buildable m2 | C5: 483 | E5: FORMULADO
B6: Building status | C6: Partially renovated | E6: FORMULADO | F6: Añadir una fórmula en que tengas que poner x hardcost por m2, x softcost por m2 según esta respuesta. Y en caso de que sea not built el coste de construcción m2 depende de la localización, y habría que preguntarle a chatgpt
B7: Purchase price | C7: 2500000
B8: Exact location | C8: "Based on client"
B9: Construction project | C9: No | E9: PDTE | F9: YES, NO
B11: Bank loan needed | C11: Yes | E11: FORMULADO | F11: YES, NO | Q11: No
B12: Expected loan start date | C12: 46753 | E12: FORMULADO
B14: Operation
B15: Management/Lease | C15: Management | E15: FORMULADO | F15: Management, Lease (poner una explicación clara de cada una)
B18: Exit strategy
B19: Exit year | C19: 2030 | E19: FORMULADO | F19: NO, 2028, 2029, 2030…

Sheet Projections
K3: 2026 | L3: 2027 | M3: 2028 | N3: 2029 | O3: 2030 | P3: 2031 | Q3: 2032 | R3: 2033 | S3: 2034 | T3: 2035
F4: Inversión inicial
F5: Distribución de la compra en años | K5: 0.15 | L5: 0 | M5: 0.85 | N5: 0 | O5: 0 | P5: 0 | Q5: 0 | R5: 0 | S5: 0 | T5: 0
F6: Distribución Hard cost, Soft cost y FF&E | K6: 0 | L6: 0 | M6: 1 | N6: 0 | O6: 0 | P6: 0 | Q6: 0 | R6: 0 | S6: 0 | T6: 0
F12: Inversión inicial | K12: 2026 | L12: 2027 | M12: 2028 | N12: 2029 | O12: 2030 | P12: 2031 | Q12: 2032 | R12: 2033 | S12: 2034 | T12: 2035
F14: Compra | I14: Inv. Total
F15: Precio de compra | I15: =-FORM!C7 -> -2500000 | K15: =+K$5*$I15 -> -375000 | L15: =+L$5*$I15 -> 0 | M15: =+M$5*$I15 -> -2125000 | N15: =+N5*$I15 -> 0 | O15: =+O5*$I15 -> 0 | P15: =+P5*$I15 -> 0 | Q15: =+Q5*$I15 -> 0 | R15: =+R5*$I15 -> 0 | S15: =+S5*$I15 -> 0 | T15: =+T5*$I15 -> 0
B16: 0.012 | F16: ITP | I16: =+$I$15*$B$16 -> -30000 | K16: =+I16 -> -30000 | L16: 0 | M16: 0 | N16: 0 | O16: 0 | P16: 0 | Q16: 0 | R16: 0 | S16: 0 | T16: 0
B17: 0.005 | F17: Abogados | I17: =+$I$15*$B$17 -> -12500 | K17: =+I17 -> -12500 | L17: 0 | M17: 0 | N17: 0 | O17: 0 | P17: 0 | Q17: 0 | R17: 0 | S17: 0 | T17: 0
B18: 0.0023 | F18: Notaría | I18: =+$I$15*$B$18 -> -5750 | K18: =+I18 -> -5750 | L18: 0 | M18: 0 | N18: 0 | O18: 0 | P18: 0 | Q18: 0 | R18: 0 | S18: 0 | T18: 0
B20: sqm | C20: €/sqm
F21: Desarrollo | G21: sqm | H21: €/sqm | I21: Inv. Total
B22: =+FORM!C5 -> 483 | C22: =-IF(FORM!C6="Renovated", 0, IF(FORM!C6="Partially renovated",0.5 * IFERROR(VLOOKUP(IFERROR(VLOOKUP(FORM!$C$4,Table1[#All], 2, FALSE), ""), PEM!$A$1:$F$14, 6, FALSE), 0), IF(OR(FORM!C6="Pending to be renovated", FORM!C6="Not built"),IFERROR(VLOOKUP(IFERROR(VLOOKUP(FORM!$C$4,Table1[#All], 2, FALSE),""), PEM!$A$1:$F$14, 6, FALSE), 0), ""))) -> -623.81475 | F22: Hard cost | G22: =+B22 -> 483 | H22: =+C22 -> -623.81475 | I22: =+G22*H22 -> -301302.52 | K22: =+K$6*$I22 -> 0 | L22: =+L$6*$I22 -> 0 | M22: =+M$6*$I22 -> -301302.52 | N22: =+N$6*$I22 -> 0 | O22: =+O$6*$I22 -> 0 | P22: =+P$6*$I22 -> 0 | Q22: =+Q$6*$I22 -> 0 | R22: =+R$6*$I22 -> 0 | S22: =+S$6*$I22 -> 0 | T22: =+T$6*$H22 -> 0
A23: Soft cost | B23: 0.17 | F23: Soft cost | G23: =+G22 -> 483 | H23: =+C22*B23 -> -106.04851 | I23: =+G23*H23 -> -51221.429 | K23: =+K$6*$I23 -> 0 | L23: =+L$6*$I23 -> 0 | M23: =+M$6*$I23 -> -51221.429 | N23: =+N$6*$I23 -> 0 | O23: =+O$6*$I23 -> 0 | P23: =+P$6*$I23 -> 0 | Q23: =+Q$6*$I23 -> 0 | R23: =+R$6*$I23 -> 0 | ... T23: =+T$6*$I23 -> 0
A24: FF&E x apt | B24: -12000 | F24: FF&E | H24: =+K64 -> 10 | I24: =+B24*H24 -> -120000 | K24: =+K$6*$I24 -> 0 | L24: =+L$6*$I24 -> 0 | M24: =+M$6*$I24 -> -120000 | N24: =+N$6*$I24 -> 0 | O24: =+O$6*$I24 -> 0 | P24: =+P$6*$I24 -> 0 | Q24: =+Q$6*$I24 -> 0 | R24: =+R$6*$I24 -> 0 | ... T24: =+T$6*$I24 -> 0
A25: Rooms/Units | B25: =+ROUNDDOWN(_xlfn.IFS( FORM!C4 = "3 star Hotel", -C22 / Sizes!D3,FORM!C4 = "4 star Hotel", -C22 /Sizes!D4,FORM!C4 = "Luxury Hotel", -C22 / Sizes!D5,FORM!C4 = "TA", -C22 /Sizes!D6),0) -> 10
F26: TOTAL | K26: =+SUM(K15:K18)+SUM(K22:K24) -> -423250 | L26: =+SUM(L15:L18)+SUM(L22:L24) -> 0 | M26: =+SUM(M15:M18)+SUM(M22:M24) -> -2597524 | N26: =+SUM(N15:N18)+SUM(N22:N24) -> 0 | O26: =+SUM(O15:O18)+SUM(O22:O24) -> 0 | P26: =+SUM(P15:P18)+SUM(P22:P24) -> 0 | Q26: =+SUM(Q15:Q18)+SUM(Q22:Q24) -> 0 | R26: =+SUM(R15:R18)+SUM(R22:R24) -> 0 | ... T26: =+SUM(T15:T18)+SUM(T22:T24) -> 0
F30: Lease | K30: 2026 | L30: 2027 | M30: 2028 | N30: 2029 | O30: 2030 | P30: 2031 | Q30: 2032 | R30: 2033 | S30: 2034 | T30: 2035
H32: Months operating | K32: 12 | L32: 12 | M32: 12 | N32: 12 | O32: 12 | P32: 12 | Q32: 12 | R32: 12 | S32: 12 | T32: 12
B34: Hostels | C34: 0.3 | K34: =+K35*15 -> 0 | L34: =+L35*15 -> 0 | M34: =+M35*15 -> 0 | N34: =+N35*15 -> 0 | O34: =+O35*15 -> 0 | P34: =+P35*15 -> 0 | Q34: =+Q35*15 -> 0 | R34: =+R35*15 -> 0 | ... T34: =+T35*15 -> 0
B35: TA | C35: 0.4 | H35: Fix min. Lease x apartment | K35: =IF(FORM!$C$15="Lease",+IF(FORM!$C$4="Hostel",Projections!$C$34,Projections!$C$35)*(Projections!K72/Projections!K64/K32),0) -> 0 | L35: =IF(FORM!$C$15="Lease",+IF(FORM!$C$4="Hostel",Projections!$C$34,Projections!$C$35)*(Projections!L72/Projections!L64/L32),0) -> 0 | M35: =IF(FORM!$C$15="Lease",+IF(FORM!$C$4="Hostel",Projections!$C$34,Projections!$C$35)*(Projections!M72/Projections!M64/M32),0) -> 0 | N35: =IF(FORM!$C$15="Lease",+IF(FORM!$C$4="Hostel",Projections!$C$34,Projections!$C$35)*(Projections!N72/Projections!N64/N32),0) -> 0 | O35: =IF(FORM!$C$15="Lease",+IF(FORM!$C$4="Hostel",Projections!$C$34,Projections!$C$35)*(Projections!O72/Projections!O64/O32),0) -> 0 | P35: =IF(FORM!$C$15="Lease",+IF(FORM!$C$4="Hostel",Projections!$C$34,Projections!$C$35)*(Projections!P72/Projections!P64/P32),0) -> 0 | Q35: =IF(FORM!$C$15="Lease",+IF(FORM!$C$4="Hostel",Projections!$C$34,Projections!$C$35)*(Projections!Q72/Projections!Q64/Q32),0) -> 0 | R35: =IF(FORM!$C$15="Lease",+IF(FORM!$C$4="Hostel",Projections!$C$34,Projections!$C$35)*(Projections!R72/Projections!R64/R32),0) -> 0 | ... T35: =IF(FORM!$C$15="Lease",+IF(FORM!$C$4="Hostel",Projections!$C$34,Projections!$C$35)*(Projections!T72/Projections!T64/T32),0) -> 0
H36: /rev | K36: =+IFERROR(K83/K72,"") | L36: =+IFERROR(L83/L72,"") | M36: =+IFERROR(M83/M72,"") | N36: =+IFERROR(N83/N72,"") -> 0 | O36: =+IFERROR(O83/O72,"") -> 0 | P36: =+IFERROR(P83/P72,"") | Q36: =+IFERROR(Q83/Q72,"") | R36: =+IFERROR(R83/R72,"") | ... T36: =+IFERROR(T83/T72,"")
H38: Variable lease | K38: 0 | L38: 0 | M38: 0 | N38: 0 | O38: 0 | P38: 0 | Q38: 0 | R38: 0 | S38: 0 | T38: 0
H39: Variable lease (F&B Bartola) | K39: 0 | L39: 0 | M39: 0 | N39: 0 | O39: 0 | P39: 0 | Q39: 0 | R39: 0 | S39: 0 | T39: 0
B40: IPC | C40: 0.025
B41: GROWTH | C41: 0.005
F46: Detalles básicos de operación
F48: Tipo de operación | G48: =+FORM!C4 -> TA
F49: Año de inicio de operación | G49: =+C61 -> 2029
F50: Management agreement o alquiler | G50: =+FORM!C15 -> Management
F51: Número de unidades | G51: =+B25 -> 10
I57: Occupanct | K57: 0 | L57: 0 | M57: 0 | N57: 0.8 | O57: 0.85378082 | P57: 0.85378082 | Q57: 0.85378082 | R57: 0.85378082 | S57: 0.85378082 | T57: 0.85378082
B60: Ops start date | C60: 47119 | F60: P&L | K60: 2026 | L60: 2027 | M60: 2028 | N60: 2029 | O60: 2030 | P60: 2031 | Q60: 2032 | R60: 2033 | S60: 2034 | T60: 2035
B61: Ops start year | C61: =+YEAR(C60) -> 2029
F62: % Average occupancy | K62: =+K57 -> 0 | L62: =+L57 -> 0 | M62: =+M57 -> 0 | N62: =+N57 -> 0.8 | O62: =+O57 -> 0.85378082 | P62: =+P57 -> 0.85378082 | Q62: =+Q57 -> 0.85378082 | R62: =+R57 -> 0.85378082 | ... T62: =+T57 -> 0.85378082 | W62: =+AVERAGE(K57:T57) -> 0.59226849 | X62: Pendiente de link Occ%
F63: Number of opened days | K63: =+IF(K$60<$C$61,0,IF(K60=$C$61,DATE($C$61,12,31)-$C$60+1,DATE(K60,12,31)-DATE(K60,1,1)+1)) -> 0 | L63: =+IF(L$60<$C$61,0,IF(L60=$C$61,DATE($C$61,12,31)-$C$60+1,DATE(L60,12,31)-DATE(L60,1,1)+1)) -> 0 | M63: =+IF(M$60<$C$61,0,IF(M60=$C$61,DATE($C$61,12,31)-$C$60+1,DATE(M60,12,31)-DATE(M60,1,1)+1)) -> 0 | N63: =+IF(N$60<$C$61,0,IF(N60=$C$61,DATE($C$61,12,31)-$C$60+1,DATE(N60,12,31)-DATE(N60,1,1)+1)) -> 365 | O63: =+IF(O$60<$C$61,0,IF(O60=$C$61,DATE($C$61,12,31)-$C$60+1,DATE(O60,12,31)-DATE(O60,1,1)+1)) -> 365 | P63: =+IF(P$60<$C$61,0,IF(P60=$C$61,DATE($C$61,12,31)-$C$60+1,DATE(P60,12,31)-DATE(P60,1,1)+1)) -> 365 | Q63: =+IF(Q$60<$C$61,0,IF(Q60=$C$61,DATE($C$61,12,31)-$C$60+1,DATE(Q60,12,31)-DATE(Q60,1,1)+1)) -> 366 | R63: =+IF(R$60<$C$61,0,IF(R60=$C$61,DATE($C$61,12,31)-$C$60+1,DATE(R60,12,31)-DATE(R60,1,1)+1)) -> 365 | ... T63: =+IF(T$60<$C$61,0,IF(T60=$C$61,DATE($C$61,12,31)-$C$60+1,DATE(T60,12,31)-DATE(T60,1,1)+1)) -> 365
B64: To get it from Chat GPT | F64: Units | K64: =+$B$25 -> 10 | L64: =+$B$25 -> 10 | M64: =+$B$25 -> 10 | N64: =+$B$25 -> 10 | O64: =+$B$25 -> 10 | P64: =+$B$25 -> 10 | Q64: =+$B$25 -> 10 | R64: =+$B$25 -> 10 | ... T64: =+$B$25 -> 10
B65: First year ADR | F65: ADR | H65: Units | K65: =+($H$66*K66+$H$69*K69+$H$68*K68+$H$67*K67)/SUM($H$66:$H$69) -> 155 | L65: =+($H$66*L66+$H$69*L69+$H$68*L68+$H$67*L67)/SUM($H$66:$H$69) -> 159.65 | M65: =+($H$66*M66+$H$69*M69+$H$68*M68+$H$67*M67)/SUM($H$66:$H$69) -> 164.4395 | N65: =+($H$66*N66+$H$69*N69+$H$68*N68+$H$67*N67)/SUM($H$66:$H$69) -> 169.37269 | O65: =+($H$66*O66+$H$69*O69+$H$68*O68+$H$67*O67)/SUM($H$66:$H$69) -> 174.45387 | P65: =+($H$66*P66+$H$69*P69+$H$68*P68+$H$67*P67)/SUM($H$66:$H$69) -> 179.68748 | Q65: =+($H$66*Q66+$H$69*Q69+$H$68*Q68+$H$67*Q67)/SUM($H$66:$H$69) -> 185.07811 | R65: =+($H$66*R66+$H$69*R69+$H$68*R68+$H$67*R67)/SUM($H$66:$H$69) -> 190.63045 | ... T65: =+($H$66*T66+$H$69*T69+$H$68*T68+$H$67*T67)/SUM($H$66:$H$69) -> 202.23984 | W65: =+AVERAGE(K65:T65) -> 177.69013
B66: Room type 1 | C66: 155 | F66: =+B66 -> Room type 1 | H66: =+K64 -> 10 | K66: =+C66 -> 155 | L66: =+K66*(1+SUM($C$40:$C$41)) -> 159.65 | M66: =+L66*(1+SUM($C$40:$C$41)) -> 164.4395 | N66: =+M66*(1+SUM($C$40:$C$41)) -> 169.37269 | O66: =+N66*(1+SUM($C$40:$C$41)) -> 174.45387 | P66: =+O66*(1+SUM($C$40:$C$41)) -> 179.68748 | Q66: =+P66*(1+SUM($C$40:$C$41)) -> 185.07811 | R66: =+Q66*(1+SUM($C$40:$C$41)) -> 190.63045 | S66: =+R66*(1+SUM($C$40:$C$41)) -> 196.34936 | T66: =+S66*(1+SUM($C$40:$C$41)) -> 202.23984
B67: Room type 2 | C67: 0 | F67: =+B67 -> Room type 2 | H67: 0 | K67: =+C67 -> 0 | L67: =+K67*(1+SUM($C$40:$C$41)) -> 0 | M67: =+L67*(1+SUM($C$40:$C$41)) -> 0 | N67: =+M67*(1+SUM($C$40:$C$41)) -> 0 | O67: =+N67*(1+SUM($C$40:$C$41)) -> 0 | P67: =+O67*(1+SUM($C$40:$C$41)) -> 0 | Q67: =+P67*(1+SUM($C$40:$C$41)) -> 0 | R67: =+Q67*(1+SUM($C$40:$C$41)) -> 0 | S67: =+R67*(1+SUM($C$40:$C$41)) -> 0 | T67: =+S67*(1+SUM($C$40:$C$41)) -> 0
B68: Room type 3 | C68: 0 | F68: =+B68 -> Room type 3 | H68: 0 | K68: =+C68 -> 0 | L68: =+K68*(1+SUM($C$40:$C$41)) -> 0 | M68: =+L68*(1+SUM($C$40:$C$41)) -> 0 | N68: =+M68*(1+SUM($C$40:$C$41)) -> 0 | O68: =+N68*(1+SUM($C$40:$C$41)) -> 0 | P68: =+O68*(1+SUM($C$40:$C$41)) -> 0 | Q68: =+P68*(1+SUM($C$40:$C$41)) -> 0 | R68: =+Q68*(1+SUM($C$40:$C$41)) -> 0 | S68: =+R68*(1+SUM($C$40:$C$41)) -> 0 | T68: =+S68*(1+SUM($C$40:$C$41)) -> 0
B69: Room type 4 | C69: 0 | F69: =+B69 -> Room type 4 | H69: 0 | K69: =+C69 -> 0 | L69: =+K69*(1+SUM($C$40:$C$41)) -> 0 | M69: =+L69*(1+SUM($C$40:$C$41)) -> 0 | N69: =+M69*(1+SUM($C$40:$C$41)) -> 0 | O69: =+N69*(1+SUM($C$40:$C$41)) -> 0 | P69: =+O69*(1+SUM($C$40:$C$41)) -> 0 | Q69: =+P69*(1+SUM($C$40:$C$41)) -> 0 | R69: =+Q69*(1+SUM($C$40:$C$41)) -> 0 | S69: =+R69*(1+SUM($C$40:$C$41)) -> 0 | T69: =+S69*(1+SUM($C$40:$C$41)) -> 0
F71: Revenue | K71: =+SUM(K72:K75) -> 0 | L71: =+SUM(L72:L75) -> 0 | M71: =+SUM(M72:M75) -> 0 | N71: =+SUM(N72:N75) -> 519296.65 | O71: =+SUM(O72:O75) -> 570833.11 | P71: =+SUM(P72:P75) -> 0 | Q71: =+SUM(Q72:Q75) -> 0 | R71: =+SUM(R72:R75) -> 0 | ... T71: =+SUM(T72:T75) -> 0 | W71: =+SUM(K71:T71) -> 1090129.8
F72: Bed revenue | K72: =IF(K60<=$C$192,+K57*K63*K64*K65,0) -> 0 | L72: =IF(L60<=$C$192,+L57*L63*L64*L65,0) -> 0 | M72: =IF(M60<=$C$192,+M57*M63*M64*M65,0) -> 0 | N72: =IF(N60<=$C$192,+N57*N63*N64*N65,0) -> 494568.24 | O72: =IF(O60<=$C$192,+O57*O63*O64*O65,0) -> 543650.58 | P72: =IF(P60<=$C$192,+P57*P63*P64*P65,0) -> 0 | Q72: =IF(Q60<=$C$192,+Q57*Q63*Q64*Q65,0) -> 0 | R72: =IF(R60<=$C$192,+R57*R63*R64*R65,0) -> 0 | ... T72: =IF(T60<=$C$192,+T57*T63*T64*T65,0) -> 0
B73: F&B over Rev | C73: =IF(H38>0,_xlfn.SWITCH(FORM!$C$4,"Hostels", Projections!$C$74,"TA", Projections!$C$75,"3 star Hotel",Projections!$C$77,"4 star Hotel", Projections!$C$76,"Luxury Hotel", Projections!$C$78, 0 ), 0) -> 0.05 | F73: F&B | K73: =IF(K60<=$C$192,+K72*$C$73,0) -> 0 | L73: =IF(L60<=$C$192,+L72*$C$73,0) -> 0 | M73: =IF(M60<=$C$192,+M72*$C$73,0) -> 0 | N73: =IF(N60<=$C$192,+N72*$C$73,0) -> 24728.412 | O73: =IF(O60<=$C$192,+O72*$C$73,0) -> 27182.529 | P73: =IF(P60<=$C$192,+P72*$C$73,0) -> 0 | Q73: =IF(Q60<=$C$192,+Q72*$C$73,0) -> 0 | R73: =IF(R60<=$C$192,+R72*$C$73,0) -> 0 | ... T73: =IF(T60<=$C$192,+T72*$C$73,0) -> 0
B74: Hostel | C74: 0.05 | F74: Experiences | K74: =+$C79*12*K$64*(K$63/(DATE(K$60,12,31)-DATE(K$60,1,1)+1))*((1+$C$40)^J$184) -> 0 | L74: =+$C79*12*L65*(L$63/(DATE(L61,12,31)-DATE(L$60,1,1)+1))*((1+$C$40)^K$184) -> 0 | M74: =+$C79*12*M65*(M$63/(DATE(M61,12,31)-DATE(M$60,1,1)+1))*((1+$C$40)^L$184) -> 0 | N74: =+$C79*12*N65*(N$63/(DATE(N61,12,31)-DATE(N$60,1,1)+1))*((1+$C$40)^M$184) -> 0 | O74: =+$C79*12*O65*(O$63/(DATE(O61,12,31)-DATE(O$60,1,1)+1))*((1+$C$40)^N$184) -> 0 | P74: =+$C79*12*P65*(P$63/(DATE(P61,12,31)-DATE(P$60,1,1)+1))*((1+$C$40)^O$184) -> 0 | Q74: =+$C79*12*Q65*(Q$63/(DATE(Q61,12,31)-DATE(Q$60,1,1)+1))*((1+$C$40)^P$184) -> 0 | R74: =+$C79*12*R65*(R$63/(DATE(R61,12,31)-DATE(R$60,1,1)+1))*((1+$C$40)^Q$184) -> 0 | S74: =+$C79*12*S65*(S$63/(DATE(S61,12,31)-DATE(S$60,1,1)+1))*((1+$C$40)^R$184) -> 0 | T74: =+$C79*12*T65*(T$63/(DATE(T61,12,31)-DATE(T$60,1,1)+1))*((1+$C$40)^S$184) -> 0
B75: TA | C75: 0.05 | F75: Parking | K75: =+$C80*12*K$64*(K$63/(DATE(K$60,12,31)-DATE(K$60,1,1)+1))*((1+$C$40)^J$184) -> 0 | L75: =+$C80*12*L66*(L$63/(DATE(L57,12,31)-DATE(L$60,1,1)+1))*((1+$C$40)^K$184) -> 0 | M75: =+$C80*12*M66*(M$63/(DATE(M57,12,31)-DATE(M$60,1,1)+1))*((1+$C$40)^L$184) -> 0 | N75: =+$C80*12*N66*(N$63/(DATE(N57,12,31)-DATE(N$60,1,1)+1))*((1+$C$40)^M$184) -> 0 | O75: =+$C80*12*O66*(O$63/(DATE(O57,12,31)-DATE(O$60,1,1)+1))*((1+$C$40)^N$184) -> 0 | P75: =+$C80*12*P66*(P$63/(DATE(P57,12,31)-DATE(P$60,1,1)+1))*((1+$C$40)^O$184) -> 0 | Q75: =+$C80*12*Q66*(Q$63/(DATE(Q57,12,31)-DATE(Q$60,1,1)+1))*((1+$C$40)^P$184) -> 0 | R75: =+$C80*12*R66*(R$63/(DATE(R57,12,31)-DATE(R$60,1,1)+1))*((1+$C$40)^Q$184) -> 0 | S75: =+$C80*12*S66*(S$63/(DATE(S57,12,31)-DATE(S$60,1,1)+1))*((1+$C$40)^R$184) -> 0 | T75: =+$C80*12*T66*(T$63/(DATE(T57,12,31)-DATE(T$60,1,1)+1))*((1+$C$40)^S$184) -> 0
B76: 3 star Hotel | C76: 0.25
B77: 4 star Hotel | C77: 0.15
B78: Luxury Hotel | C78: 0.2
B79: Exp ov. Rev | C79: 0 | W79: =+SUM(K82:T82) -> 0
B80: Parking ov Rev | C80: 0 | H80: =IFERROR(+K26/(K83/12),"") | K80: =IFERROR(-(K35*K64)*H80,"")
F81: Grace-Months
F82: Lease | K82: =+K83 -> 0 | L82: =+IF(L80<0,MIN(L83:L84),MAX(L83:L84)) -> 0 | M82: =+IF(M80<0,MIN(M83:M84),MAX(M83:M84)) -> 0 | N82: =+IF(N80<0,MIN(N83:N84),MAX(N83:N84)) -> 0 | O82: =+IF(O80<0,MIN(O83:O84),MAX(O83:O84)) -> 0 | P82: =+IF(P80<0,MIN(P83:P84),MAX(P83:P84)) -> 0 | Q82: =+IF(Q80<0,MIN(Q83:Q84),MAX(Q83:Q84)) -> 0 | R82: =+IF(R80<0,MIN(R83:R84),MAX(R83:R84)) -> 0 | S82: =+IF(S80<0,MIN(S83:S84),MAX(S83:S84)) -> 0 | T82: =+IF(T80<0,MIN(T83:T84),MAX(T83:T84)) -> 0
B83: OPEX over Rev | F83: Fix minimum lease | K83: =+K35*K64*K32 -> 0 | L83: =+L35*L64*L32 -> 0 | M83: =+M35*M64*M32 -> 0 | N83: =+N35*N64*N32 -> 0 | O83: =+O35*O64*O32 -> 0 | P83: =+P35*P64*P32 -> 0 | Q83: =+Q35*Q64*Q32 -> 0 | R83: =+R35*R64*R32 -> 0 | ... T83: =+T35*T64*T32 -> 0
B84: Hostel | C84: 0.52 | F84: Variable lease | K84: =+(K38*(K72+K74+K75))+(K73*$K$39) -> 0 | L84: =+(L38*(L72+L74+L75))+(L73*$K$39) -> 0 | M84: =+(M38*(M72+M74+M75))+(M73*$K$39) -> 0 | N84: =+(N38*(N72+N74+N75))+(N73*$K$39) -> 0 | O84: =+(O38*(O72+O74+O75))+(O73*$K$39) -> 0 | P84: =+(P38*(P72+P74+P75))+(P73*$K$39) -> 0 | Q84: =+(Q38*(Q72+Q74+Q75))+(Q73*$K$39) -> 0 | R84: =+(R38*(R72+R74+R75))+(R73*$K$39) -> 0 | ... T84: =+(T38*(T72+T74+T75))+(T73*$K$39) -> 0 | W84: =+SUM(K86:T86) -> 523262.29
B85: TA | C85: 0.48
B86: 3 star Hotel | C86: 0.5 | F86: Expenses | K86: =+K87*K71 -> 0 | L86: =+L87*L71 -> 0 | M86: =+M87*M71 -> 0 | N86: =+N87*N71 -> 249262.39 | O86: =+O87*O71 -> 273999.89 | P86: =+P87*P71 -> 0 | Q86: =+Q87*Q71 -> 0 | R86: =+R87*R71 -> 0 | ... T86: =+T87*T71 -> 0
B87: 4 star Hotel | C87: 0.55 | K87: =IF(K63>0,_xlfn.SWITCH(FORM!$C$4,"Hostels", Projections!$C$84,"TA", Projections!$C$85,"3 star Hotel",Projections!$C$87,"4 star Hotel", Projections!$C$86,"Luxury Hotel", Projections!$C$88, 0 ), 0) -> 0 | L87: =IF(L63>0,_xlfn.SWITCH(FORM!$C$4,"Hostels", Projections!$C$84,"TA", Projections!$C$85,"3 star Hotel",Projections!$C$87,"4 star Hotel", Projections!$C$86,"Luxury Hotel", Projections!$C$88, 0 ), 0) -> 0 | M87: =IF(M63>0,_xlfn.SWITCH(FORM!$C$4,"Hostels", Projections!$C$84,"TA", Projections!$C$85,"3 star Hotel",Projections!$C$87,"4 star Hotel", Projections!$C$86,"Luxury Hotel", Projections!$C$88, 0 ), 0) -> 0 | N87: =IF(N63>0,_xlfn.SWITCH(FORM!$C$4,"Hostels", Projections!$C$84,"TA", Projections!$C$85,"3 star Hotel",Projections!$C$87,"4 star Hotel", Projections!$C$86,"Luxury Hotel", Projections!$C$88, 0 ), 0) -> 0.48 | O87: =IF(O63>0,_xlfn.SWITCH(FORM!$C$4,"Hostels", Projections!$C$84,"TA", Projections!$C$85,"3 star Hotel",Projections!$C$87,"4 star Hotel", Projections!$C$86,"Luxury Hotel", Projections!$C$88, 0 ), 0) -> 0.48 | P87: =IF(P63>0,_xlfn.SWITCH(FORM!$C$4,"Hostels", Projections!$C$84,"TA", Projections!$C$85,"3 star Hotel",Projections!$C$87,"4 star Hotel", Projections!$C$86,"Luxury Hotel", Projections!$C$88, 0 ), 0) -> 0.48 | Q87: =IF(Q63>0,_xlfn.SWITCH(FORM!$C$4,"Hostels", Projections!$C$84,"TA", Projections!$C$85,"3 star Hotel",Projections!$C$87,"4 star Hotel", Projections!$C$86,"Luxury Hotel", Projections!$C$88, 0 ), 0) -> 0.48 | R87: =IF(R63>0,_xlfn.SWITCH(FORM!$C$4,"Hostels", Projections!$C$84,"TA", Projections!$C$85,"3 star Hotel",Projections!$C$87,"4 star Hotel", Projections!$C$86,"Luxury Hotel", Projections!$C$88, 0 ), 0) -> 0.48 | ... T87: =IF(T63>0,_xlfn.SWITCH(FORM!$C$4,"Hostels", Projections!$C$84,"TA", Projections!$C$85,"3 star Hotel",Projections!$C$87,"4 star Hotel", Projections!$C$86,"Luxury Hotel", Projections!$C$88, 0 ), 0) -> 0.48 | W87: =+SUM(K89:T89) -> 566867.48
B88: Luxury Hotel | C88: 0.65
F89: GOP | K89: =+K71-K82-K86 -> 0 | L89: =+L71-L82-L86 -> 0 | M89: =+M71-M82-M86 -> 0 | N89: =+N71-N82-N86 -> 270034.26 | O89: =+O71-O82-O86 -> 296833.22 | P89: =+P71-P82-P86 -> 0 | Q89: =+Q71-Q82-Q86 -> 0 | R89: =+R71-R82-R86 -> 0 | ... T89: =+T71-T82-T86 -> 0
B90: Other | C90: TA | W90: =+SUM(K92:T92) -> 148257.65
A91: Ov. Inc | B91: 0.03 | C91: 0.04
A92: Ov. GOP | B92: 0.1 | C92: 0.2 | F92: Management fee | K92: =+SUM(K93:K94) -> 0 | L92: =+SUM(L93:L94) -> 0 | M92: =+SUM(M93:M94) -> 0 | N92: =+SUM(N93:N94) -> 70624.345 | O92: =+SUM(O93:O94) -> 77633.303 | P92: =+SUM(P93:P94) -> 0 | Q92: =+SUM(Q93:Q94) -> 0 | R92: =+SUM(R93:R94) -> 0 | ... T92: =+SUM(T93:T94) -> 0
F93: % over Incomes | H93: =+IF(FORM!$C$15="Management",IF(FORM!$C$4="TA",Projections!C91,Projections!B91),0) -> 0.04 | K93: =+$H$93*K71 -> 0 | L93: =+$H$93*L71 -> 0 | M93: =+$H$93*M71 -> 0 | N93: =+$H$93*N71 -> 20771.866 | O93: =+$H$93*O71 -> 22833.324 | P93: =+$H$93*P71 -> 0 | Q93: =+$H$93*Q71 -> 0 | R93: =+$H$93*R71 -> 0 | ... T93: =+$H$93*T71 -> 0
F94: % over GOP | H94: =+IF(FORM!$C$15="Management",IF(FORM!$C$4="TA",Projections!C92,Projections!B92),0) -> 0.2 | K94: =+$H$94*(K89-K93) -> 0 | L94: =+$H$94*(L89-L93) -> 0 | M94: =+$H$94*(M89-M93) -> 0 | N94: =+$H$94*(N89-N93) -> 49852.479 | O94: =+$H$94*(O89-O93) -> 54799.979 | P94: =+$H$94*(P89-P93) -> 0 | Q94: =+$H$94*(Q89-Q93) -> 0 | R94: =+$H$94*(R89-R93) -> 0 | ... T94: =+$H$94*(T89-T93) -> 0
W95: =+SUM(K97:T97) -> 418609.83
F97: NOI | K97: =+K89-K92 -> 0 | L97: =+L89-L92 -> 0 | M97: =+M89-M92 -> 0 | N97: =+N89-N92 -> 199409.91 | O97: =+O89-O92 -> 219199.91 | P97: =+P89-P92 -> 0 | Q97: =+Q89-Q92 -> 0 | R97: =+R89-R92 -> 0 | ... T97: =+T89-T92 -> 0
K98: =+IFERROR(K97/K71,"") | L98: =+IFERROR(L97/L71,"") | M98: =+IFERROR(M97/M71,"") | N98: =+IFERROR(N97/N71,"") -> 0.384 | O98: =+IFERROR(O97/O71,"") -> 0.384 | P98: =+IFERROR(P97/P71,"") | Q98: =+IFERROR(Q97/Q71,"") | R98: =+IFERROR(R97/R71,"") | ... T98: =+IFERROR(T97/T71,"") | W98: =+SUM(K100:T100) -> -4640.1712
F100: NOI after inv. | K100: =+K97+K26 -> -423250 | L100: =+L97 -> 0 | M100: =+M97 -> 0 | N100: =+N97 -> 199409.91 | O100: =+O97 -> 219199.91 | P100: =+P97 -> 0 | Q100: =+Q97 -> 0 | R100: =+R97 -> 0 | S100: =+S97 -> 0 | T100: =+T97 -> 0
B102: FF&E Replacement | C102: 0.03 | F102: FF&E Replacement | K102: 0 | L102: =+L71*$C$102 -> 0 | M102: =+M71*$C$102 -> 0 | N102: =+N71*$C$102 -> 15578.9 | O102: =+O71*$C$102 -> 17124.993 | P102: =+P71*$C$102 -> 0 | Q102: =+Q71*$C$102 -> 0 | R102: =+R71*$C$102 -> 0 | S102: =+S71*$C$102 -> 0 | T102: =+T71*$C$102 -> 0
F104: Gross sale | K104: =+IF($C$192=K183,K100/$C$196,0) -> 0 | L104: =+IF($C$192=L183,L100/$C$196,0) -> 0 | M104: =+IF($C$192=M183,M100/$C$196,0) -> 0 | N104: =+IF($C$192=N183,N100/$C$196,0) -> 0 | O104: =+IF($C$192=O183,O100/$C$196,0) -> 3985453 | P104: =+IF($C$192=P183,P100/$C$196,0) -> 0 | Q104: =+IF($C$192=Q183,Q100/$C$196,0) -> 0 | R104: =+IF($C$192=R183,R100/$C$196,0) -> 0 | ... T104: =+IF($C$192=T183,T100/$C$196,0) -> 0
F106: Final FCF | K106: =+K26+K71-K86-K92-K102+K104 -> -423250 | L106: =+L26+L71-L86-L92-L102+L104 -> 0 | M106: =+M26+M71-M86-M92-M102+M104 -> -2597524 | N106: =+N26+N71-N86-N92-N102+N104 -> 183831.01 | O106: =+O26+O71-O86-O92-O102+O104 -> 4187527.9 | P106: =+P26+P71-P86-P92-P102+P104 -> 0 | Q106: =+Q26+Q71-Q86-Q92-Q102+Q104 -> 0 | R106: =+R26+R71-R86-R92-R102+R104 -> 0 | ... T106: =+T26+T71-T86-T92-T102+T104 -> 0
F109: Un- Levered IRR | K109: =+XIRR(K106:T106,K182:T182) -> 0.17617536
C115: Inv x Space | H115: Units | I115: Inv. x unit | K115: Total inv .
C117: 80000 | F117: Bar-F&B investment | H117: 1 | I117: =+C117 -> 80000 | K117: =+C117*H117 -> 80000
F119: Total investment | K119: =+SUM(K117:K117) -> 80000
F124: Roftop Bar P&L | K124: 2026 | L124: 2027 | M124: 2028 | N124: 2029 | O124: 2030 | P124: 2031 | Q124: 2032 | R124: 2033 | S124: 2034 | T124: 2035
F126: Revenue | K126: =+K127 -> 480000 | L126: =+L127 -> 540000 | M126: =+M127 -> 556200 | N126: =+N127 -> 572886 | O126: =+O127 -> 590072.58 | P126: =+P127 -> 607774.76 | Q126: =+Q127 -> 626008 | R126: =+R127 -> 644788.24 | ... T126: =+T127 -> 684055.84 | W126: 32323594
F127: Rooftop bar | H127: 40000 | K127: =+H127*12 -> 480000 | L127: =45000*12 -> 540000 | M127: =+L127*(1+SUM($C$40:$C$41)) -> 556200 | N127: =+M127*(1+SUM($C$40:$C$41)) -> 572886 | O127: =+N127*(1+SUM($C$40:$C$41)) -> 590072.58 | P127: =+O127*(1+SUM($C$40:$C$41)) -> 607774.76 | Q127: =+P127*(1+SUM($C$40:$C$41)) -> 626008 | R127: =+Q127*(1+SUM($C$40:$C$41)) -> 644788.24 | S127: =+R127*(1+SUM($C$40:$C$41)) -> 664131.89 | T127: =+S127*(1+SUM($C$40:$C$41)) -> 684055.84
F129: Grace-Months | H129: 8 | K129: =-(H133)*H129 -> -24000
F131: Lease to Charming Stay | K131: =+MAX(K133:K134) -> 38400 | L131: =+MAX(L133:L134) -> 43200 | M131: =+MAX(M133:M134) -> 44496 | N131: =+MAX(N133:N134) -> 45830.88 | O131: =+MAX(O133:O134) -> 47205.806 | P131: =+MAX(P133:P134) -> 48621.981 | Q131: =+MAX(Q133:Q134) -> 50080.64 | R131: =+MAX(R133:R134) -> 51583.059 | ... T131: =+MAX(T133:T134) -> 54724.468 | U131: =+U132+U129 -> 0
F132: Lease to Charming Stay | K132: =+K133 -> 36000 | L132: =+IF(L127<0,MIN(L133:L135),MAX(L133:L135)) -> 43200 | M132: =+IF(M127<0,MIN(M133:M135),MAX(M133:M135)) -> 44496 | N132: =+IF(N127<0,MIN(N133:N135),MAX(N133:N135)) -> 45830.88 | O132: =+IF(O127<0,MIN(O133:O135),MAX(O133:O135)) -> 47205.806 | P132: =+IF(P127<0,MIN(P133:P135),MAX(P133:P135)) -> 48621.981 | Q132: =+IF(Q127<0,MIN(Q133:Q135),MAX(Q133:Q135)) -> 50080.64 | R132: =+IF(R127<0,MIN(R133:R135),MAX(R133:R135)) -> 51583.059 | S132: =+IF(S127<0,MIN(S133:S135),MAX(S133:S135)) -> 53130.551 | T132: =+IF(T127<0,MIN(T133:T135),MAX(T133:T135)) -> 54724.468
F133: Rooftop bar rent | H133: 3000 | K133: =+$H133*12 -> 36000 | L133: =+K133*(1+$C$40) -> 36900 | M133: =+L133*(1+$C$40) -> 37822.5 | N133: =+M133*(1+$C$40) -> 38768.062 | O133: =+N133*(1+$C$40) -> 39737.264 | P133: =+O133*(1+$C$40) -> 40730.696 | Q133: =+P133*(1+$C$40) -> 41748.963 | R133: =+Q133*(1+$C$40) -> 42792.687 | S133: =+R133*(1+$C$40) -> 43862.504 | T133: =+S133*(1+$C$40) -> 44959.067
F134: Variable lease | H134: 0.08 | K134: =+K126*$H$134 -> 38400 | L134: =+L126*$H$134 -> 43200 | M134: =+M126*$H$134 -> 44496 | N134: =+N126*$H$134 -> 45830.88 | O134: =+O126*$H$134 -> 47205.806 | P134: =+P126*$H$134 -> 48621.981 | Q134: =+Q126*$H$134 -> 50080.64 | R134: =+R126*$H$134 -> 51583.059 | ... T134: =+T126*$H$134 -> 54724.468
F140: Expenses | K140: =+SUM(K141:K143) -> 468000 | L140: =+K140*(1+$C$40) -> 479700 | M140: =+L140*(1+$C$40) -> 491692.5 | N140: =+M140*(1+$C$40) -> 503984.81 | O140: =+N140*(1+$C$40) -> 516584.43 | P140: =+O140*(1+$C$40) -> 529499.04 | Q140: =+P140*(1+$C$40) -> 542736.52 | R140: =+Q140*(1+$C$40) -> 556304.93 | S140: =+R140*(1+$C$40) -> 570212.56 | T140: =+S140*(1+$C$40) -> 584467.87
F141: Rooftop bar rent | H141: 3000 | I141: N | K141: =+$H141*12 -> 36000 | L141: =+K141*(1+$C$40) -> 36900 | M141: =+L141*(1+$C$40) -> 37822.5 | N141: =+M141*(1+$C$40) -> 38768.062 | O141: =+N141*(1+$C$40) -> 39737.264 | P141: =+O141*(1+$C$40) -> 40730.696 | Q141: =+P141*(1+$C$40) -> 41748.963 | R141: =+Q141*(1+$C$40) -> 42792.687 | S141: =+R141*(1+$C$40) -> 43862.504 | T141: =+S141*(1+$C$40) -> 44959.067
E142: 10 | F142: Bartender payroll | H142: 2200 | I142: N | K142: =+$H142*$E142*12 -> 264000 | L142: =+K142*(1+$C$40) -> 270600 | M142: =+L142*(1+$C$40) -> 277365 | N142: =+M142*(1+$C$40) -> 284299.12 | O142: =+N142*(1+$C$40) -> 291406.6 | P142: =+O142*(1+$C$40) -> 298691.77 | Q142: =+P142*(1+$C$40) -> 306159.06 | R142: =+Q142*(1+$C$40) -> 313813.04 | S142: =+R142*(1+$C$40) -> 321658.36 | T142: =+S142*(1+$C$40) -> 329699.82
F143: Rooftop F&B costs | H143: 0.35 | I143: W/Roof rev. | K143: =+$H143*K126 -> 168000 | L143: =+$H143*L126 -> 189000 | M143: =+$H143*M126 -> 194670 | N143: =+$H143*N126 -> 200510.1 | O143: =+$H143*O126 -> 206525.4 | P143: =+$H143*P126 -> 212721.17 | Q143: =+$H143*Q126 -> 219102.8 | R143: =+$H143*R126 -> 225675.88 | ... T143: =+$H143*T126 -> 239419.55
F147: Rooftop Bar NOI | K147: =+K126-K140 -> 12000 | L147: =+L126-L140 -> 60300 | M147: =+M126-M140 -> 64507.5 | N147: =+N126-N140 -> 68901.188 | O147: =+O126-O140 -> 73488.147 | P147: =+P126-P140 -> 78275.714 | Q147: =+Q126-Q140 -> 83271.48 | R147: =+R126-R140 -> 88483.307 | ... T147: =+T126-T140 -> 99587.974 | W147: =+SUM(K147:T147) -> 722734.64
F149: NOI after inv. | K149: =+K147-K119 -> -68000 | L149: =+L147-L119 -> 60300 | M149: =+M147-M119 -> 64507.5 | N149: =+N147-N119 -> 68901.188 | O149: =+O147-O119 -> 73488.147 | P149: =+P147-P119 -> 78275.714 | Q149: =+Q147-Q119 -> 83271.48 | R149: =+R147-R119 -> 88483.307 | ... T149: =+T147-T119 -> 99587.974 | W149: =+SUM(K149:T149) -> 642734.64
F156: NOI (Complete building) | K156: =+K149+K100 -> -491250 | L156: =+L149+L100 -> 60300 | M156: =+M149+M100 -> 64507.5 | N156: =+N149+N100 -> 268311.1 | O156: =+O149+O100 -> 292688.06 | P156: =+P149+P100 -> 78275.714 | Q156: =+Q149+Q100 -> 83271.48 | R156: =+R149+R100 -> 88483.307 | ... T156: =+T149+T100 -> 99587.974
F159: APTS guarantee | K159: =-M35*56*6 -> 0
F160: Rooftop guarantee | K160: =-H133*6 -> -18000
F163: Final FCF (Combined) | K163: =+SUM(K156:K160) -> -509250 | L163: =+SUM(L156:L160) -> 60300 | M163: =+SUM(M156:M160) -> 64507.5 | N163: =+SUM(N156:N160) -> 268311.1 | O163: =+SUM(O156:O160) -> 292688.06 | P163: =+SUM(P156:P160) -> 78275.714 | Q163: =+SUM(Q156:Q160) -> 83271.48 | R163: =+SUM(R156:R160) -> 88483.307 | ... T163: =+SUM(T156:T160) -> 99587.974
K170: 2026 | L170: 2027 | M170: 2028 | N170: 2029 | O170: 2030 | P170: 2031 | Q170: 2032 | R170: 2033 | S170: 2034 | T170: 2035
F171: Lease to Charming Stay | K171: =+MAX(K173,K176)+MAX(K174,K177) -> 945600 | L171: =+MAX(L173,L176)+MAX(L174,L177) -> 1000800 | M171: =+MAX(M173,M176)+MAX(M174,M177) -> 1052496 | N171: =+MAX(N173,N176)+MAX(N174,N177) -> 1084070.9 | O171: =+MAX(O173,O176)+MAX(O174,O177) -> 1116593 | P171: =+MAX(P173,P176)+MAX(P174,P177) -> 1150090.8 | Q171: =+MAX(Q173,Q176)+MAX(Q174,Q177) -> 1184593.5 | R171: =+MAX(R173,R176)+MAX(R174,R177) -> 1220131.3 | ... T171: =+MAX(T173,T176)+MAX(T174,T177) -> 1294437.3
F173: Fix minimum lease- APTS | K173: 907200 | L173: 957600 | M173: 1008000 | N173: 1038240 | O173: 1069387.2 | P173: 1101468.8 | Q173: 1134512.9 | R173: 1168548.3 | S173: 1203604.7 | T173: 1239712.9
F174: Fix minimum lease- Rooftop | K174: =+K133 -> 36000 | L174: =+L133 -> 36900 | M174: =+M133 -> 37822.5 | N174: =+N133 -> 38768.062 | O174: =+O133 -> 39737.264 | P174: =+P133 -> 40730.696 | Q174: =+Q133 -> 41748.963 | R174: =+R133 -> 42792.687 | ... T174: =+T133 -> 44959.067
F176: Variable lease- APTS | K176: =+K84 -> 0 | L176: =+L84 -> 0 | M176: =+M84 -> 0 | N176: =+N84 -> 0 | O176: =+O84 -> 0 | P176: =+P84 -> 0 | Q176: =+Q84 -> 0 | R176: =+R84 -> 0 | ... T176: =+T84 -> 0
...

Sheet PEM
A1: Tipo de construcción | B1: PEM €/m² (calidad media) | C1: PEM €/m² (calidad baja -20%) | D1: PEM €/m² (calidad alta +50%) | E1: PEC €/m² (media ×1.2) | F1: Coste total estimado €/m² (media ×1.35)
A2: Vivienda unifamiliar adosada | B2: 1069.12 | C2: 855.296 | D2: 1603.68 | E2: 1282.944 | F2: 1443.312
A3: Vivienda unifamiliar aislada | B3: 1299.39 | C3: 1039.512 | D3: 1949.085 | E3: 1559.268 | F3: 1754.1765
A4: Vivienda plurifamiliar medianera | B4: 924.17 | C4: 739.336 | D4: 1386.255 | E4: 1109.004 | F4: 1247.6295
A5: Vivienda plurifamiliar aislada | B5: 990.99 | C5: 792.792 | D5: 1486.485 | E5: 1189.188 | F5: 1337.8365
A6: Hotel 5 estrellas | B6: 2379.82 | C6: 1903.856 | D6: 3569.73 | E6: 2855.784 | F6: 3212.757
A7: Hotel 4 estrellas | B7: 1975.82 | C7: 1580.656 | D7: 2963.73 | E7: 2370.984 | F7: 2667.357
A8: Hotel 3 estrellas | B8: 1570.78 | C8: 1256.624 | D8: 2356.17 | E8: 1884.936 | F8: 2120.553
A9: Hotel 2 estrellas | B9: 1428.92 | C9: 1143.136 | D9: 2143.38 | E9: 1714.704 | F9: 1929.042
A10: Hotel 1 estrella | B10: 1287.06 | C10: 1029.648 | D10: 1930.59 | E10: 1544.472 | F10: 1737.531
A11: Pensiones, hostales, albergues | B11: 1092.76 | C11: 874.208 | D11: 1639.14 | E11: 1311.312 | F11: 1475.226
A12: Local comercial con acabados | B12: 1135.94 | C12: 908.752 | D12: 1703.91 | E12: 1363.128 | F12: 1533.519
A13: Oficina equipada edificio exclusivo | B13: 1298.36 | C13: 1038.688 | D13: 1947.54 | E13: 1558.032 | F13: 1752.786
A14: Restaurante | B14: 1428.92 | C14: 1143.136 | D14: 2143.38 | E14: 1714.704 | F14: 1929.042
A17: A | B17: B
A18: Tipo personalizado | B18: Tipo oficial COA
A19: Hostel | B19: Pensiones, hostales, albergues
A20: TA | B20: Vivienda plurifamiliar medianera
A21: 3 star Hotel | B21: Hotel 3 estrellas
A22: 4 star Hotel | B22: Hotel 4 estrellas
A23: Luxury Hotel | B23: Hotel 5 estrellas

Sheet Especerías - Expenses
H2: Months operating | K2: 12 | L2: 12 | M2: 12 | N2: 12 | O2: 12 | P2: 12 | Q2: 12 | R2: 12 | S2: 12 | T2: 12
F4: IPC | H4: 0.025
F5: GROWTH | H5: 0.02
K9: 2026 | L9: 2027 | M9: 2028 | N9: 2029 | O9: 2030 | P9: 2031 | Q9: 2032 | R9: 2033 | S9: 2034 | T9: 2035
F11: % Average occupancy | K11: =+Projections!K57 -> 0 | L11: =+Projections!L57 -> 0 | M11: =+Projections!M57 -> 0 | N11: =+Projections!N57 -> 0.8 | O11: =+Projections!O57 -> 0.85378082 | P11: =+Projections!P57 -> 0.85378082 | Q11: =+Projections!Q57 -> 0.85378082 | R11: =+Projections!R57 -> 0.85378082 | ... T11: =+Projections!T57 -> 0.85378082 | W11: =+AVERAGE(K11:T11) -> 0.59226849
F12: Number of opened days | K12: 365 | L12: 365 | M12: 366 | N12: 365 | O12: 365 | P12: 365 | Q12: 366 | R12: 365 | S12: 365 | T12: 365
F13: Units | K13: =+Projections!K64 -> 10 | L13: =+Projections!L64 -> 10 | M13: =+Projections!M64 -> 10 | N13: =+Projections!N64 -> 10 | O13: =+Projections!O64 -> 10 | P13: =+Projections!P64 -> 10 | Q13: =+Projections!Q64 -> 10 | R13: =+Projections!R64 -> 10 | ... T13: =+Projections!T64 -> 10
F14: ADR | K14: =+Projections!K65 -> 155 | L14: =+Projections!L65 -> 159.65 | M14: =+Projections!M65 -> 164.4395 | N14: =+Projections!N65 -> 169.37269 | O14: =+Projections!O65 -> 174.45387 | P14: =+Projections!P65 -> 179.68748 | Q14: =+Projections!Q65 -> 185.07811 | R14: =+Projections!R65 -> 190.63045 | ... T14: =+Projections!T65 -> 202.23984 | W14: =+AVERAGE(K14:T14) -> 177.69013
F15: Revenue | H15: Monthly | K15: =+SUM(K16:K19) -> 0 | L15: =+SUM(L16:L19) -> 0 | M15: =+SUM(M16:M19) -> 0 | N15: =+SUM(N16:N19) -> 519296.65 | O15: =+SUM(O16:O19) -> 570833.11 | P15: =+SUM(P16:P19) -> 587958.1 | Q15: =+SUM(Q16:Q19) -> 607256.02 | R15: =+SUM(R16:R19) -> 623764.75 | ... T15: =+SUM(T16:T19) -> 661752.03 | W15: =+SUM(K15:T15) -> 4213338.4
F16: Bed revenue | K16: =+K11*K12*K13*K14 -> 0 | L16: =+L11*L12*L13*L14 -> 0 | M16: =+M11*M12*M13*M14 -> 0 | N16: =+N11*N12*N13*N14 -> 494568.24 | O16: =+O11*O12*O13*O14 -> 543650.58 | P16: =+P11*P12*P13*P14 -> 559960.1 | Q16: =+Q11*Q12*Q13*Q14 -> 578339.06 | R16: =+R11*R12*R13*R14 -> 594061.67 | ... T16: =+T11*T12*T13*T14 -> 630240.02
F17: F&B | H17: =+Projections!C73 -> 0.05 | I17: x Apt | K17: =+K11*K12*K13*K14*$H$17 -> 0 | L17: =+L11*L12*L13*L14*$H$17 -> 0 | M17: =+M11*M12*M13*M14*$H$17 -> 0 | N17: =+N11*N12*N13*N14*$H$17 -> 24728.412 | O17: =+O11*O12*O13*O14*$H$17 -> 27182.529 | P17: =+P11*P12*P13*P14*$H$17 -> 27998.005 | Q17: =+Q11*Q12*Q13*Q14*$H$17 -> 28916.953 | R17: =+R11*R12*R13*R14*$H$17 -> 29703.083 | ... T17: =+T11*T12*T13*T14*$H$17 -> 31512.001
F18: Experiences | H18: 0 | K18: =+H18*12 -> 0 | L18: =+K18*(1+SUM($H$4:$H$5)) -> 0 | M18: =+L18*(1+SUM($H$4:$H$5)) -> 0 | N18: =+M18*(1+SUM($H$4:$H$5)) -> 0 | O18: =+N18*(1+SUM($H$4:$H$5)) -> 0 | P18: =+O18*(1+SUM($H$4:$H$5)) -> 0 | Q18: =+P18*(1+SUM($H$4:$H$5)) -> 0 | R18: =+Q18*(1+SUM($H$4:$H$5)) -> 0 | S18: =+R18*(1+SUM($H$4:$H$5)) -> 0 | T18: =+S18*(1+SUM($H$4:$H$5)) -> 0
F19: Parking | H19: 0 | K19: =+H19*12 -> 0 | L19: =+K19*(1+SUM($H$4:$H$5)) -> 0 | M19: =+L19*(1+SUM($H$4:$H$5)) -> 0 | N19: =+M19*(1+SUM($H$4:$H$5)) -> 0 | O19: =+N19*(1+SUM($H$4:$H$5)) -> 0 | P19: =+O19*(1+SUM($H$4:$H$5)) -> 0 | Q19: =+P19*(1+SUM($H$4:$H$5)) -> 0 | R19: =+Q19*(1+SUM($H$4:$H$5)) -> 0 | S19: =+R19*(1+SUM($H$4:$H$5)) -> 0 | T19: =+S19*(1+SUM($H$4:$H$5)) -> 0
F24: Total nights sold | H24: =+K13*K12*K11 -> 0
E26: Employees | F26: Expenses | H26: Monthly | K26: =+K27+K28+K32+K36+K41+K52+K56+K57+K59+K60+K63 -> 376002.29 | L26: =+L27+L28+L32+L36+L41+L52+L56+L57+L59+L60+L63 -> 385402.34 | M26: =+M27+M28+M32+M36+M41+M52+M56+M57+M59+M60+M63 -> 395037.4 | N26: =+N27+N28+N32+N36+N41+N52+N56+N57+N59+N60+N63 -> 404913.34 | O26: =+O27+O28+O32+O36+O41+O52+O56+O57+O59+O60+O63 -> 415036.17 | P26: =+P27+P28+P32+P36+P41+P52+P56+P57+P59+P60+P63 -> 425412.07 | Q26: =+Q27+Q28+Q32+Q36+Q41+Q52+Q56+Q57+Q59+Q60+Q63 -> 436047.38 | R26: =+R27+R28+R32+R36+R41+R52+R56+R57+R59+R60+R63 -> 446948.56 | ... T26: =+T27+T28+T32+T36+T41+T52+T56+T57+T59+T60+T63 -> 469575.33 | W26: =+SUM(K26:T26) -> 4212497.2 | X26: =+K26/K15 -> #DIV/0!
C27: =1/84 -> 0.011904762 | E27: 1 | F27: Asset Manager | H27: 2750 | I27: N | K27: =+$H27*$E27*K2 -> 33000 | L27: =+K27*(1+$H$4) -> 33825 | M27: =+L27*(1+$H$4) -> 34670.625 | N27: =+M27*(1+$H$4) -> 35537.391 | O27: =+N27*(1+$H$4) -> 36425.825 | P27: =+O27*(1+$H$4) -> 37336.471 | Q27: =+P27*(1+$H$4) -> 38269.883 | R27: =+Q27*(1+$H$4) -> 39226.63 | S27: =+R27*(1+$H$4) -> 40207.296 | T27: =+S27*(1+$H$4) -> 41212.478
A28: N | B28: NOMINAL | F28: Cleaning | K28: =+SUM(K29:K31) -> 75342.857 | L28: =+K28*(1+$H$4) -> 77226.429 | M28: =+L28*(1+$H$4) -> 79157.089 | N28: =+M28*(1+$H$4) -> 81136.017 | O28: =+N28*(1+$H$4) -> 83164.417 | P28: =+O28*(1+$H$4) -> 85243.527 | Q28: =+P28*(1+$H$4) -> 87374.616 | R28: =+Q28*(1+$H$4) -> 89558.981 | S28: =+R28*(1+$H$4) -> 91797.955 | T28: =+S28*(1+$H$4) -> 94092.904
A29: W | B29: WEIGHTS/REV | C29: =1/84 -> 0.011904762 | E29: 1 | F29: Housekeeper Payroll | H29: 2350 | I29: N | K29: =+$H29*$E29*K2 -> 28200 | L29: =+K29*(1+$H$4) -> 28905 | M29: =+L29*(1+$H$4) -> 29627.625 | N29: =+M29*(1+$H$4) -> 30368.316 | O29: =+N29*(1+$H$4) -> 31127.524 | P29: =+O29*(1+$H$4) -> 31905.712 | Q29: =+P29*(1+$H$4) -> 32703.354 | R29: =+Q29*(1+$H$4) -> 33520.938 | S29: =+R29*(1+$H$4) -> 34358.962 | T29: =+S29*(1+$H$4) -> 35217.936
A30: R | B30: RATIOS | C30: 0.19642857 | E30: =+C30*K13 -> 1.9642857 | F30: Cleaning cost payroll | H30: 2000 | I30: N | K30: =+$H30*$E30*K2 -> 47142.857 | L30: =+K30*(1+$H$4) -> 48321.429 | M30: =+L30*(1+$H$4) -> 49529.464 | N30: =+M30*(1+$H$4) -> 50767.701 | O30: =+N30*(1+$H$4) -> 52036.893 | P30: =+O30*(1+$H$4) -> 53337.816 | Q30: =+P30*(1+$H$4) -> 54671.261 | R30: =+Q30*(1+$H$4) -> 56038.043 | S30: =+R30*(1+$H$4) -> 57438.994 | T30: =+S30*(1+$H$4) -> 58874.969
F31: Other cleaning + products | H31: 1.2 | I31: R | K31: =+$H31*$H$24 -> 0 | L31: =+K31*(1+$H$4) -> 0 | M31: =+L31*(1+$H$4) -> 0 | N31: =+M31*(1+$H$4) -> 0 | O31: =+N31*(1+$H$4) -> 0 | P31: =+O31*(1+$H$4) -> 0 | Q31: =+P31*(1+$H$4) -> 0 | R31: =+Q31*(1+$H$4) -> 0 | S31: =+R31*(1+$H$4) -> 0 | T31: =+S31*(1+$H$4) -> 0
F32: Maintenance | K32: =+SUM(K33:K35) -> 58800 | L32: =+K32*(1+$H$4) -> 60270 | M32: =+L32*(1+$H$4) -> 61776.75 | N32: =+M32*(1+$H$4) -> 63321.169 | O32: =+N32*(1+$H$4) -> 64904.198 | P32: =+O32*(1+$H$4) -> 66526.803 | Q32: =+P32*(1+$H$4) -> 68189.973 | R32: =+Q32*(1+$H$4) -> 69894.722 | S32: =+R32*(1+$H$4) -> 71642.09 | T32: =+S32*(1+$H$4) -> 73433.143
F33: Elevator maintenance | H33: 500 | I33: N | K33: =+H33*K2 -> 6000 | L33: =+K33*(1+$H$4) -> 6150 | M33: =+L33*(1+$H$4) -> 6303.75 | N33: =+M33*(1+$H$4) -> 6461.3437 | O33: =+N33*(1+$H$4) -> 6622.8773 | P33: =+O33*(1+$H$4) -> 6788.4493 | Q33: =+P33*(1+$H$4) -> 6958.1605 | R33: =+Q33*(1+$H$4) -> 7132.1145 | S33: =+R33*(1+$H$4) -> 7310.4174 | T33: =+S33*(1+$H$4) -> 7493.1778
C34: =1.5/84 -> 0.017857143 | E34: 2 | F34: Maintenance cost payroll | H34: 2200 | I34: N | K34: =+$H34*$E34*K2 -> 52800 | L34: =+K34*(1+$H$4) -> 54120 | M34: =+L34*(1+$H$4) -> 55473 | N34: =+M34*(1+$H$4) -> 56859.825 | O34: =+N34*(1+$H$4) -> 58281.321 | P34: =+O34*(1+$H$4) -> 59738.354 | Q34: =+P34*(1+$H$4) -> 61231.812 | R34: =+Q34*(1+$H$4) -> 62762.608 | S34: =+R34*(1+$H$4) -> 64331.673 | T34: =+S34*(1+$H$4) -> 65939.965
F35: Maintenance expenses | H35: 0.35 | I35: R | K35: =+$H35*$H$24 -> 0 | L35: =+K35*(1+$H$4) -> 0 | M35: =+L35*(1+$H$4) -> 0 | N35: =+M35*(1+$H$4) -> 0 | O35: =+N35*(1+$H$4) -> 0 | P35: =+O35*(1+$H$4) -> 0 | Q35: =+P35*(1+$H$4) -> 0 | R35: =+Q35*(1+$H$4) -> 0 | S35: =+R35*(1+$H$4) -> 0 | T35: =+S35*(1+$H$4) -> 0
F36: Marketing | K36: =+SUM(K37:K40) -> 0 | L36: =+K36*(1+$H$4) -> 0 | M36: =+L36*(1+$H$4) -> 0 | N36: =+M36*(1+$H$4) -> 0 | O36: =+N36*(1+$H$4) -> 0 | P36: =+O36*(1+$H$4) -> 0 | Q36: =+P36*(1+$H$4) -> 0 | R36: =+Q36*(1+$H$4) -> 0 | S36: =+R36*(1+$H$4) -> 0 | T36: =+S36*(1+$H$4) -> 0
F37: Marketing Expenses | H37: 0.025 | I37: W | K37: =+$H37*K$15 -> 0 | L37: =+K37*(1+$H$4) -> 0 | M37: =+L37*(1+$H$4) -> 0 | N37: =+M37*(1+$H$4) -> 0 | O37: =+N37*(1+$H$4) -> 0 | P37: =+O37*(1+$H$4) -> 0 | Q37: =+P37*(1+$H$4) -> 0 | R37: =+Q37*(1+$H$4) -> 0 | S37: =+R37*(1+$H$4) -> 0 | T37: =+S37*(1+$H$4) -> 0
E38: 0 | F38: Experience payroll | H38: 2200 | I38: N | K38: =+$H38*$E38*K2 -> 0 | L38: =+K38*(1+$H$4) -> 0 | M38: =+L38*(1+$H$4) -> 0 | N38: =+M38*(1+$H$4) -> 0 | O38: =+N38*(1+$H$4) -> 0 | P38: =+O38*(1+$H$4) -> 0 | Q38: =+P38*(1+$H$4) -> 0 | R38: =+Q38*(1+$H$4) -> 0 | S38: =+R38*(1+$H$4) -> 0 | T38: =+S38*(1+$H$4) -> 0
F39: Experience expenses | H39: 0.14 | I39: W/Exp. Rev | K39: =+$H39*K$18 -> 0 | L39: =+K39*(1+$H$4) -> 0 | M39: =+L39*(1+$H$4) -> 0 | N39: =+M39*(1+$H$4) -> 0 | O39: =+N39*(1+$H$4) -> 0 | P39: =+O39*(1+$H$4) -> 0 | Q39: =+P39*(1+$H$4) -> 0 | R39: =+Q39*(1+$H$4) -> 0 | S39: =+R39*(1+$H$4) -> 0 | T39: =+S39*(1+$H$4) -> 0
F40: Experience insurance | H40: 0 | I40: N | K40: =+H40*K2 -> 0 | L40: =+K40*(1+$H$4) -> 0 | M40: =+L40*(1+$H$4) -> 0 | N40: =+M40*(1+$H$4) -> 0 | O40: =+N40*(1+$H$4) -> 0 | P40: =+O40*(1+$H$4) -> 0 | Q40: =+P40*(1+$H$4) -> 0 | R40: =+Q40*(1+$H$4) -> 0 | S40: =+R40*(1+$H$4) -> 0 | T40: =+S40*(1+$H$4) -> 0
F41: Others | K41: =+SUM(K42:K51) -> 10364.429 | L41: =+K41*(1+$H$4) -> 10623.539 | M41: =+L41*(1+$H$4) -> 10889.128 | N41: =+M41*(1+$H$4) -> 11161.356 | O41: =+N41*(1+$H$4) -> 11440.39 | P41: =+O41*(1+$H$4) -> 11726.4 | Q41: =+P41*(1+$H$4) -> 12019.56 | R41: =+Q41*(1+$H$4) -> 12320.049 | S41: =+R41*(1+$H$4) -> 12628.05 | T41: =+S41*(1+$H$4) -> 12943.751
F42: Amenities | H42: 0.5 | I42: R | K42: =+$H42*$H$24 -> 0 | L42: =+K42*(1+$H$4) -> 0 | M42: =+L42*(1+$H$4) -> 0 | N42: =+M42*(1+$H$4) -> 0 | O42: =+N42*(1+$H$4) -> 0 | P42: =+O42*(1+$H$4) -> 0 | Q42: =+P42*(1+$H$4) -> 0 | R42: =+Q42*(1+$H$4) -> 0 | S42: =+R42*(1+$H$4) -> 0 | T42: =+S42*(1+$H$4) -> 0
F43: Fire System | H43: 65 | I43: N | K43: =+H43*K2 -> 780 | L43: =+K43*(1+$H$4) -> 799.5 | M43: =+L43*(1+$H$4) -> 819.4875 | N43: =+M43*(1+$H$4) -> 839.97469 | O43: =+N43*(1+$H$4) -> 860.97405 | P43: =+O43*(1+$H$4) -> 882.49841 | Q43: =+P43*(1+$H$4) -> 904.56087 | R43: =+Q43*(1+$H$4) -> 927.17489 | S43: =+R43*(1+$H$4) -> 950.35426 | T43: =+S43*(1+$H$4) -> 974.11312
C44: 22.321429 | F44: Insurances | H44: =+C44*K13 -> 223.21429 | I44: N | K44: =+H44*K2 -> 2678.5714 | L44: =+K44*(1+$H$4) -> 2745.5357 | M44: =+L44*(1+$H$4) -> 2814.1741 | N44: =+M44*(1+$H$4) -> 2884.5285 | O44: =+N44*(1+$H$4) -> 2956.6417 | P44: =+O44*(1+$H$4) -> 3030.5577 | Q44: =+P44*(1+$H$4) -> 3106.3217 | R44: =+Q44*(1+$H$4) -> 3183.9797 | S44: =+R44*(1+$H$4) -> 3263.5792 | T44: =+S44*(1+$H$4) -> 3345.1687
F45: Taxes | H45: 0 | I45: N | K45: =+H45*K2 -> 0 | L45: =+K45*(1+$H$4) -> 0 | M45: =+L45*(1+$H$4) -> 0 | N45: =+M45*(1+$H$4) -> 0 | O45: =+N45*(1+$H$4) -> 0 | P45: =+O45*(1+$H$4) -> 0 | Q45: =+P45*(1+$H$4) -> 0 | R45: =+Q45*(1+$H$4) -> 0 | S45: =+R45*(1+$H$4) -> 0 | T45: =+S45*(1+$H$4) -> 0
C46: 5.952381 | F46: Duve | H46: =+C46*K13 -> 59.52381 | I46: N | K46: =+H46*K2 -> 714.28571 | L46: =+K46*(1+$H$4) -> 732.14286 | M46: =+L46*(1+$H$4) -> 750.44643 | N46: =+M46*(1+$H$4) -> 769.20759 | O46: =+N46*(1+$H$4) -> 788.43778 | P46: =+O46*(1+$H$4) -> 808.14872 | Q46: =+P46*(1+$H$4) -> 828.35244 | R46: =+Q46*(1+$H$4) -> 849.06125 | S46: =+R46*(1+$H$4) -> 870.28778 | T46: =+S46*(1+$H$4) -> 892.04498
C47: 14 | F47: Mews software | H47: =+C47*$K$13 -> 140 | I47: N | K47: =+H47*K2 -> 1680 | L47: =+K47*(1+$H$4) -> 1722 | M47: =+L47*(1+$H$4) -> 1765.05 | N47: =+M47*(1+$H$4) -> 1809.1762 | O47: =+N47*(1+$H$4) -> 1854.4057 | P47: =+O47*(1+$H$4) -> 1900.7658 | Q47: =+P47*(1+$H$4) -> 1948.2849 | R47: =+Q47*(1+$H$4) -> 1996.9921 | S47: =+R47*(1+$H$4) -> 2046.9169 | T47: =+S47*(1+$H$4) -> 2098.0898
F48: Stripe fees | H48: 0.03 | I48: W | K48: =+$H48*K$15 -> 0 | L48: =+K48*(1+$H$4) -> 0 | M48: =+L48*(1+$H$4) -> 0 | N48: =+M48*(1+$H$4) -> 0 | O48: =+N48*(1+$H$4) -> 0 | P48: =+O48*(1+$H$4) -> 0 | Q48: =+P48*(1+$H$4) -> 0 | R48: =+Q48*(1+$H$4) -> 0 | S48: =+R48*(1+$H$4) -> 0 | T48: =+S48*(1+$H$4) -> 0
F49: Bank fees | H49: 0.002 | I49: W | K49: =+$H49*K$15 -> 0 | L49: =+K49*(1+$H$4) -> 0 | M49: =+L49*(1+$H$4) -> 0 | N49: =+M49*(1+$H$4) -> 0 | O49: =+N49*(1+$H$4) -> 0 | P49: =+O49*(1+$H$4) -> 0 | Q49: =+P49*(1+$H$4) -> 0 | R49: =+Q49*(1+$H$4) -> 0 | S49: =+R49*(1+$H$4) -> 0 | T49: =+S49*(1+$H$4) -> 0
C50: 14.5 | F50: Labour consulting | H50: =+C50*(SUM($E$27:$E$66)) -> 187.98214 | I50: N | K50: =+H50*K2 -> 2255.7857 | L50: =+K50*(1+$H$4) -> 2312.1804 | M50: =+L50*(1+$H$4) -> 2369.9849 | N50: =+M50*(1+$H$4) -> 2429.2345 | O50: =+N50*(1+$H$4) -> 2489.9653 | P50: =+O50*(1+$H$4) -> 2552.2145 | Q50: =+P50*(1+$H$4) -> 2616.0198 | R50: =+Q50*(1+$H$4) -> 2681.4203 | S50: =+R50*(1+$H$4) -> 2748.4559 | T50: =+S50*(1+$H$4) -> 2817.1672
F51: Occupational risk prevention | H51: =+H50 -> 187.98214 | I51: N | K51: =+H51*K2 -> 2255.7857 | L51: =+K51*(1+$H$4) -> 2312.1804 | M51: =+L51*(1+$H$4) -> 2369.9849 | N51: =+M51*(1+$H$4) -> 2429.2345 | O51: =+N51*(1+$H$4) -> 2489.9653 | P51: =+O51*(1+$H$4) -> 2552.2145 | Q51: =+P51*(1+$H$4) -> 2616.0198 | R51: =+Q51*(1+$H$4) -> 2681.4203 | S51: =+R51*(1+$H$4) -> 2748.4559 | T51: =+S51*(1+$H$4) -> 2817.1672
F52: Supplies | K52: =+SUM(K53:K55) -> 4800 | L52: =+K52*(1+$H$4) -> 4920 | M52: =+L52*(1+$H$4) -> 5043 | N52: =+M52*(1+$H$4) -> 5169.075 | O52: =+N52*(1+$H$4) -> 5298.3019 | P52: =+O52*(1+$H$4) -> 5430.7594 | Q52: =+P52*(1+$H$4) -> 5566.5284 | R52: =+Q52*(1+$H$4) -> 5705.6916 | S52: =+R52*(1+$H$4) -> 5848.3339 | T52: =+S52*(1+$H$4) -> 5994.5423
F53: Lights supply | H53: 3.5 | I53: R | K53: =+$H53*$H$24 -> 0 | L53: =+K53*(1+$H$4) -> 0 | M53: =+L53*(1+$H$4) -> 0 | N53: =+M53*(1+$H$4) -> 0 | O53: =+N53*(1+$H$4) -> 0 | P53: =+O53*(1+$H$4) -> 0 | Q53: =+P53*(1+$H$4) -> 0 | R53: =+Q53*(1+$H$4) -> 0 | S53: =+R53*(1+$H$4) -> 0 | T53: =+S53*(1+$H$4) -> 0
F54: Water supply | H54: 0.8 | I54: R | K54: =+$H54*$H$24 -> 0 | L54: =+K54*(1+$H$4) -> 0 | M54: =+L54*(1+$H$4) -> 0 | N54: =+M54*(1+$H$4) -> 0 | O54: =+N54*(1+$H$4) -> 0 | P54: =+O54*(1+$H$4) -> 0 | Q54: =+P54*(1+$H$4) -> 0 | R54: =+Q54*(1+$H$4) -> 0 | S54: =+R54*(1+$H$4) -> 0 | T54: =+S54*(1+$H$4) -> 0
F55: Wifi and phone supply | H55: 400 | I55: N | K55: =+H55*K2 -> 4800 | L55: =+K55*(1+$H$4) -> 4920 | M55: =+L55*(1+$H$4) -> 5043 | N55: =+M55*(1+$H$4) -> 5169.075 | O55: =+N55*(1+$H$4) -> 5298.3019 | P55: =+O55*(1+$H$4) -> 5430.7594 | Q55: =+P55*(1+$H$4) -> 5566.5284 | R55: =+Q55*(1+$H$4) -> 5705.6916 | S55: =+R55*(1+$H$4) -> 5848.3339 | T55: =+S55*(1+$H$4) -> 5994.5423
C56: =2.2/29 -> 0.075862069 | E56: 7 | F56: Reception | H56: 2300 | I56: N | K56: =+$H56*$E56*K2 -> 193200 | L56: =+K56*(1+$H$4) -> 198030 | M56: =+L56*(1+$H$4) -> 202980.75 | N56: =+M56*(1+$H$4) -> 208055.27 | O56: =+N56*(1+$H$4) -> 213256.65 | P56: =+O56*(1+$H$4) -> 218588.07 | Q56: =+P56*(1+$H$4) -> 224052.77 | R56: =+Q56*(1+$H$4) -> 229654.09 | S56: =+R56*(1+$H$4) -> 235395.44 | T56: =+S56*(1+$H$4) -> 241280.33
F57: Bar | K57: =+SUM(K58:K58) -> 0 | L57: =+K57*(1+$H$4) -> 0 | M57: =+L57*(1+$H$4) -> 0 | N57: =+M57*(1+$H$4) -> 0 | O57: =+N57*(1+$H$4) -> 0 | P57: =+O57*(1+$H$4) -> 0 | Q57: =+P57*(1+$H$4) -> 0 | R57: =+Q57*(1+$H$4) -> 0 | S57: =+R57*(1+$H$4) -> 0 | T57: =+S57*(1+$H$4) -> 0
F58: Bartola | H58: 0.68181818 | I58: W/Bart. Rev. | K58: =+$H58*K$17 -> 0 | L58: =+K58*(1+$H$4) -> 0 | M58: =+L58*(1+$H$4) -> 0 | N58: =+M58*(1+$H$4) -> 0 | O58: =+N58*(1+$H$4) -> 0 | P58: =+O58*(1+$H$4) -> 0 | Q58: =+P58*(1+$H$4) -> 0 | R58: =+Q58*(1+$H$4) -> 0 | S58: =+R58*(1+$H$4) -> 0 | T58: =+S58*(1+$H$4) -> 0
F59: Laundry | H59: 4.5 | I59: R | K59: =+$H59*$H$24 -> 0 | L59: =+K59*(1+$H$4) -> 0 | M59: =+L59*(1+$H$4) -> 0 | N59: =+M59*(1+$H$4) -> 0 | O59: =+N59*(1+$H$4) -> 0 | P59: =+O59*(1+$H$4) -> 0 | Q59: =+P59*(1+$H$4) -> 0 | R59: =+Q59*(1+$H$4) -> 0 | S59: =+R59*(1+$H$4) -> 0 | T59: =+S59*(1+$H$4) -> 0
B60: Walk-in | C60: 0.03 | F60: OTA's | K60: =+SUM(K61:K62) -> 0 | L60: =+K60*(1+$H$4) -> 0 | M60: =+L60*(1+$H$4) -> 0 | N60: =+M60*(1+$H$4) -> 0 | O60: =+N60*(1+$H$4) -> 0 | P60: =+O60*(1+$H$4) -> 0 | Q60: =+P60*(1+$H$4) -> 0 | R60: =+Q60*(1+$H$4) -> 0 | S60: =+R60*(1+$H$4) -> 0 | T60: =+S60*(1+$H$4) -> 0
B61: Website | C61: 0.21 | F61: Website | H61: 0.0225 | I61: W/SB REV. | K61: =+(K$16+K$17*$C$62)*C61*H61 -> 0 | L61: =+K61*(1+$H$4) -> 0 | M61: =+L61*(1+$H$4) -> 0 | N61: =+M61*(1+$H$4) -> 0 | O61: =+N61*(1+$H$4) -> 0 | P61: =+O61*(1+$H$4) -> 0 | Q61: =+P61*(1+$H$4) -> 0 | R61: =+Q61*(1+$H$4) -> 0 | S61: =+R61*(1+$H$4) -> 0 | T61: =+S61*(1+$H$4) -> 0
B62: Booking, Expedia, Airbnb | C62: =100%-SUM(C60:C61) -> 0.76 | F62: Booking, Expedia, Airbnb | H62: 0.15 | I62: W/B. REV. | K62: =+(K$16+K$17*$C$62)*C62*H62 -> 0 | L62: =+K62*(1+$H$4) -> 0 | M62: =+L62*(1+$H$4) -> 0 | N62: =+M62*(1+$H$4) -> 0 | O62: =+N62*(1+$H$4) -> 0 | P62: =+O62*(1+$H$4) -> 0 | Q62: =+P62*(1+$H$4) -> 0 | R62: =+Q62*(1+$H$4) -> 0 | S62: =+R62*(1+$H$4) -> 0 | T62: =+S62*(1+$H$4) -> 0
F63: Revenue Manager | K63: =+SUM(K64:K65) -> 495 | L63: =+K63*(1+$H$4) -> 507.375 | M63: =+L63*(1+$H$4) -> 520.05937 | N63: =+M63*(1+$H$4) -> 533.06086 | O63: =+N63*(1+$H$4) -> 546.38738 | P63: =+O63*(1+$H$4) -> 560.04707 | Q63: =+P63*(1+$H$4) -> 574.04824 | R63: =+Q63*(1+$H$4) -> 588.39945 | S63: =+R63*(1+$H$4) -> 603.10943 | T63: =+S63*(1+$H$4) -> 618.18717
F64: Channel Manager Software | H64: 41.25 | I64: N | K64: =+H64*K2 -> 495 | L64: =+K64*(1+$H$4) -> 507.375 | M64: =+L64*(1+$H$4) -> 520.05937 | N64: =+M64*(1+$H$4) -> 533.06086 | O64: =+N64*(1+$H$4) -> 546.38738 | P64: =+O64*(1+$H$4) -> 560.04707 | Q64: =+P64*(1+$H$4) -> 574.04824 | R64: =+Q64*(1+$H$4) -> 588.39945 | S64: =+R64*(1+$H$4) -> 603.10943 | T64: =+S64*(1+$H$4) -> 618.18717
F65: Fees Excellation (Asaf) | H65: 0.02 | I65: W | K65: =+$H65*K$15 -> 0 | L65: =+K65*(1+$H$4) -> 0 | M65: =+L65*(1+$H$4) -> 0 | N65: =+M65*(1+$H$4) -> 0 | O65: =+N65*(1+$H$4) -> 0 | P65: =+O65*(1+$H$4) -> 0 | Q65: =+P65*(1+$H$4) -> 0 | R65: =+Q65*(1+$H$4) -> 0 | S65: =+R65*(1+$H$4) -> 0 | T65: =+S65*(1+$H$4) -> 0

Sheet Sheet2
B3: Ratios personal
C5: Real | D5: Units
B6: Recepción Hostels | C6: 10.9 | D6: =57+115 -> 172 | E6: =+C6/D6 -> 0.063372093 | F6: x unit in Hostels
B7: Recepción TA | C7: 4 | D7: =11+15+14+15+29 -> 84 | E7: =+C7/D7 -> 0.047619048 | F7: x apt
B8: Cleaners

Sheet Superfícies
D2: sin zonas comunes
B3: Planta | C3: Apartamento | D3: Superficie construida (m²) | E3: Superficie útil (m²)
B4: Planta baja | C4: local comercial | D4: ?? | E4: ??
B5: 1ª planta | C5: A | D5: 49.2 | E5: 40.77
B6: 1ª planta | C6: B | D6: 59.72 | E6: 47.07
B7: 2ª planta | C7: A | D7: 49.2 | E7: 40.77
B8: 2ª planta | C8: B | D8: 59.72 | E8: 47.07
B9: 3ª planta | C9: A | D9: 49.2 | E9: 40.77
B10: 3ª planta | C10: B | D10: 59.72 | E10: 47.07
B11: Ático | C11: C | D11: 90.4 | E11: 69.27
D12: =SUM(D5:D11) -> 417.16 | E12: =SUM(E5:E11) -> 332.79
B62: Floor | C62: Standard Rooms | D62: Suites | E62: Total Rooms
B63: First Floor | C63: 18 | D63: 0 | E63: 18
B64: Second Floor | C64: 18 | D64: 0 | E64: 18
B65: Third Floor | C65: 14 | D65: 4 | E65: 18
B66: Fourth Floor | C66: 14 | D66: 4 | E66: 18
B67: Penthouse | C67: 0 | D67: 0 | E67: 0
B68: Total | C68: 64 | D68: 8 | E68: 72

Sheet Sizes
A1: Tipo de producto | B1: m2 mínimos por unidad | C1: m2 máximos por unidad | D1: Average m2
A2: Hostel | D2: 11.5
A3: 3 star Hotel | B3: 30 | C3: 35 | D3: =+AVERAGE(B3:C3) -> 32.5
A4: 4 star Hotel | B4: 35 | C4: 45 | D4: =+AVERAGE(B4:C4) -> 40
A5: Luxury Hotel | B5: 45 | C5: 60 | D5: =+AVERAGE(B5:C5) -> 52.5
A6: TA | B6: 50 | C6: 70 | D6: =+AVERAGE(B6:C6) -> 60

Sheet Listings
B2: Building type: | D2: YES/NO
B4: Hostel | D4: Yes
B5: TA | D5: No
B6: 3 star Hotel
B7: 4 star Hotel
B8: Luxury Hotel
B10: Building situation
B12: Renovated
B13: Partially renovated
B14: Pending to be renovated
B15: Not built
B18: Building luxury standards
B20: 1
B21: 2
B22: 3
B23: 4
B24: 5 (5 star hotel level)
B27: Operation
B29: Management
B30: Lease
